[{"stock_id":"1201","last_trade_date":"2004-12-24","open":10.9,"high":12.2,"low":10.9,"close":12.05,"volume":19947315,"week_end_date":"2004-12-24","date":"2004-12-20","ma20":11.2925,"prev_close":11.1,"prev_ma20":11.2575,"cross_above_ma20":true,"ma20_rising":true,"ma20_distance_pct":6.7079920301,"capital_report_date":null,"capital_billion":null,"stock_name":"味全","industry_category":"食品工業","type":"twse"},{"stock_id":"1203","last_trade_date":"2004-12-24","open":10.7,"high":11.25,"low":10.5,"close":11.15,"volume":4890097,"week_end_date":"2004-12-24","date":"2004-12-20","ma20":10.9875,"prev_close":10.8,"prev_ma20":10.9475,"cross_above_ma20":true,"ma20_rising":true,"ma20_distance_pct":1.4789533561,"capital_report_date":null,"capital_billion":null,"stock_name":"味王","industry_category":"食品工業","type":"twse"},{"stock_id":"1225","last_trade_date":"2004-12-24","open":4.7,"high":5.1,"low":4.66,"close":5.0,"volume":1340474,"week_end_date":"2004-12-24","date":"2004-12-20","ma20":4.995,"prev_close":4.73,"prev_ma20":5.0375,"cross_above_ma20":true,"ma20_rising":false,"ma20_distance_pct":0.1001001001,"capital_report_date":null,"capital_billion":null,"stock_name":"福懋油","industry_category":"食品工業","type":"twse"},{"stock_id":"1231","last_trade_date":"2004-12-24","open":9.05,"high":9.5,"low":9.05,"close":9.4,"volume":2117926,"week_end_date":"2004-12-24","date":"2004-12-20","ma20":9.33,"prev_close":9.05,"prev_ma20":9.335,"cross_above_ma20":true,"ma20_rising":false,"ma20_distance_pct":0.7502679528,"capital_report_date":null,"capital_billion":null,"stock_name":"聯華食","industry_category":"食品工業","type":"twse"},{"stock_id":"1234","last_trade_date":"2004-12-24","open":9.95,"high":10.25,"low":9.9,"close":10.2,"volume":1312850,"week_end_date":"2004-12-24","date":"2004-12-20","ma20":10.08,"prev_close":10.0,"prev_ma20":10.0725,"cross_above_ma20":true,"ma20_rising":true,"ma20_distance_pct":1.1904761905,"capital_report_date":null,"capital_billion":null,"stock_name":"黑松","industry_category":"食品工業","type":"twse"},{"stock_id":"1236","last_trade_date":"2004-12-24","open":16.6,"high":16.8,"low":16.4,"close":16.8,"volume":188015,"week_end_date":"2004-12-24","date":"2004-12-20","ma20":16.715,"prev_close":16.6,"prev_ma20":16.64,"cross_above_ma20":true,"ma20_rising":true,"ma20_distance_pct":0.5085252767,"capital_report_date":null,"capital_billion":null,"stock_name":"宏亞","industry_category":"食品工業","type":"twse"},{"stock_id":"1410","last_trade_date":"2004-12-24","open":6.35,"high":6.95,"low":6.15,"close":6.8,"volume":2638625,"week_end_date":"2004-12-24","date":"2004-12-20","ma20":6.4025,"prev_close":6.3,"prev_ma20":6.3625,"cross_above_ma20":true,"ma20_rising":true,"ma20_distance_pct":6.2085122999,"capital_report_date":null,"capital_billion":null,"stock_name":"南染","industry_category":"紡織纖維","type":"twse"},{"stock_id":"1439","last_trade_date":"2004-12-24","open":9.8,"high":10.2,"low":9.8,"close":10.15,"volume":232001,"week_end_date":"2004-12-24","date":"2004-12-20","ma20":10.0775,"prev_close":10.0,"prev_ma20":10.015,"cross_above_ma20":true,"ma20_rising":true,"ma20_distance_pct":0.7194244604,"capital_report_date":null,"capital_billion":null,"stock_name":"雋揚","industry_category":"紡織纖維","type":"twse"},{"stock_id":"1441","last_trade_date":"2004-12-24","open":3.19,"high":3.99,"low":3.19,"close":3.87,"volume":6232493,"week_end_date":"2004-12-24","date":"2004-12-20","ma20":3.479,"prev_close":3.3,"prev_ma20":3.4905,"cross_above_ma20":true,"ma20_rising":false,"ma20_distance_pct":11.2388617419,"capital_report_date":null,"capital_billion":null,"stock_name":"大東","industry_category":"紡織纖維","type":"twse"},{"stock_id":"1445","last_trade_date":"2004-12-24","open":4.96,"high":5.15,"low":4.88,"close":5.15,"volume":1484679,"week_end_date":"2004-12-24","date":"2004-12-20","ma20":5.0345,"prev_close":4.96,"prev_ma20":5.0185,"cross_above_ma20":true,"ma20_rising":true,"ma20_distance_pct":2.2941702254,"capital_report_date":null,"capital_billion":null,"stock_name":"大宇","industry_category":"紡織纖維","type":"twse"},{"stock_id":"1449","last_trade_date":"2004-12-24","open":3.3,"high":3.63,"low":3.25,"close":3.63,"volume":6115418,"week_end_date":"2004-12-24","date":"2004-12-20","ma20":3.4455,"prev_close":3.33,"prev_ma20":3.417,"cross_above_ma20":true,"ma20_rising":true,"ma20_distance_pct":5.3548106226,"capital_report_date":null,"capital_billion":null,"stock_name":"佳和","industry_category":"紡織纖維","type":"twse"},{"stock_id":"1465","last_trade_date":"2004-12-24","open":8.1,"high":8.4,"low":8.05,"close":8.4,"volume":536001,"week_end_date":"2004-12-24","date":"2004-12-20","ma20":8.3025,"prev_close":8.15,"prev_ma20":8.28,"cross_above_ma20":true,"ma20_rising":true,"ma20_distance_pct":1.1743450768,"capital_report_date":null,"capital_billion":null,"stock_name":"偉全","industry_category":"紡織纖維","type":"twse"},{"stock_id":"1473","last_trade_date":"2004-12-24","open":40.0,"high":41.7,"low":40.0,"close":41.7,"volume":418147,"week_end_date":"2004-12-24","date":"2004-12-20","ma20":41.305,"prev_close":40.5,"prev_ma20":41.355,"cross_above_ma20":true,"ma20_rising":false,"ma20_distance_pct":0.95630069,"capital_report_date":null,"capital_billion":null,"stock_name":"台南","industry_category":"紡織纖維","type":"twse"},{"stock_id":"1506","last_trade_date":"2004-12-24","open":6.15,"high":6.85,"low":6.05,"close":6.5,"volume":1892894,"week_end_date":"2004-12-24","date":"2004-12-20","ma20":6.3775,"prev_close":6.2,"prev_ma20":6.375,"cross_above_ma20":true,"ma20_rising":true,"ma20_distance_pct":1.9208153665,"capital_report_date":null,"capital_billion":null,"stock_name":"正道","industry_category":"電機機械","type":"twse"},{"stock_id":"1516","last_trade_date":"2004-12-24","open":6.1,"high":6.7,"low":6.0,"close":6.45,"volume":3923734,"week_end_date":"2004-12-24","date":"2004-12-20","ma20":6.405,"prev_close":6.15,"prev_ma20":6.405,"cross_above_ma20":true,"ma20_rising":false,"ma20_distance_pct":0.7025761124,"capital_report_date":null,"capital_billion":null,"stock_name":"川飛","industry_category":"其他","type":"twse"},{"stock_id":"1519","last_trade_date":"2004-12-24","open":8.75,"high":9.25,"low":8.7,"close":9.25,"volume":1388586,"week_end_date":"2004-12-24","date":"2004-12-20","ma20":8.8975,"prev_close":8.9,"prev_ma20":8.93,"cross_above_ma20":true,"ma20_rising":false,"ma20_distance_pct":3.9617870188,"capital_report_date":null,"capital_billion":null,"stock_name":"華城","industry_category":"電機機械","type":"twse"},{"stock_id":"1527","last_trade_date":"2004-12-24","open":68.0,"high":70.0,"low":68.0,"close":69.0,"volume":1511871,"week_end_date":"2004-12-24","date":"2004-12-20","ma20":68.275,"prev_close":68.0,"prev_ma20":68.025,"cross_above_ma20":true,"ma20_rising":true,"ma20_distance_pct":1.0618820945,"capital_report_date":null,"capital_billion":null,"stock_name":"鑽全","industry_category":"電機機械","type":"twse"},{"stock_id":"1606","last_trade_date":"2004-12-24","open":6.9,"high":7.6,"low":6.9,"close":7.4,"volume":53828143,"week_end_date":"2004-12-24","date":"2004-12-20","ma20":7.345,"prev_close":7.05,"prev_ma20":7.355,"cross_above_ma20":true,"ma20_rising":false,"ma20_distance_pct":0.7488087134,"capital_report_date":null,"capital_billion":null,"stock_name":"歌林","industry_category":"電器電纜","type":"twse"},{"stock_id":"1608","last_trade_date":"2004-12-24","open":8.0,"high":8.6,"low":8.0,"close":8.5,"volume":13194454,"week_end_date":"2004-12-24","date":"2004-12-20","ma20":8.3275,"prev_close":8.2,"prev_ma20":8.2925,"cross_above_ma20":true,"ma20_rising":true,"ma20_distance_pct":2.071450015,"capital_report_date":null,"capital_billion":null,"stock_name":"華榮","industry_category":"電器電纜","type":"twse"},{"stock_id":"2013","last_trade_date":"2004-12-24","open":16.5,"high":17.8,"low":16.4,"close":17.5,"volume":6354411,"week_end_date":"2004-12-24","date":"2004-12-20","ma20":16.91,"prev_close":16.6,"prev_ma20":16.795,"cross_above_ma20":true,"ma20_rising":true,"ma20_distance_pct":3.489059728,"capital_report_date":null,"capital_billion":null,"stock_name":"中鋼構","industry_category":"鋼鐵工業","type":"twse"},{"stock_id":"2027","last_trade_date":"2004-12-24","open":23.4,"high":26.1,"low":23.2,"close":25.2,"volume":56477322,"week_end_date":"2004-12-24","date":"2004-12-20","ma20":25.095,"prev_close":23.8,"prev_ma20":24.88,"cross_above_ma20":true,"ma20_rising":true,"ma20_distance_pct":0.4184100418,"capital_report_date":null,"capital_billion":null,"stock_name":"大成鋼","industry_category":"鋼鐵工業","type":"twse"},{"stock_id":"2028","last_trade_date":"2004-12-24","open":8.65,"high":9.35,"low":8.5,"close":9.2,"volume":16102444,"week_end_date":"2004-12-24","date":"2004-12-20","ma20":8.9275,"prev_close":8.8,"prev_ma20":8.845,"cross_above_ma20":true,"ma20_rising":true,"ma20_distance_pct":3.052366284,"capital_report_date":null,"capital_billion":null,"stock_name":"威致","industry_category":"鋼鐵工業","type":"twse"},{"stock_id":"2030","last_trade_date":"2004-12-24","open":23.7,"high":26.5,"low":23.5,"close":26.4,"volume":54159750,"week_end_date":"2004-12-24","date":"2004-12-20","ma20":24.43,"prev_close":24.0,"prev_ma20":24.035,"cross_above_ma20":true,"ma20_rising":true,"ma20_distance_pct":8.0638559149,"capital_report_date":null,"capital_billion":null,"stock_name":"彰源","industry_category":"鋼鐵工業","type":"twse"},{"stock_id":"2034","last_trade_date":"2004-12-24","open":34.9,"high":37.6,"low":34.1,"close":36.9,"volume":27888686,"week_end_date":"2004-12-24","date":"2004-12-20","ma20":36.335,"prev_close":35.3,"prev_ma20":35.99,"cross_above_ma20":true,"ma20_rising":true,"ma20_distance_pct":1.5549745425,"capital_report_date":null,"capital_billion":null,"stock_name":"允強","industry_category":"鋼鐵工業","type":"twse"},{"stock_id":"2345","last_trade_date":"2004-12-24","open":14.0,"high":15.1,"low":13.9,"close":15.0,"volume":26576907,"week_end_date":"2004-12-24","date":"2004-12-20","ma20":14.53,"prev_close":14.3,"prev_ma20":14.54,"cross_above_ma20":true,"ma20_rising":false,"ma20_distance_pct":3.2346868548,"capital_report_date":null,"capital_billion":null,"stock_name":"智邦","industry_category":"通信網路業","type":"twse"},{"stock_id":"2444","last_trade_date":"2004-12-24","open":7.45,"high":8.3,"low":7.25,"close":8.2,"volume":11166088,"week_end_date":"2004-12-24","date":"2004-12-20","ma20":7.9025,"prev_close":7.45,"prev_ma20":8.0225,"cross_above_ma20":true,"ma20_rising":false,"ma20_distance_pct":3.7646314457,"capital_report_date":null,"capital_billion":null,"stock_name":"兆勁","industry_category":"通信網路業","type":"twse"},{"stock_id":"2480","last_trade_date":"2004-12-24","open":14.75,"high":15.9,"low":14.6,"close":15.6,"volume":9914646,"week_end_date":"2004-12-24","date":"2004-12-20","ma20":15.455,"prev_close":14.9,"prev_ma20":15.495,"cross_above_ma20":true,"ma20_rising":false,"ma20_distance_pct":0.9382076998,"capital_report_date":null,"capital_billion":null,"stock_name":"敦陽科","industry_category":"資訊服務業","type":"twse"},{"stock_id":"2540","last_trade_date":"2004-12-24","open":0.42,"high":0.55,"low":0.41,"close":0.55,"volume":4422445,"week_end_date":"2004-12-24","date":"2004-12-20","ma20":0.523,"prev_close":0.42,"prev_ma20":0.528,"cross_above_ma20":true,"ma20_rising":false,"ma20_distance_pct":5.1625239006,"capital_report_date":null,"capital_billion":null,"stock_name":"愛山林","industry_category":"建材營造","type":"twse"},{"stock_id":"2851","last_trade_date":"2004-12-24","open":12.95,"high":13.35,"low":12.9,"close":13.25,"volume":2505228,"week_end_date":"2004-12-24","date":"2004-12-20","ma20":13.1225,"prev_close":13.05,"prev_ma20":13.085,"cross_above_ma20":true,"ma20_rising":true,"ma20_distance_pct":0.9716136407,"capital_report_date":null,"capital_billion":null,"stock_name":"中再保","industry_category":"金融保險","type":"twse"},{"stock_id":"2882","last_trade_date":"2004-12-24","open":61.5,"high":63.5,"low":61.5,"close":63.5,"volume":40039256,"week_end_date":"2004-12-24","date":"2004-12-20","ma20":62.85,"prev_close":62.5,"prev_ma20":62.5,"cross_above_ma20":true,"ma20_rising":true,"ma20_distance_pct":1.0342084328,"capital_report_date":null,"capital_billion":null,"stock_name":"國泰金","industry_category":"金融保險","type":"twse"},{"stock_id":"3035","last_trade_date":"2004-12-24","open":47.5,"high":49.7,"low":47.5,"close":49.0,"volume":3653936,"week_end_date":"2004-12-24","date":"2004-12-20","ma20":48.94,"prev_close":48.7,"prev_ma20":49.065,"cross_above_ma20":true,"ma20_rising":false,"ma20_distance_pct":0.1225991009,"capital_report_date":null,"capital_billion":null,"stock_name":"智原","industry_category":"半導體業","type":"twse"},{"stock_id":"3047","last_trade_date":"2004-12-24","open":6.25,"high":6.55,"low":6.0,"close":6.45,"volume":2543000,"week_end_date":"2004-12-24","date":"2004-12-20","ma20":6.402,"prev_close":5.95,"prev_ma20":6.452,"cross_above_ma20":true,"ma20_rising":false,"ma20_distance_pct":0.7497656982,"capital_report_date":null,"capital_billion":null,"stock_name":"訊舟","industry_category":"電子工業","type":"twse"},{"stock_id":"3054","last_trade_date":"2004-12-24","open":7.6,"high":9.2,"low":7.55,"close":9.0,"volume":2026469,"week_end_date":"2004-12-24","date":"2004-12-20","ma20":8.8475,"prev_close":8.1,"prev_ma20":8.8475,"cross_above_ma20":true,"ma20_rising":false,"ma20_distance_pct":1.7236507488,"capital_report_date":null,"capital_billion":null,"stock_name":"立萬利","industry_category":"電子工業","type":"twse"},{"stock_id":"3056","last_trade_date":"2004-12-24","open":9.45,"high":9.9,"low":9.2,"close":9.6,"volume":61000,"week_end_date":"2004-12-24","date":"2004-12-20","ma20":9.505,"prev_close":9.5,"prev_ma20":9.5125,"cross_above_ma20":true,"ma20_rising":false,"ma20_distance_pct":0.9994739611,"capital_report_date":null,"capital_billion":null,"stock_name":"富華新","industry_category":"建材營造","type":"twse"},{"stock_id":"4113","last_trade_date":"2004-12-24","open":3.09,"high":3.53,"low":3.09,"close":3.18,"volume":870763,"week_end_date":"2004-12-24","date":"2004-12-20","ma20":3.052,"prev_close":2.89,"prev_ma20":3.283,"cross_above_ma20":true,"ma20_rising":false,"ma20_distance_pct":4.1939711664,"capital_report_date":null,"capital_billion":null,"stock_name":"聯上","industry_category":"建材營造","type":"tpex"},{"stock_id":"4121","last_trade_date":"2004-12-24","open":28.1,"high":30.8,"low":27.8,"close":29.1,"volume":1363932,"week_end_date":"2004-12-24","date":"2004-12-20","ma20":28.5,"prev_close":28.1,"prev_ma20":28.45,"cross_above_ma20":true,"ma20_rising":true,"ma20_distance_pct":2.1052631579,"capital_report_date":null,"capital_billion":null,"stock_name":"優盛","industry_category":"生技醫療業","type":"tpex"},{"stock_id":"4406","last_trade_date":"2004-12-24","open":5.1,"high":5.1,"low":5.1,"close":5.1,"volume":13000,"week_end_date":"2004-12-24","date":"2004-12-20","ma20":5.083,"prev_close":5.0,"prev_ma20":5.0715,"cross_above_ma20":true,"ma20_rising":true,"ma20_distance_pct":0.3344481605,"capital_report_date":null,"capital_billion":null,"stock_name":"新昕纖","industry_category":"紡織纖維","type":"tpex"},{"stock_id":"4420","last_trade_date":"2004-12-24","open":15.9,"high":16.0,"low":15.4,"close":15.9,"volume":864000,"week_end_date":"2004-12-24","date":"2004-12-20","ma20":15.885,"prev_close":15.7,"prev_ma20":15.85,"cross_above_ma20":true,"ma20_rising":true,"ma20_distance_pct":0.0944287063,"capital_report_date":null,"capital_billion":null,"stock_name":"光明","industry_category":"紡織纖維","type":"tpex"},{"stock_id":"4530","last_trade_date":"2004-12-24","open":8.3,"high":9.35,"low":8.0,"close":9.1,"volume":5641635,"week_end_date":"2004-12-24","date":"2004-12-20","ma20":8.71,"prev_close":8.3,"prev_ma20":8.81,"cross_above_ma20":true,"ma20_rising":false,"ma20_distance_pct":4.4776119403,"capital_report_date":null,"capital_billion":null,"stock_name":"宏易","industry_category":"電機機械","type":"tpex"},{"stock_id":"4535","last_trade_date":"2004-12-24","open":56.0,"high":63.0,"low":55.5,"close":62.5,"volume":1750240,"week_end_date":"2004-12-24","date":"2004-12-20","ma20":57.775,"prev_close":56.5,"prev_ma20":57.725,"cross_above_ma20":true,"ma20_rising":true,"ma20_distance_pct":8.1782778018,"capital_report_date":null,"capital_billion":null,"stock_name":"至興","industry_category":"電機機械","type":"tpex"},{"stock_id":"4903","last_trade_date":"2004-12-24","open":1.95,"high":2.44,"low":1.95,"close":2.3,"volume":1535100,"week_end_date":"2004-12-24","date":"2004-12-20","ma20":2.247,"prev_close":1.88,"prev_ma20":2.307,"cross_above_ma20":true,"ma20_rising":false,"ma20_distance_pct":2.3587004895,"capital_report_date":null,"capital_billion":null,"stock_name":"聯光通","industry_category":"通信網路業","type":"tpex"},{"stock_id":"5301","last_trade_date":"2004-12-24","open":4.02,"high":4.76,"low":3.96,"close":4.5,"volume":1049300,"week_end_date":"2004-12-24","date":"2004-12-20","ma20":4.486,"prev_close":4.13,"prev_ma20":4.541,"cross_above_ma20":true,"ma20_rising":false,"ma20_distance_pct":0.312082033,"capital_report_date":null,"capital_billion":null,"stock_name":"寶得利","industry_category":"觀光事業","type":"tpex"},{"stock_id":"5312","last_trade_date":"2004-12-24","open":15.9,"high":17.2,"low":15.8,"close":16.6,"volume":466382,"week_end_date":"2004-12-24","date":"2004-12-20","ma20":16.07,"prev_close":16.1,"prev_ma20":16.1,"cross_above_ma20":true,"ma20_rising":false,"ma20_distance_pct":3.2980709396,"capital_report_date":null,"capital_billion":null,"stock_name":"寶島科","industry_category":"生技醫療業","type":"tpex"},{"stock_id":"5464","last_trade_date":"2004-12-24","open":16.0,"high":17.4,"low":16.0,"close":16.4,"volume":147450,"week_end_date":"2004-12-24","date":"2004-12-20","ma20":16.35,"prev_close":16.2,"prev_ma20":16.305,"cross_above_ma20":true,"ma20_rising":true,"ma20_distance_pct":0.3058103976,"capital_report_date":null,"capital_billion":null,"stock_name":"霖宏","industry_category":"電子零組件業","type":"tpex"},{"stock_id":"5478","last_trade_date":"2004-12-24","open":55.0,"high":62.5,"low":54.5,"close":62.0,"volume":6623696,"week_end_date":"2004-12-24","date":"2004-12-20","ma20":57.85,"prev_close":56.5,"prev_ma20":57.925,"cross_above_ma20":true,"ma20_rising":false,"ma20_distance_pct":7.1737251513,"capital_report_date":null,"capital_billion":null,"stock_name":"智冠","industry_category":"文化創意業","type":"tpex"},{"stock_id":"5514","last_trade_date":"2004-12-24","open":9.1,"high":10.45,"low":9.1,"close":10.35,"volume":5480750,"week_end_date":"2004-12-24","date":"2004-12-20","ma20":10.2975,"prev_close":9.6,"prev_ma20":10.3375,"cross_above_ma20":true,"ma20_rising":false,"ma20_distance_pct":0.5098324836,"capital_report_date":null,"capital_billion":null,"stock_name":"三豐","industry_category":"建材營造","type":"tpex"},{"stock_id":"5609","last_trade_date":"2004-12-24","open":13.85,"high":14.15,"low":13.85,"close":14.05,"volume":390300,"week_end_date":"2004-12-24","date":"2004-12-20","ma20":13.9875,"prev_close":13.95,"prev_ma20":13.9975,"cross_above_ma20":true,"ma20_rising":false,"ma20_distance_pct":0.4468275246,"capital_report_date":null,"capital_billion":null,"stock_name":"中菲行","industry_category":"航運業","type":"tpex"},{"stock_id":"5704","last_trade_date":"2004-12-24","open":15.3,"high":16.6,"low":14.6,"close":16.6,"volume":9118,"week_end_date":"2004-12-24","date":"2004-12-20","ma20":16.04,"prev_close":15.3,"prev_ma20":16.025,"cross_above_ma20":true,"ma20_rising":true,"ma20_distance_pct":3.4912718204,"capital_report_date":null,"capital_billion":null,"stock_name":"老爺知","industry_category":"觀光事業","type":"tpex"},{"stock_id":"6101","last_trade_date":"2004-12-24","open":7.2,"high":7.9,"low":7.2,"close":7.8,"volume":127700,"week_end_date":"2004-12-24","date":"2004-12-20","ma20":7.7975,"prev_close":7.6,"prev_ma20":7.78,"cross_above_ma20":true,"ma20_rising":true,"ma20_distance_pct":0.0320615582,"capital_report_date":null,"capital_billion":null,"stock_name":"寬魚國際","industry_category":"文化創意業","type":"tpex"},{"stock_id":"6111","last_trade_date":"2004-12-24","open":18.5,"high":20.3,"low":18.3,"close":20.3,"volume":1282357,"week_end_date":"2004-12-24","date":"2004-12-20","ma20":19.255,"prev_close":18.7,"prev_ma20":19.35,"cross_above_ma20":true,"ma20_rising":false,"ma20_distance_pct":5.4271617762,"capital_report_date":null,"capital_billion":null,"stock_name":"光聚晶電","industry_category":"文化創意業","type":"tpex"},{"stock_id":"6183","last_trade_date":"2004-12-24","open":9.5,"high":10.0,"low":9.5,"close":10.0,"volume":364000,"week_end_date":"2004-12-24","date":"2004-12-20","ma20":9.95,"prev_close":9.6,"prev_ma20":9.9675,"cross_above_ma20":true,"ma20_rising":false,"ma20_distance_pct":0.5025125628,"capital_report_date":null,"capital_billion":null,"stock_name":"關貿","industry_category":"電子工業","type":"twse"},{"stock_id":"6188","last_trade_date":"2004-12-24","open":33.3,"high":36.2,"low":33.0,"close":34.7,"volume":24787319,"week_end_date":"2004-12-24","date":"2004-12-20","ma20":34.52,"prev_close":34.2,"prev_ma20":35.075,"cross_above_ma20":true,"ma20_rising":false,"ma20_distance_pct":0.5214368482,"capital_report_date":null,"capital_billion":null,"stock_name":"廣明","industry_category":"電腦及週邊設備業","type":"tpex"},{"stock_id":"8908","last_trade_date":"2004-12-24","open":14.9,"high":15.0,"low":14.35,"close":15.0,"volume":176010,"week_end_date":"2004-12-24","date":"2004-12-20","ma20":14.7175,"prev_close":14.65,"prev_ma20":14.7075,"cross_above_ma20":true,"ma20_rising":true,"ma20_distance_pct":1.9194836079,"capital_report_date":null,"capital_billion":null,"stock_name":"欣雄","industry_category":"油電燃氣業","type":"tpex"},{"stock_id":"8917","last_trade_date":"2004-12-24","open":26.5,"high":28.4,"low":26.5,"close":28.4,"volume":3004,"week_end_date":"2004-12-24","date":"2004-12-20","ma20":25.715,"prev_close":24.9,"prev_ma20":25.545,"cross_above_ma20":true,"ma20_rising":true,"ma20_distance_pct":10.4413766284,"capital_report_date":null,"capital_billion":null,"stock_name":"欣泰","industry_category":"油電燃氣業","type":"tpex"},{"stock_id":"8921","last_trade_date":"2004-12-24","open":7.3,"high":7.9,"low":7.0,"close":7.9,"volume":58011,"week_end_date":"2004-12-24","date":"2004-12-20","ma20":7.505,"prev_close":7.3,"prev_ma20":7.53,"cross_above_ma20":true,"ma20_rising":false,"ma20_distance_pct":5.2631578947,"capital_report_date":null,"capital_billion":null,"stock_name":"沈氏","industry_category":"其他","type":"tpex"},{"stock_id":"8927","last_trade_date":"2004-12-24","open":13.5,"high":13.6,"low":13.5,"close":13.6,"volume":75162,"week_end_date":"2004-12-24","date":"2004-12-20","ma20":13.5175,"prev_close":13.5,"prev_ma20":13.5425,"cross_above_ma20":true,"ma20_rising":false,"ma20_distance_pct":0.6103199556,"capital_report_date":null,"capital_billion":null,"stock_name":"北基","industry_category":"油電燃氣業","type":"tpex"},{"stock_id":"8931","last_trade_date":"2004-12-24","open":10.35,"high":10.5,"low":10.3,"close":10.5,"volume":534482,"week_end_date":"2004-12-24","date":"2004-12-20","ma20":10.435,"prev_close":10.35,"prev_ma20":10.435,"cross_above_ma20":true,"ma20_rising":false,"ma20_distance_pct":0.6229036895,"capital_report_date":null,"capital_billion":null,"stock_name":"大汽電","industry_category":"油電燃氣業","type":"tpex"},{"stock_id":"9904","last_trade_date":"2004-12-24","open":27.0,"high":29.0,"low":26.9,"close":28.4,"volume":34803492,"week_end_date":"2004-12-24","date":"2004-12-20","ma20":28.28,"prev_close":27.5,"prev_ma20":28.365,"cross_above_ma20":true,"ma20_rising":false,"ma20_distance_pct":0.4243281471,"capital_report_date":null,"capital_billion":null,"stock_name":"寶成","industry_category":"其他","type":"twse"},{"stock_id":"9908","last_trade_date":"2004-12-24","open":12.1,"high":12.6,"low":12.0,"close":12.4,"volume":4517826,"week_end_date":"2004-12-24","date":"2004-12-20","ma20":12.3125,"prev_close":12.1,"prev_ma20":12.2675,"cross_above_ma20":true,"ma20_rising":true,"ma20_distance_pct":0.7106598985,"capital_report_date":null,"capital_billion":null,"stock_name":"大台北","industry_category":"油電燃氣業","type":"twse"},{"stock_id":"9918","last_trade_date":"2004-12-24","open":17.1,"high":17.4,"low":16.9,"close":17.4,"volume":65001,"week_end_date":"2004-12-24","date":"2004-12-20","ma20":17.215,"prev_close":17.0,"prev_ma20":17.17,"cross_above_ma20":true,"ma20_rising":true,"ma20_distance_pct":1.0746442056,"capital_report_date":null,"capital_billion":null,"stock_name":"欣天然","industry_category":"油電燃氣業","type":"twse"},{"stock_id":"9949","last_trade_date":"2004-12-24","open":22.3,"high":22.8,"low":22.0,"close":22.8,"volume":68100,"week_end_date":"2004-12-24","date":"2004-12-20","ma20":22.57,"prev_close":22.4,"prev_ma20":22.48,"cross_above_ma20":true,"ma20_rising":true,"ma20_distance_pct":1.0190518387,"capital_report_date":null,"capital_billion":null,"stock_name":"琉園","industry_category":"文化創意業","type":"tpex"}]