[{"stock_id":"1107","last_trade_date":"2010-02-10","open":0.91,"high":0.98,"low":0.86,"close":0.98,"volume":1185000,"date":"2010-02-12","ma20":0.9415,"prev_close":0.92,"prev_ma20":0.94,"cross_above_ma20":true,"ma20_distance_pct":4.0892193309,"stock_name":"建台","industry_category":"其他","type":"twse"},{"stock_id":"1235","last_trade_date":"2010-02-10","open":31.85,"high":34.25,"low":31.8,"close":34.2,"volume":44000,"date":"2010-02-12","ma20":33.1825,"prev_close":32.55,"prev_ma20":33.1975,"cross_above_ma20":true,"ma20_distance_pct":3.0663753485,"stock_name":"興泰","industry_category":"食品工業","type":"twse"},{"stock_id":"1236","last_trade_date":"2010-02-10","open":16.8,"high":17.7,"low":16.8,"close":17.6,"volume":213437,"date":"2010-02-12","ma20":16.9525,"prev_close":16.8,"prev_ma20":16.8775,"cross_above_ma20":true,"ma20_distance_pct":3.8194956496,"stock_name":"宏亞","industry_category":"食品工業","type":"twse"},{"stock_id":"1304","last_trade_date":"2010-02-10","open":17.4,"high":18.85,"low":17.1,"close":18.6,"volume":13113365,"date":"2010-02-12","ma20":18.4875,"prev_close":17.2,"prev_ma20":18.325,"cross_above_ma20":true,"ma20_distance_pct":0.6085192698,"stock_name":"台聚","industry_category":"塑膠工業","type":"twse"},{"stock_id":"1308","last_trade_date":"2010-02-10","open":25.3,"high":27.45,"low":25.3,"close":27.3,"volume":3778679,"date":"2010-02-12","ma20":25.9325,"prev_close":25.3,"prev_ma20":25.7475,"cross_above_ma20":true,"ma20_distance_pct":5.2733056975,"stock_name":"亞聚","industry_category":"塑膠工業","type":"twse"},{"stock_id":"1324","last_trade_date":"2010-02-10","open":16.45,"high":18.25,"low":16.4,"close":17.85,"volume":1662209,"date":"2010-02-12","ma20":17.2775,"prev_close":16.4,"prev_ma20":17.0725,"cross_above_ma20":true,"ma20_distance_pct":3.3135580958,"stock_name":"地球","industry_category":"塑膠工業","type":"twse"},{"stock_id":"1336","last_trade_date":"2010-02-10","open":16.5,"high":18.35,"low":16.2,"close":18.3,"volume":159463,"date":"2010-02-12","ma20":18.1775,"prev_close":16.5,"prev_ma20":18.1325,"cross_above_ma20":true,"ma20_distance_pct":0.6739100536,"stock_name":"台翰","industry_category":"電子零組件業","type":"tpex"},{"stock_id":"1416","last_trade_date":"2010-02-10","open":9.09,"high":9.8,"low":8.89,"close":9.78,"volume":5141853,"date":"2010-02-12","ma20":9.38,"prev_close":8.95,"prev_ma20":9.2685,"cross_above_ma20":true,"ma20_distance_pct":4.2643923241,"stock_name":"廣豐","industry_category":"其他","type":"twse"},{"stock_id":"1444","last_trade_date":"2010-02-10","open":7.1,"high":8.3,"low":7.08,"close":8.07,"volume":8587499,"date":"2010-02-12","ma20":7.629,"prev_close":7.08,"prev_ma20":7.5415,"cross_above_ma20":true,"ma20_distance_pct":5.780574125,"stock_name":"力麗","industry_category":"紡織纖維","type":"twse"},{"stock_id":"1445","last_trade_date":"2010-02-10","open":7.1,"high":7.79,"low":7.1,"close":7.79,"volume":359940,"date":"2010-02-12","ma20":7.5275,"prev_close":7.2,"prev_ma20":7.4675,"cross_above_ma20":true,"ma20_distance_pct":3.4872135503,"stock_name":"大宇","industry_category":"紡織纖維","type":"twse"},{"stock_id":"1452","last_trade_date":"2010-02-10","open":7.95,"high":8.46,"low":7.86,"close":8.45,"volume":418662,"date":"2010-02-12","ma20":8.2155,"prev_close":7.95,"prev_ma20":8.148,"cross_above_ma20":true,"ma20_distance_pct":2.8543606597,"stock_name":"宏益","industry_category":"紡織纖維","type":"twse"},{"stock_id":"1464","last_trade_date":"2010-02-10","open":6.25,"high":6.59,"low":6.09,"close":6.44,"volume":782286,"date":"2010-02-12","ma20":6.383,"prev_close":6.25,"prev_ma20":6.352,"cross_above_ma20":true,"ma20_distance_pct":0.8929970233,"stock_name":"得力","industry_category":"紡織纖維","type":"twse"},{"stock_id":"1466","last_trade_date":"2010-02-10","open":6.72,"high":7.24,"low":6.61,"close":7.19,"volume":142538,"date":"2010-02-12","ma20":7.0555,"prev_close":6.6,"prev_ma20":6.9975,"cross_above_ma20":true,"ma20_distance_pct":1.9063142229,"stock_name":"聚隆","industry_category":"紡織纖維","type":"twse"},{"stock_id":"1467","last_trade_date":"2010-02-10","open":7.89,"high":8.24,"low":7.86,"close":8.2,"volume":1808419,"date":"2010-02-12","ma20":8.039,"prev_close":7.92,"prev_ma20":8.0185,"cross_above_ma20":true,"ma20_distance_pct":2.0027366588,"stock_name":"南緯","industry_category":"紡織纖維","type":"twse"},{"stock_id":"1471","last_trade_date":"2010-02-10","open":30.5,"high":34.5,"low":29.8,"close":33.8,"volume":8114897,"date":"2010-02-12","ma20":32.8,"prev_close":30.0,"prev_ma20":32.3,"cross_above_ma20":true,"ma20_distance_pct":3.0487804878,"stock_name":"首利","industry_category":"電子工業","type":"twse"},{"stock_id":"1477","last_trade_date":"2010-02-10","open":57.8,"high":59.6,"low":57.3,"close":59.2,"volume":936025,"date":"2010-02-12","ma20":59.065,"prev_close":57.8,"prev_ma20":59.075,"cross_above_ma20":true,"ma20_distance_pct":0.228561754,"stock_name":"聚陽","industry_category":"紡織纖維","type":"twse"},{"stock_id":"1521","last_trade_date":"2010-02-10","open":38.9,"high":43.1,"low":38.6,"close":43.0,"volume":1439056,"date":"2010-02-12","ma20":40.5475,"prev_close":38.65,"prev_ma20":39.585,"cross_above_ma20":true,"ma20_distance_pct":6.0484616807,"stock_name":"大億","industry_category":"汽車工業","type":"twse"},{"stock_id":"1523","last_trade_date":"2010-02-10","open":25.3,"high":28.6,"low":24.85,"close":27.7,"volume":1231235,"date":"2010-02-12","ma20":27.3975,"prev_close":25.3,"prev_ma20":26.9475,"cross_above_ma20":true,"ma20_distance_pct":1.104115339,"stock_name":"開億","industry_category":"電機機械","type":"twse"},{"stock_id":"1526","last_trade_date":"2010-02-10","open":5.99,"high":6.24,"low":5.92,"close":6.24,"volume":379388,"date":"2010-02-12","ma20":6.155,"prev_close":6.0,"prev_ma20":6.1235,"cross_above_ma20":true,"ma20_distance_pct":1.3809910642,"stock_name":"日馳","industry_category":"電機機械","type":"twse"},{"stock_id":"1531","last_trade_date":"2010-02-10","open":16.1,"high":17.7,"low":16.1,"close":17.6,"volume":2441388,"date":"2010-02-12","ma20":16.575,"prev_close":16.1,"prev_ma20":16.4775,"cross_above_ma20":true,"ma20_distance_pct":6.1840120664,"stock_name":"高林股","industry_category":"電機機械","type":"twse"},{"stock_id":"1538","last_trade_date":"2010-02-10","open":32.1,"high":34.3,"low":31.8,"close":33.9,"volume":2926541,"date":"2010-02-12","ma20":33.27,"prev_close":32.1,"prev_ma20":32.5975,"cross_above_ma20":true,"ma20_distance_pct":1.8935978359,"stock_name":"正峰","industry_category":"電機機械","type":"twse"},{"stock_id":"1584","last_trade_date":"2010-02-10","open":14.5,"high":15.0,"low":14.0,"close":15.0,"volume":218038,"date":"2010-02-12","ma20":14.4425,"prev_close":14.2,"prev_ma20":14.3325,"cross_above_ma20":true,"ma20_distance_pct":3.8601350182,"stock_name":"精剛","industry_category":"其他","type":"tpex"},{"stock_id":"1608","last_trade_date":"2010-02-10","open":10.05,"high":10.8,"low":10.05,"close":10.7,"volume":7442621,"date":"2010-02-12","ma20":10.682,"prev_close":10.05,"prev_ma20":10.6055,"cross_above_ma20":true,"ma20_distance_pct":0.1685077701,"stock_name":"華榮","industry_category":"電器電纜","type":"twse"},{"stock_id":"1702","last_trade_date":"2010-02-10","open":23.45,"high":26.5,"low":23.1,"close":25.75,"volume":9516038,"date":"2010-02-12","ma20":24.64,"prev_close":23.35,"prev_ma20":24.0025,"cross_above_ma20":true,"ma20_distance_pct":4.5048701299,"stock_name":"南僑","industry_category":"食品工業","type":"twse"},{"stock_id":"1709","last_trade_date":"2010-02-10","open":12.8,"high":13.25,"low":12.7,"close":13.2,"volume":858249,"date":"2010-02-12","ma20":13.145,"prev_close":12.8,"prev_ma20":13.095,"cross_above_ma20":true,"ma20_distance_pct":0.4184100418,"stock_name":"和益","industry_category":"化學工業","type":"twse"},{"stock_id":"1710","last_trade_date":"2010-02-10","open":23.8,"high":25.5,"low":23.15,"close":25.1,"volume":11606681,"date":"2010-02-12","ma20":24.6875,"prev_close":23.1,"prev_ma20":24.4425,"cross_above_ma20":true,"ma20_distance_pct":1.6708860759,"stock_name":"東聯","industry_category":"化學工業","type":"twse"},{"stock_id":"1718","last_trade_date":"2010-02-10","open":6.72,"high":7.49,"low":6.66,"close":7.23,"volume":34517397,"date":"2010-02-12","ma20":6.9495,"prev_close":6.51,"prev_ma20":6.8915,"cross_above_ma20":true,"ma20_distance_pct":4.0362616016,"stock_name":"中纖","industry_category":"化學工業","type":"twse"},{"stock_id":"1727","last_trade_date":"2010-02-10","open":17.3,"high":20.1,"low":17.3,"close":19.8,"volume":3021461,"date":"2010-02-12","ma20":17.9,"prev_close":17.3,"prev_ma20":17.655,"cross_above_ma20":true,"ma20_distance_pct":10.6145251397,"stock_name":"中華化","industry_category":"化學生技醫療","type":"twse"},{"stock_id":"1742","last_trade_date":"2010-02-10","open":37.5,"high":39.2,"low":37.5,"close":39.0,"volume":228149,"date":"2010-02-12","ma20":38.3325,"prev_close":37.5,"prev_ma20":38.9425,"cross_above_ma20":true,"ma20_distance_pct":1.7413422031,"stock_name":"台蠟","industry_category":"化學工業","type":"tpex"},{"stock_id":"1776","last_trade_date":"2010-02-09","open":21.4,"high":22.0,"low":21.2,"close":22.0,"volume":4001,"date":"2010-02-12","ma20":21.4,"prev_close":20.5,"prev_ma20":21.225,"cross_above_ma20":true,"ma20_distance_pct":2.8037383178,"stock_name":"展宇","industry_category":"化學生技醫療","type":"twse"},{"stock_id":"1781","last_trade_date":"2010-02-10","open":14.15,"high":15.9,"low":14.15,"close":15.9,"volume":299975,"date":"2010-02-12","ma20":15.82,"prev_close":13.95,"prev_ma20":15.7975,"cross_above_ma20":true,"ma20_distance_pct":0.5056890013,"stock_name":"合世","industry_category":"生技醫療業","type":"tpex"},{"stock_id":"1802","last_trade_date":"2010-02-10","open":25.45,"high":26.85,"low":24.6,"close":26.85,"volume":9062574,"date":"2010-02-12","ma20":26.3025,"prev_close":25.3,"prev_ma20":26.2275,"cross_above_ma20":true,"ma20_distance_pct":2.0815511833,"stock_name":"台玻","industry_category":"玻璃陶瓷","type":"twse"},{"stock_id":"1806","last_trade_date":"2010-02-10","open":16.95,"high":18.95,"low":16.8,"close":18.95,"volume":11088720,"date":"2010-02-12","ma20":17.68,"prev_close":16.8,"prev_ma20":17.315,"cross_above_ma20":true,"ma20_distance_pct":7.1832579186,"stock_name":"冠軍","industry_category":"玻璃陶瓷","type":"twse"},{"stock_id":"2006","last_trade_date":"2010-02-10","open":33.5,"high":35.5,"low":33.35,"close":34.8,"volume":16579231,"date":"2010-02-12","ma20":33.9575,"prev_close":33.3,"prev_ma20":33.935,"cross_above_ma20":true,"ma20_distance_pct":2.4810424796,"stock_name":"東和鋼鐵","industry_category":"鋼鐵工業","type":"twse"},{"stock_id":"2007","last_trade_date":"2010-02-10","open":6.42,"high":7.35,"low":6.42,"close":7.35,"volume":2762572,"date":"2010-02-12","ma20":6.6075,"prev_close":6.42,"prev_ma20":6.555,"cross_above_ma20":true,"ma20_distance_pct":11.23723042,"stock_name":"燁興","industry_category":"鋼鐵工業","type":"twse"},{"stock_id":"2014","last_trade_date":"2010-02-10","open":13.55,"high":14.75,"low":13.3,"close":14.65,"volume":31418739,"date":"2010-02-12","ma20":14.15,"prev_close":13.5,"prev_ma20":14.0425,"cross_above_ma20":true,"ma20_distance_pct":3.5335689046,"stock_name":"中鴻","industry_category":"鋼鐵工業","type":"twse"},{"stock_id":"2024","last_trade_date":"2010-02-10","open":5.45,"high":6.3,"low":5.45,"close":6.21,"volume":1930337,"date":"2010-02-12","ma20":5.6595,"prev_close":5.45,"prev_ma20":5.6105,"cross_above_ma20":true,"ma20_distance_pct":9.7270076862,"stock_name":"志聯","industry_category":"鋼鐵工業","type":"twse"},{"stock_id":"2030","last_trade_date":"2010-02-10","open":15.15,"high":16.8,"low":14.8,"close":16.5,"volume":1780725,"date":"2010-02-12","ma20":16.105,"prev_close":15.05,"prev_ma20":16.07,"cross_above_ma20":true,"ma20_distance_pct":2.4526544551,"stock_name":"彰源","industry_category":"鋼鐵工業","type":"twse"},{"stock_id":"2031","last_trade_date":"2010-02-10","open":28.3,"high":31.15,"low":27.25,"close":31.0,"volume":11288899,"date":"2010-02-12","ma20":29.8375,"prev_close":28.0,"prev_ma20":29.5525,"cross_above_ma20":true,"ma20_distance_pct":3.8961038961,"stock_name":"新光鋼","industry_category":"鋼鐵工業","type":"twse"},{"stock_id":"2101","last_trade_date":"2010-02-10","open":37.5,"high":41.95,"low":37.1,"close":41.35,"volume":46180354,"date":"2010-02-12","ma20":38.0075,"prev_close":37.0,"prev_ma20":37.65,"cross_above_ma20":true,"ma20_distance_pct":8.7943169111,"stock_name":"南港","industry_category":"橡膠工業","type":"twse"},{"stock_id":"2221","last_trade_date":"2010-02-10","open":11.7,"high":12.45,"low":11.0,"close":12.45,"volume":160024,"date":"2010-02-12","ma20":12.195,"prev_close":11.7,"prev_ma20":12.1475,"cross_above_ma20":true,"ma20_distance_pct":2.0910209102,"stock_name":"大甲","industry_category":"其他","type":"tpex"},{"stock_id":"2302","last_trade_date":"2010-02-10","open":5.35,"high":5.94,"low":5.15,"close":5.85,"volume":1007267,"date":"2010-02-12","ma20":5.6535,"prev_close":5.35,"prev_ma20":5.5225,"cross_above_ma20":true,"ma20_distance_pct":3.4757230034,"stock_name":"麗正","industry_category":"電子工業","type":"twse"},{"stock_id":"2308","last_trade_date":"2010-02-10","open":93.5,"high":96.0,"low":92.0,"close":95.6,"volume":17292169,"date":"2010-02-12","ma20":93.25,"prev_close":91.4,"prev_ma20":92.935,"cross_above_ma20":true,"ma20_distance_pct":2.5201072386,"stock_name":"台達電","industry_category":"電子工業","type":"twse"},{"stock_id":"2312","last_trade_date":"2010-02-10","open":8.8,"high":9.15,"low":8.78,"close":9.13,"volume":8822433,"date":"2010-02-12","ma20":9.0575,"prev_close":8.9,"prev_ma20":9.0355,"cross_above_ma20":true,"ma20_distance_pct":0.800441623,"stock_name":"金寶","industry_category":"其他電子業","type":"twse"},{"stock_id":"2323","last_trade_date":"2010-02-10","open":7.77,"high":8.25,"low":7.74,"close":8.09,"volume":61726492,"date":"2010-02-12","ma20":7.913,"prev_close":7.74,"prev_ma20":7.912,"cross_above_ma20":true,"ma20_distance_pct":2.2368254771,"stock_name":"中環","industry_category":"光電業","type":"twse"},{"stock_id":"2332","last_trade_date":"2010-02-10","open":31.5,"high":33.05,"low":31.1,"close":32.5,"volume":11365463,"date":"2010-02-12","ma20":32.165,"prev_close":31.1,"prev_ma20":31.94,"cross_above_ma20":true,"ma20_distance_pct":1.0415047412,"stock_name":"友訊","industry_category":"通信網路業","type":"twse"},{"stock_id":"2337","last_trade_date":"2010-02-10","open":16.45,"high":17.45,"low":16.4,"close":17.2,"volume":41315121,"date":"2010-02-12","ma20":17.0125,"prev_close":16.35,"prev_ma20":17.03,"cross_above_ma20":true,"ma20_distance_pct":1.1021307862,"stock_name":"旺宏","industry_category":"半導體業","type":"twse"},{"stock_id":"2344","last_trade_date":"2010-02-10","open":6.88,"high":7.6,"low":6.84,"close":7.48,"volume":38842955,"date":"2010-02-12","ma20":7.2785,"prev_close":6.86,"prev_ma20":7.2305,"cross_above_ma20":true,"ma20_distance_pct":2.7684275606,"stock_name":"華邦電","industry_category":"電子工業","type":"twse"},{"stock_id":"2350","last_trade_date":"2010-02-10","open":18.0,"high":19.65,"low":17.9,"close":19.45,"volume":8789421,"date":"2010-02-12","ma20":18.825,"prev_close":17.8,"prev_ma20":18.5475,"cross_above_ma20":true,"ma20_distance_pct":3.3200531208,"stock_name":"環電","industry_category":"其他電子業","type":"twse"},{"stock_id":"2353","last_trade_date":"2010-02-10","open":85.6,"high":88.5,"low":83.8,"close":87.4,"volume":48545589,"date":"2010-02-12","ma20":86.32,"prev_close":84.5,"prev_ma20":85.92,"cross_above_ma20":true,"ma20_distance_pct":1.2511584801,"stock_name":"宏碁","industry_category":"電腦及週邊設備業","type":"twse"},{"stock_id":"2363","last_trade_date":"2010-02-10","open":19.2,"high":21.5,"low":18.9,"close":21.35,"volume":16733196,"date":"2010-02-12","ma20":21.245,"prev_close":18.9,"prev_ma20":20.8675,"cross_above_ma20":true,"ma20_distance_pct":0.4942339374,"stock_name":"矽統","industry_category":"半導體業","type":"twse"},{"stock_id":"2375","last_trade_date":"2010-02-10","open":4.49,"high":4.83,"low":4.4,"close":4.7,"volume":6321143,"date":"2010-02-12","ma20":4.567,"prev_close":4.47,"prev_ma20":4.5615,"cross_above_ma20":true,"ma20_distance_pct":2.9121961901,"stock_name":"凱美","industry_category":"電子工業","type":"twse"},{"stock_id":"2379","last_trade_date":"2010-02-10","open":82.8,"high":88.5,"low":82.4,"close":87.2,"volume":19873889,"date":"2010-02-12","ma20":83.2,"prev_close":82.1,"prev_ma20":82.4,"cross_above_ma20":true,"ma20_distance_pct":4.8076923077,"stock_name":"瑞昱","industry_category":"半導體業","type":"twse"},{"stock_id":"2384","last_trade_date":"2010-02-10","open":22.95,"high":25.15,"low":22.55,"close":23.95,"volume":101569290,"date":"2010-02-12","ma20":23.87,"prev_close":22.3,"prev_ma20":23.8325,"cross_above_ma20":true,"ma20_distance_pct":0.3351487222,"stock_name":"勝華","industry_category":"光電業","type":"twse"},{"stock_id":"2403","last_trade_date":"2010-02-10","open":30.15,"high":33.95,"low":29.9,"close":33.7,"volume":11425065,"date":"2010-02-12","ma20":30.435,"prev_close":29.8,"prev_ma20":29.9875,"cross_above_ma20":true,"ma20_distance_pct":10.7277805159,"stock_name":"友尚","industry_category":"電子通路業","type":"twse"},{"stock_id":"2406","last_trade_date":"2010-02-10","open":26.5,"high":29.75,"low":25.9,"close":29.65,"volume":14060041,"date":"2010-02-12","ma20":28.32,"prev_close":26.0,"prev_ma20":27.3075,"cross_above_ma20":true,"ma20_distance_pct":4.6963276836,"stock_name":"國碩","industry_category":"光電業","type":"twse"},{"stock_id":"2425","last_trade_date":"2010-02-10","open":16.8,"high":19.45,"low":16.6,"close":19.15,"volume":3327872,"date":"2010-02-12","ma20":17.7075,"prev_close":16.75,"prev_ma20":17.445,"cross_above_ma20":true,"ma20_distance_pct":8.1462657066,"stock_name":"承啟","industry_category":"電子工業","type":"twse"},{"stock_id":"2428","last_trade_date":"2010-02-10","open":53.5,"high":56.0,"low":53.1,"close":54.8,"volume":2626915,"date":"2010-02-12","ma20":54.59,"prev_close":53.5,"prev_ma20":54.1,"cross_above_ma20":true,"ma20_distance_pct":0.3846858399,"stock_name":"興勤","industry_category":"電子工業","type":"twse"},{"stock_id":"2431","last_trade_date":"2010-02-10","open":17.15,"high":20.2,"low":17.15,"close":20.2,"volume":3020269,"date":"2010-02-12","ma20":19.3775,"prev_close":18.0,"prev_ma20":19.08,"cross_above_ma20":true,"ma20_distance_pct":4.2446135982,"stock_name":"聯昌","industry_category":"電子工業","type":"twse"},{"stock_id":"2440","last_trade_date":"2010-02-10","open":10.65,"high":11.25,"low":10.15,"close":10.9,"volume":2025198,"date":"2010-02-12","ma20":10.7435,"prev_close":10.3,"prev_ma20":10.5025,"cross_above_ma20":true,"ma20_distance_pct":1.4566947457,"stock_name":"太空梭","industry_category":"電子工業","type":"twse"},{"stock_id":"2441","last_trade_date":"2010-02-10","open":29.2,"high":31.85,"low":29.0,"close":31.8,"volume":9004833,"date":"2010-02-12","ma20":31.6625,"prev_close":29.2,"prev_ma20":31.6625,"cross_above_ma20":true,"ma20_distance_pct":0.4342676668,"stock_name":"超豐","industry_category":"半導體業","type":"twse"},{"stock_id":"2443","last_trade_date":"2010-02-10","open":6.69,"high":7.51,"low":6.4,"close":7.35,"volume":13911235,"date":"2010-02-12","ma20":7.0215,"prev_close":6.69,"prev_ma20":6.8565,"cross_above_ma20":true,"ma20_distance_pct":4.6784875027,"stock_name":"昶虹","industry_category":"其他","type":"twse"},{"stock_id":"2455","last_trade_date":"2010-02-10","open":67.5,"high":77.0,"low":66.7,"close":75.2,"volume":6538104,"date":"2010-02-12","ma20":75.16,"prev_close":67.5,"prev_ma20":74.735,"cross_above_ma20":true,"ma20_distance_pct":0.0532197978,"stock_name":"全新","industry_category":"通信網路業","type":"twse"},{"stock_id":"2457","last_trade_date":"2010-02-10","open":27.5,"high":30.1,"low":27.5,"close":29.35,"volume":19013895,"date":"2010-02-12","ma20":28.805,"prev_close":27.5,"prev_ma20":28.42,"cross_above_ma20":true,"ma20_distance_pct":1.8920326332,"stock_name":"飛宏","industry_category":"電子工業","type":"twse"},{"stock_id":"2462","last_trade_date":"2010-02-10","open":52.3,"high":54.6,"low":51.7,"close":53.9,"volume":2069896,"date":"2010-02-12","ma20":52.955,"prev_close":52.3,"prev_ma20":53.02,"cross_above_ma20":true,"ma20_distance_pct":1.7845340383,"stock_name":"良得電","industry_category":"電子工業","type":"twse"},{"stock_id":"2464","last_trade_date":"2010-02-10","open":27.65,"high":29.95,"low":27.3,"close":29.4,"volume":1609846,"date":"2010-02-12","ma20":28.7375,"prev_close":27.65,"prev_ma20":28.4225,"cross_above_ma20":true,"ma20_distance_pct":2.3053501522,"stock_name":"盟立","industry_category":"其他電子業","type":"twse"},{"stock_id":"2473","last_trade_date":"2010-02-10","open":30.6,"high":34.9,"low":30.6,"close":34.85,"volume":4898814,"date":"2010-02-12","ma20":34.08,"prev_close":31.0,"prev_ma20":33.7125,"cross_above_ma20":true,"ma20_distance_pct":2.2593896714,"stock_name":"思源","industry_category":"半導體業","type":"twse"},{"stock_id":"2480","last_trade_date":"2010-02-10","open":25.2,"high":27.2,"low":24.6,"close":27.0,"volume":3596847,"date":"2010-02-12","ma20":25.1575,"prev_close":24.4,"prev_ma20":24.7275,"cross_above_ma20":true,"ma20_distance_pct":7.323859684,"stock_name":"敦陽科","industry_category":"資訊服務業","type":"twse"},{"stock_id":"2481","last_trade_date":"2010-02-10","open":24.9,"high":28.1,"low":24.8,"close":27.0,"volume":18795709,"date":"2010-02-12","ma20":25.205,"prev_close":24.55,"prev_ma20":24.885,"cross_above_ma20":true,"ma20_distance_pct":7.1216028566,"stock_name":"強茂","industry_category":"半導體業","type":"twse"},{"stock_id":"2483","last_trade_date":"2010-02-10","open":14.3,"high":15.75,"low":14.0,"close":15.6,"volume":723292,"date":"2010-02-12","ma20":14.7975,"prev_close":14.0,"prev_ma20":14.6175,"cross_above_ma20":true,"ma20_distance_pct":5.4232133806,"stock_name":"百容","industry_category":"電子工業","type":"twse"},{"stock_id":"2486","last_trade_date":"2010-02-10","open":46.1,"high":50.1,"low":46.1,"close":49.45,"volume":6803534,"date":"2010-02-12","ma20":48.9425,"prev_close":46.1,"prev_ma20":48.81,"cross_above_ma20":true,"ma20_distance_pct":1.0369310926,"stock_name":"一詮","industry_category":"光電業","type":"twse"},{"stock_id":"2509","last_trade_date":"2010-02-10","open":24.3,"high":26.5,"low":24.1,"close":25.8,"volume":4835345,"date":"2010-02-12","ma20":25.4975,"prev_close":24.05,"prev_ma20":25.5525,"cross_above_ma20":true,"ma20_distance_pct":1.1863908226,"stock_name":"全坤建","industry_category":"建材營造","type":"twse"},{"stock_id":"2516","last_trade_date":"2010-02-10","open":6.7,"high":7.43,"low":6.35,"close":7.43,"volume":2535675,"date":"2010-02-12","ma20":7.234,"prev_close":6.41,"prev_ma20":7.216,"cross_above_ma20":true,"ma20_distance_pct":2.7094277025,"stock_name":"新建","industry_category":"建材營造","type":"twse"},{"stock_id":"2530","last_trade_date":"2010-02-10","open":10.95,"high":11.8,"low":10.6,"close":11.35,"volume":5508630,"date":"2010-02-12","ma20":11.1345,"prev_close":10.55,"prev_ma20":10.9465,"cross_above_ma20":true,"ma20_distance_pct":1.9354259284,"stock_name":"華建","industry_category":"建材營造","type":"twse"},{"stock_id":"2534","last_trade_date":"2010-02-10","open":15.85,"high":18.1,"low":15.8,"close":17.6,"volume":24330810,"date":"2010-02-12","ma20":16.05,"prev_close":15.85,"prev_ma20":15.8875,"cross_above_ma20":true,"ma20_distance_pct":9.6573208723,"stock_name":"宏盛","industry_category":"建材營造","type":"twse"},{"stock_id":"2542","last_trade_date":"2010-02-10","open":45.95,"high":49.2,"low":45.6,"close":48.5,"volume":28030858,"date":"2010-02-12","ma20":46.0,"prev_close":45.2,"prev_ma20":45.55,"cross_above_ma20":true,"ma20_distance_pct":5.4347826087,"stock_name":"興富發","industry_category":"建材營造","type":"twse"},{"stock_id":"2543","last_trade_date":"2010-02-10","open":6.0,"high":6.69,"low":6.0,"close":6.62,"volume":4293910,"date":"2010-02-12","ma20":6.3795,"prev_close":6.1,"prev_ma20":6.379,"cross_above_ma20":true,"ma20_distance_pct":3.7698879223,"stock_name":"皇昌","industry_category":"建材營造","type":"twse"},{"stock_id":"2636","last_trade_date":"2010-02-10","open":18.8,"high":19.05,"low":18.7,"close":19.0,"volume":527436,"date":"2010-02-12","ma20":18.7075,"prev_close":18.75,"prev_ma20":18.7825,"cross_above_ma20":true,"ma20_distance_pct":1.5635440331,"stock_name":"台驊控股","industry_category":"航運業","type":"twse"},{"stock_id":"2637","last_trade_date":"2010-02-10","open":42.54,"high":43.15,"low":41.0,"close":43.15,"volume":2545400,"date":"2010-02-12","ma20":43.0825,"prev_close":43.0,"prev_ma20":43.175,"cross_above_ma20":true,"ma20_distance_pct":0.1566761446,"stock_name":"慧洋-KY","industry_category":"航運業","type":"twse"},{"stock_id":"2904","last_trade_date":"2010-02-10","open":12.7,"high":14.15,"low":12.5,"close":14.1,"volume":1407001,"date":"2010-02-12","ma20":13.265,"prev_close":12.45,"prev_ma20":13.1725,"cross_above_ma20":true,"ma20_distance_pct":6.2947606483,"stock_name":"匯僑","industry_category":"其他","type":"twse"},{"stock_id":"2908","last_trade_date":"2010-02-10","open":15.9,"high":16.7,"low":15.4,"close":16.6,"volume":11809568,"date":"2010-02-12","ma20":16.245,"prev_close":15.8,"prev_ma20":16.1625,"cross_above_ma20":true,"ma20_distance_pct":2.1852877809,"stock_name":"特力","industry_category":"貿易百貨","type":"twse"},{"stock_id":"3032","last_trade_date":"2010-02-10","open":13.25,"high":14.35,"low":13.2,"close":14.0,"volume":504656,"date":"2010-02-12","ma20":13.805,"prev_close":13.25,"prev_ma20":13.695,"cross_above_ma20":true,"ma20_distance_pct":1.4125316914,"stock_name":"偉訓","industry_category":"電子工業","type":"twse"},{"stock_id":"3033","last_trade_date":"2010-02-10","open":18.4,"high":19.15,"low":18.1,"close":19.05,"volume":2574184,"date":"2010-02-12","ma20":19.0175,"prev_close":18.2,"prev_ma20":18.9125,"cross_above_ma20":true,"ma20_distance_pct":0.1708952281,"stock_name":"威健","industry_category":"電子工業","type":"twse"},{"stock_id":"3042","last_trade_date":"2010-02-10","open":46.5,"high":51.5,"low":46.35,"close":50.1,"volume":7411672,"date":"2010-02-12","ma20":49.38,"prev_close":46.35,"prev_ma20":49.065,"cross_above_ma20":true,"ma20_distance_pct":1.4580801944,"stock_name":"晶技","industry_category":"電子工業","type":"twse"},{"stock_id":"3048","last_trade_date":"2010-02-10","open":15.4,"high":17.15,"low":15.4,"close":17.1,"volume":1485481,"date":"2010-02-12","ma20":16.095,"prev_close":15.5,"prev_ma20":15.8325,"cross_above_ma20":true,"ma20_distance_pct":6.2441752097,"stock_name":"益登","industry_category":"電子通路業","type":"twse"},{"stock_id":"3049","last_trade_date":"2010-02-10","open":19.3,"high":22.2,"low":19.1,"close":21.7,"volume":50436547,"date":"2010-02-12","ma20":21.6325,"prev_close":19.1,"prev_ma20":21.4125,"cross_above_ma20":true,"ma20_distance_pct":0.3120305096,"stock_name":"精金","industry_category":"光電業","type":"twse"},{"stock_id":"3050","last_trade_date":"2010-02-10","open":13.1,"high":14.35,"low":12.8,"close":14.1,"volume":8994343,"date":"2010-02-12","ma20":13.54,"prev_close":12.95,"prev_ma20":13.495,"cross_above_ma20":true,"ma20_distance_pct":4.1358936484,"stock_name":"鈺德","industry_category":"光電業","type":"twse"},{"stock_id":"3060","last_trade_date":"2010-02-10","open":41.9,"high":45.35,"low":41.5,"close":44.05,"volume":3342249,"date":"2010-02-12","ma20":42.6475,"prev_close":41.25,"prev_ma20":42.2,"cross_above_ma20":true,"ma20_distance_pct":3.2885866698,"stock_name":"銘異","industry_category":"電子工業","type":"twse"},{"stock_id":"3085","last_trade_date":"2010-02-10","open":18.35,"high":20.2,"low":17.9,"close":19.8,"volume":5684378,"date":"2010-02-12","ma20":19.0575,"prev_close":17.15,"prev_ma20":18.8775,"cross_above_ma20":true,"ma20_distance_pct":3.8961038961,"stock_name":"新零售","industry_category":"電子商務業","type":"tpex"},{"stock_id":"3089","last_trade_date":"2010-02-10","open":8.68,"high":9.61,"low":8.4,"close":9.61,"volume":1254015,"date":"2010-02-12","ma20":9.5065,"prev_close":8.65,"prev_ma20":9.394,"cross_above_ma20":true,"ma20_distance_pct":1.0887287645,"stock_name":"億杰","industry_category":"電子零組件業","type":"tpex"},{"stock_id":"3090","last_trade_date":"2010-02-10","open":32.75,"high":33.7,"low":31.9,"close":32.9,"volume":3531370,"date":"2010-02-12","ma20":32.72,"prev_close":32.0,"prev_ma20":32.64,"cross_above_ma20":true,"ma20_distance_pct":0.5501222494,"stock_name":"日電貿","industry_category":"電子工業","type":"twse"},{"stock_id":"3115","last_trade_date":"2010-02-10","open":12.8,"high":13.9,"low":12.75,"close":13.9,"volume":212009,"date":"2010-02-12","ma20":13.675,"prev_close":12.6,"prev_ma20":13.63,"cross_above_ma20":true,"ma20_distance_pct":1.6453382084,"stock_name":"富榮綱","industry_category":"電子零組件業","type":"tpex"},{"stock_id":"3130","last_trade_date":"2010-02-10","open":86.0,"high":87.9,"low":86.0,"close":87.3,"volume":165054,"date":"2010-02-12","ma20":83.635,"prev_close":82.4,"prev_ma20":82.93,"cross_above_ma20":true,"ma20_distance_pct":4.3821366653,"stock_name":"一零四","industry_category":"電子工業","type":"twse"},{"stock_id":"3144","last_trade_date":"2010-02-10","open":13.5,"high":14.1,"low":12.8,"close":14.05,"volume":1428063,"date":"2010-02-12","ma20":13.7635,"prev_close":13.5,"prev_ma20":13.5935,"cross_above_ma20":true,"ma20_distance_pct":2.0815926182,"stock_name":"新揚科","industry_category":"電子零組件業","type":"tpex"},{"stock_id":"3162","last_trade_date":"2010-02-10","open":13.5,"high":15.1,"low":13.2,"close":14.95,"volume":2137023,"date":"2010-02-12","ma20":13.815,"prev_close":13.4,"prev_ma20":13.6425,"cross_above_ma20":true,"ma20_distance_pct":8.2157075642,"stock_name":"精確","industry_category":"電機機械","type":"tpex"},{"stock_id":"3188","last_trade_date":"2010-02-10","open":17.5,"high":19.75,"low":17.15,"close":19.75,"volume":1466895,"date":"2010-02-12","ma20":19.615,"prev_close":17.5,"prev_ma20":19.3925,"cross_above_ma20":true,"ma20_distance_pct":0.6882487892,"stock_name":"鑫龍騰","industry_category":"建材營造","type":"tpex"},{"stock_id":"3322","last_trade_date":"2010-02-10","open":22.9,"high":23.7,"low":22.7,"close":23.45,"volume":2493964,"date":"2010-02-12","ma20":23.27,"prev_close":22.8,"prev_ma20":23.265,"cross_above_ma20":true,"ma20_distance_pct":0.7735281478,"stock_name":"建舜電","industry_category":"電子零組件業","type":"tpex"},{"stock_id":"3332","last_trade_date":"2010-02-10","open":31.5,"high":33.65,"low":31.5,"close":33.4,"volume":172026,"date":"2010-02-12","ma20":32.6275,"prev_close":31.3,"prev_ma20":32.5875,"cross_above_ma20":true,"ma20_distance_pct":2.367634664,"stock_name":"幸康","industry_category":"電子零組件業","type":"tpex"},{"stock_id":"3380","last_trade_date":"2010-02-10","open":26.3,"high":27.6,"low":25.9,"close":27.2,"volume":4326167,"date":"2010-02-12","ma20":26.8475,"prev_close":26.25,"prev_ma20":26.7675,"cross_above_ma20":true,"ma20_distance_pct":1.3129714126,"stock_name":"明泰","industry_category":"通信網路業","type":"twse"},{"stock_id":"3383","last_trade_date":"2010-02-10","open":37.95,"high":43.3,"low":37.5,"close":42.4,"volume":5745766,"date":"2010-02-12","ma20":39.8,"prev_close":37.25,"prev_ma20":39.5975,"cross_above_ma20":true,"ma20_distance_pct":6.5326633166,"stock_name":"新世紀","industry_category":"光電業","type":"twse"},{"stock_id":"3438","last_trade_date":"2010-02-10","open":71.2,"high":82.2,"low":70.3,"close":81.9,"volume":2644583,"date":"2010-02-12","ma20":81.195,"prev_close":71.0,"prev_ma20":80.45,"cross_above_ma20":true,"ma20_distance_pct":0.8682800665,"stock_name":"類比科","industry_category":"半導體業","type":"tpex"},{"stock_id":"3444","last_trade_date":"2010-02-10","open":28.2,"high":31.4,"low":28.0,"close":30.8,"volume":358558,"date":"2010-02-12","ma20":29.1275,"prev_close":28.0,"prev_ma20":28.7325,"cross_above_ma20":true,"ma20_distance_pct":5.7419963952,"stock_name":"利機","industry_category":"電子通路業","type":"tpex"},{"stock_id":"3474","last_trade_date":"2010-02-10","open":21.3,"high":22.9,"low":20.85,"close":22.85,"volume":87239558,"date":"2010-02-12","ma20":22.3125,"prev_close":20.85,"prev_ma20":22.2,"cross_above_ma20":true,"ma20_distance_pct":2.4089635854,"stock_name":"華亞科","industry_category":"半導體業","type":"twse"},{"stock_id":"3479","last_trade_date":"2010-02-10","open":39.25,"high":45.0,"low":39.0,"close":45.0,"volume":448000,"date":"2010-02-12","ma20":44.04,"prev_close":42.0,"prev_ma20":43.79,"cross_above_ma20":true,"ma20_distance_pct":2.1798365123,"stock_name":"安勤","industry_category":"電腦及週邊設備業","type":"tpex"},{"stock_id":"3489","last_trade_date":"2010-02-10","open":19.3,"high":22.55,"low":19.3,"close":22.55,"volume":555536,"date":"2010-02-12","ma20":20.6425,"prev_close":20.05,"prev_ma20":20.535,"cross_above_ma20":true,"ma20_distance_pct":9.2406443018,"stock_name":"森寶","industry_category":"建材營造","type":"tpex"},{"stock_id":"3511","last_trade_date":"2010-02-10","open":71.0,"high":73.0,"low":69.0,"close":71.7,"volume":564163,"date":"2010-02-12","ma20":69.24,"prev_close":68.7,"prev_ma20":69.005,"cross_above_ma20":true,"ma20_distance_pct":3.5528596187,"stock_name":"矽瑪","industry_category":"電子零組件業","type":"tpex"},{"stock_id":"3523","last_trade_date":"2010-02-10","open":60.2,"high":64.3,"low":58.0,"close":62.3,"volume":2525299,"date":"2010-02-12","ma20":61.7775,"prev_close":60.0,"prev_ma20":60.8675,"cross_above_ma20":true,"ma20_distance_pct":0.8457771842,"stock_name":"迎輝","industry_category":"光電業","type":"tpex"},{"stock_id":"3530","last_trade_date":"2010-02-10","open":17.89,"high":17.89,"low":17.89,"close":17.89,"volume":0,"date":"2010-02-12","ma20":17.6035,"prev_close":17.4,"prev_ma20":17.624,"cross_above_ma20":true,"ma20_distance_pct":1.6275172551,"stock_name":"晶相光","industry_category":"半導體業","type":"twse"},{"stock_id":"3534","last_trade_date":"2010-02-10","open":103.0,"high":111.5,"low":102.5,"close":107.0,"volume":9029558,"date":"2010-02-12","ma20":103.4,"prev_close":102.0,"prev_ma20":102.47,"cross_above_ma20":true,"ma20_distance_pct":3.4816247582,"stock_name":"雷凌","industry_category":"電子工業","type":"twse"},{"stock_id":"3552","last_trade_date":"2010-02-10","open":108.5,"high":113.0,"low":107.5,"close":111.0,"volume":108154,"date":"2010-02-12","ma20":110.115,"prev_close":108.0,"prev_ma20":109.225,"cross_above_ma20":true,"ma20_distance_pct":0.8037052173,"stock_name":"同致","industry_category":"其他電子類","type":"tpex"},{"stock_id":"3570","last_trade_date":"2010-02-10","open":29.95,"high":33.9,"low":29.05,"close":32.3,"volume":840705,"date":"2010-02-12","ma20":30.16,"prev_close":29.3,"prev_ma20":30.12,"cross_above_ma20":true,"ma20_distance_pct":7.0954907162,"stock_name":"大塚","industry_category":"資訊服務業","type":"tpex"},{"stock_id":"3576","last_trade_date":"2010-02-10","open":55.5,"high":61.9,"low":53.6,"close":61.9,"volume":18124198,"date":"2010-02-12","ma20":59.305,"prev_close":55.0,"prev_ma20":58.245,"cross_above_ma20":true,"ma20_distance_pct":4.3756850181,"stock_name":"聯合再生","industry_category":"光電業","type":"twse"},{"stock_id":"3584","last_trade_date":"2010-02-10","open":59.76,"high":65.3,"low":58.5,"close":62.5,"volume":1002200,"date":"2010-02-12","ma20":61.145,"prev_close":59.5,"prev_ma20":61.275,"cross_above_ma20":true,"ma20_distance_pct":2.2160438302,"stock_name":"介面","industry_category":"光電業","type":"twse"},{"stock_id":"3587","last_trade_date":"2010-02-10","open":23.9,"high":25.6,"low":22.6,"close":25.4,"volume":492897,"date":"2010-02-12","ma20":24.58,"prev_close":22.45,"prev_ma20":24.485,"cross_above_ma20":true,"ma20_distance_pct":3.3360455655,"stock_name":"閎康","industry_category":"其他電子類","type":"tpex"},{"stock_id":"3631","last_trade_date":"2010-02-10","open":62.76,"high":66.0,"low":60.0,"close":65.5,"volume":375000,"date":"2010-02-12","ma20":59.5465,"prev_close":57.0,"prev_ma20":59.1765,"cross_above_ma20":true,"ma20_distance_pct":9.9980687362,"stock_name":"晟楠","industry_category":"電子零組件業","type":"tpex"},{"stock_id":"3702","last_trade_date":"2010-02-10","open":46.9,"high":50.8,"low":46.6,"close":50.5,"volume":13325595,"date":"2010-02-12","ma20":49.2675,"prev_close":46.9,"prev_ma20":48.9475,"cross_above_ma20":true,"ma20_distance_pct":2.5016491602,"stock_name":"大聯大","industry_category":"電子工業","type":"twse"},{"stock_id":"4420","last_trade_date":"2010-02-10","open":16.05,"high":16.45,"low":16.05,"close":16.35,"volume":60746,"date":"2010-02-12","ma20":16.315,"prev_close":16.05,"prev_ma20":16.345,"cross_above_ma20":true,"ma20_distance_pct":0.2145265093,"stock_name":"光明","industry_category":"紡織纖維","type":"tpex"},{"stock_id":"4510","last_trade_date":"2010-02-10","open":7.97,"high":8.14,"low":7.89,"close":8.14,"volume":649507,"date":"2010-02-12","ma20":8.01,"prev_close":7.88,"prev_ma20":7.992,"cross_above_ma20":true,"ma20_distance_pct":1.6229712859,"stock_name":"高鋒","industry_category":"電機機械","type":"tpex"},{"stock_id":"4609","last_trade_date":"2010-02-10","open":20.3,"high":21.4,"low":19.7,"close":21.4,"volume":197852,"date":"2010-02-12","ma20":20.17,"prev_close":19.6,"prev_ma20":19.99,"cross_above_ma20":true,"ma20_distance_pct":6.0981655925,"stock_name":"唐鋒","industry_category":"電器電纜","type":"tpex"},{"stock_id":"4702","last_trade_date":"2010-02-10","open":4.63,"high":5.37,"low":4.63,"close":5.29,"volume":601019,"date":"2010-02-12","ma20":4.71,"prev_close":4.62,"prev_ma20":4.6915,"cross_above_ma20":true,"ma20_distance_pct":12.3142250531,"stock_name":"中美實","industry_category":"化學工業","type":"tpex"},{"stock_id":"4706","last_trade_date":"2010-02-10","open":11.4,"high":12.7,"low":11.4,"close":12.45,"volume":367000,"date":"2010-02-12","ma20":11.5725,"prev_close":11.3,"prev_ma20":11.4875,"cross_above_ma20":true,"ma20_distance_pct":7.5826312378,"stock_name":"大恭","industry_category":"化學工業","type":"tpex"},{"stock_id":"4714","last_trade_date":"2010-02-10","open":12.8,"high":14.3,"low":12.8,"close":14.05,"volume":356263,"date":"2010-02-12","ma20":13.7,"prev_close":13.0,"prev_ma20":13.497,"cross_above_ma20":true,"ma20_distance_pct":2.5547445255,"stock_name":"永捷","industry_category":"化學工業","type":"tpex"},{"stock_id":"4738","last_trade_date":"2010-02-10","open":64.96,"high":73.5,"low":64.0,"close":67.5,"volume":87100,"date":"2010-02-12","ma20":66.7115,"prev_close":64.0,"prev_ma20":67.4365,"cross_above_ma20":true,"ma20_distance_pct":1.1819551352,"stock_name":"大同精化","industry_category":"化學工業","type":"emerging"},{"stock_id":"4909","last_trade_date":"2010-02-10","open":42.9,"high":45.7,"low":42.8,"close":45.0,"volume":1142415,"date":"2010-02-12","ma20":44.7675,"prev_close":42.5,"prev_ma20":44.5975,"cross_above_ma20":true,"ma20_distance_pct":0.5193499749,"stock_name":"新復興","industry_category":"通信網路業","type":"tpex"},{"stock_id":"5013","last_trade_date":"2010-02-10","open":11.5,"high":12.7,"low":11.5,"close":12.7,"volume":1558702,"date":"2010-02-12","ma20":11.8125,"prev_close":11.6,"prev_ma20":11.725,"cross_above_ma20":true,"ma20_distance_pct":7.5132275132,"stock_name":"強新","industry_category":"鋼鐵工業","type":"tpex"},{"stock_id":"5211","last_trade_date":"2010-02-10","open":35.1,"high":39.0,"low":34.85,"close":38.5,"volume":550252,"date":"2010-02-12","ma20":38.29,"prev_close":35.05,"prev_ma20":38.055,"cross_above_ma20":true,"ma20_distance_pct":0.5484460695,"stock_name":"蒙恬","industry_category":"資訊服務業","type":"tpex"},{"stock_id":"5213","last_trade_date":"2010-02-10","open":28.6,"high":33.85,"low":28.6,"close":33.85,"volume":2506007,"date":"2010-02-12","ma20":33.3175,"prev_close":30.15,"prev_ma20":33.1375,"cross_above_ma20":true,"ma20_distance_pct":1.5982591731,"stock_name":"亞昕","industry_category":"建材營造","type":"tpex"},{"stock_id":"5306","last_trade_date":"2010-02-10","open":5.0,"high":5.7,"low":5.0,"close":5.44,"volume":657014,"date":"2010-02-12","ma20":5.4325,"prev_close":5.24,"prev_ma20":5.4045,"cross_above_ma20":true,"ma20_distance_pct":0.1380579844,"stock_name":"桂盟","industry_category":"其他","type":"twse"},{"stock_id":"5349","last_trade_date":"2010-02-10","open":15.0,"high":17.0,"low":14.75,"close":17.0,"volume":9967517,"date":"2010-02-12","ma20":15.5875,"prev_close":14.6,"prev_ma20":15.4575,"cross_above_ma20":true,"ma20_distance_pct":9.0617481957,"stock_name":"先豐","industry_category":"電子零組件業","type":"tpex"},{"stock_id":"5351","last_trade_date":"2010-02-10","open":20.55,"high":22.85,"low":20.15,"close":22.3,"volume":16560032,"date":"2010-02-12","ma20":21.095,"prev_close":20.55,"prev_ma20":20.7575,"cross_above_ma20":true,"ma20_distance_pct":5.7122540886,"stock_name":"鈺創","industry_category":"半導體業","type":"tpex"},{"stock_id":"5371","last_trade_date":"2010-02-10","open":42.85,"high":48.0,"low":42.05,"close":46.5,"volume":23430986,"date":"2010-02-12","ma20":42.52,"prev_close":42.05,"prev_ma20":42.19,"cross_above_ma20":true,"ma20_distance_pct":9.3603010348,"stock_name":"中光電","industry_category":"光電業","type":"tpex"},{"stock_id":"5383","last_trade_date":"2010-02-10","open":15.6,"high":16.8,"low":15.5,"close":16.8,"volume":1711570,"date":"2010-02-12","ma20":16.55,"prev_close":15.5,"prev_ma20":16.49,"cross_above_ma20":true,"ma20_distance_pct":1.5105740181,"stock_name":"金利","industry_category":"其他電子類","type":"tpex"},{"stock_id":"5388","last_trade_date":"2010-02-10","open":20.2,"high":22.3,"low":19.45,"close":22.0,"volume":3371037,"date":"2010-02-12","ma20":21.8975,"prev_close":20.0,"prev_ma20":21.7125,"cross_above_ma20":true,"ma20_distance_pct":0.4680899646,"stock_name":"中磊","industry_category":"電子工業","type":"twse"},{"stock_id":"5398","last_trade_date":"2010-02-10","open":10.05,"high":11.8,"low":10.05,"close":11.8,"volume":348442,"date":"2010-02-12","ma20":11.1515,"prev_close":10.4,"prev_ma20":10.8745,"cross_above_ma20":true,"ma20_distance_pct":5.8153611622,"stock_name":"慕康生醫","industry_category":"其他","type":"tpex"},{"stock_id":"5434","last_trade_date":"2010-02-10","open":37.5,"high":40.35,"low":37.15,"close":39.3,"volume":4067883,"date":"2010-02-12","ma20":37.9525,"prev_close":37.4,"prev_ma20":37.5475,"cross_above_ma20":true,"ma20_distance_pct":3.550490745,"stock_name":"崇越","industry_category":"電子工業","type":"twse"},{"stock_id":"5439","last_trade_date":"2010-02-10","open":15.05,"high":17.9,"low":15.05,"close":17.9,"volume":1528865,"date":"2010-02-12","ma20":16.0275,"prev_close":15.15,"prev_ma20":15.7975,"cross_above_ma20":true,"ma20_distance_pct":11.6830447668,"stock_name":"高技","industry_category":"電子零組件業","type":"tpex"},{"stock_id":"5443","last_trade_date":"2010-02-10","open":18.1,"high":20.25,"low":17.85,"close":19.75,"volume":16832064,"date":"2010-02-12","ma20":19.3525,"prev_close":17.85,"prev_ma20":18.9675,"cross_above_ma20":true,"ma20_distance_pct":2.0539981914,"stock_name":"均豪","industry_category":"光電業","type":"tpex"},{"stock_id":"5471","last_trade_date":"2010-02-10","open":72.0,"high":78.5,"low":71.0,"close":77.4,"volume":11478262,"date":"2010-02-12","ma20":74.325,"prev_close":72.0,"prev_ma20":73.785,"cross_above_ma20":true,"ma20_distance_pct":4.137235116,"stock_name":"松翰","industry_category":"半導體業","type":"twse"},{"stock_id":"5474","last_trade_date":"2010-02-10","open":21.4,"high":24.2,"low":21.05,"close":23.5,"volume":1580125,"date":"2010-02-12","ma20":23.435,"prev_close":21.4,"prev_ma20":23.185,"cross_above_ma20":true,"ma20_distance_pct":0.2773629187,"stock_name":"聰泰","industry_category":"電腦及週邊設備業","type":"tpex"},{"stock_id":"5489","last_trade_date":"2010-02-10","open":34.6,"high":35.05,"low":34.0,"close":34.8,"volume":222456,"date":"2010-02-12","ma20":34.725,"prev_close":34.6,"prev_ma20":34.72,"cross_above_ma20":true,"ma20_distance_pct":0.2159827214,"stock_name":"彩富","industry_category":"其他電子類","type":"tpex"},{"stock_id":"5490","last_trade_date":"2010-02-10","open":18.95,"high":20.9,"low":18.95,"close":20.3,"volume":1030197,"date":"2010-02-12","ma20":20.0575,"prev_close":19.05,"prev_ma20":19.9425,"cross_above_ma20":true,"ma20_distance_pct":1.2090240558,"stock_name":"同亨","industry_category":"電腦及週邊設備業","type":"tpex"},{"stock_id":"5493","last_trade_date":"2010-02-10","open":18.7,"high":20.4,"low":18.45,"close":20.1,"volume":355242,"date":"2010-02-12","ma20":19.175,"prev_close":18.8,"prev_ma20":19.0125,"cross_above_ma20":true,"ma20_distance_pct":4.8239895698,"stock_name":"三聯","industry_category":"其他電子類","type":"tpex"},{"stock_id":"5498","last_trade_date":"2010-02-10","open":7.8,"high":8.75,"low":7.61,"close":8.56,"volume":1875295,"date":"2010-02-12","ma20":8.051,"prev_close":7.78,"prev_ma20":7.932,"cross_above_ma20":true,"ma20_distance_pct":6.3221960005,"stock_name":"凱崴","industry_category":"電子零組件業","type":"tpex"},{"stock_id":"5508","last_trade_date":"2010-02-10","open":36.8,"high":39.85,"low":36.6,"close":39.15,"volume":1049127,"date":"2010-02-12","ma20":38.7025,"prev_close":36.8,"prev_ma20":38.735,"cross_above_ma20":true,"ma20_distance_pct":1.1562560558,"stock_name":"永信建","industry_category":"建材營造","type":"tpex"},{"stock_id":"5604","last_trade_date":"2010-02-10","open":20.2,"high":21.65,"low":20.1,"close":21.65,"volume":487716,"date":"2010-02-12","ma20":21.0475,"prev_close":20.2,"prev_ma20":20.985,"cross_above_ma20":true,"ma20_distance_pct":2.8625727521,"stock_name":"中連貨","industry_category":"航運業","type":"tpex"},{"stock_id":"5701","last_trade_date":"2010-02-10","open":12.8,"high":13.65,"low":12.6,"close":13.35,"volume":17640034,"date":"2010-02-12","ma20":12.6375,"prev_close":12.5,"prev_ma20":12.67,"cross_above_ma20":true,"ma20_distance_pct":5.6379821958,"stock_name":"劍湖山","industry_category":"觀光事業","type":"tpex"},{"stock_id":"5904","last_trade_date":"2010-02-10","open":27.8,"high":28.3,"low":27.65,"close":28.3,"volume":197232,"date":"2010-02-12","ma20":27.9375,"prev_close":27.8,"prev_ma20":27.885,"cross_above_ma20":true,"ma20_distance_pct":1.2975391499,"stock_name":"寶雅","industry_category":"貿易百貨","type":"tpex"},{"stock_id":"6021","last_trade_date":"2010-02-10","open":16.5,"high":18.0,"low":15.9,"close":17.75,"volume":3343215,"date":"2010-02-12","ma20":17.4625,"prev_close":16.5,"prev_ma20":17.345,"cross_above_ma20":true,"ma20_distance_pct":1.646385111,"stock_name":"美好證","industry_category":"金融業","type":"tpex"},{"stock_id":"6113","last_trade_date":"2010-02-10","open":10.6,"high":13.1,"low":10.6,"close":12.8,"volume":1685429,"date":"2010-02-12","ma20":12.7625,"prev_close":10.85,"prev_ma20":12.618,"cross_above_ma20":true,"ma20_distance_pct":0.2938295788,"stock_name":"亞矽","industry_category":"電子通路業","type":"tpex"},{"stock_id":"6119","last_trade_date":"2010-02-10","open":10.8,"high":11.55,"low":10.7,"close":11.5,"volume":1258437,"date":"2010-02-12","ma20":11.3575,"prev_close":10.9,"prev_ma20":11.285,"cross_above_ma20":true,"ma20_distance_pct":1.2546775259,"stock_name":"大傳","industry_category":"電子通路業","type":"twse"},{"stock_id":"6121","last_trade_date":"2010-02-10","open":179.0,"high":184.0,"low":175.0,"close":183.0,"volume":4083410,"date":"2010-02-12","ma20":179.075,"prev_close":178.0,"prev_ma20":178.9,"cross_above_ma20":true,"ma20_distance_pct":2.1918190702,"stock_name":"新普","industry_category":"電腦及週邊設備業","type":"tpex"},{"stock_id":"6126","last_trade_date":"2010-02-10","open":38.8,"high":42.5,"low":37.1,"close":41.0,"volume":3356328,"date":"2010-02-12","ma20":40.7525,"prev_close":37.8,"prev_ma20":40.595,"cross_above_ma20":true,"ma20_distance_pct":0.607324704,"stock_name":"信音","industry_category":"電子零組件業","type":"tpex"},{"stock_id":"6129","last_trade_date":"2010-02-10","open":20.35,"high":23.3,"low":20.05,"close":22.8,"volume":7326731,"date":"2010-02-12","ma20":21.77,"prev_close":20.25,"prev_ma20":21.345,"cross_above_ma20":true,"ma20_distance_pct":4.7312815802,"stock_name":"普誠","industry_category":"半導體業","type":"tpex"},{"stock_id":"6134","last_trade_date":"2010-02-10","open":69.1,"high":76.5,"low":69.1,"close":75.2,"volume":1447151,"date":"2010-02-12","ma20":74.355,"prev_close":69.0,"prev_ma20":74.3,"cross_above_ma20":true,"ma20_distance_pct":1.1364400511,"stock_name":"萬旭","industry_category":"電子零組件業","type":"tpex"},{"stock_id":"6138","last_trade_date":"2010-02-10","open":38.8,"high":42.5,"low":38.7,"close":42.45,"volume":7383251,"date":"2010-02-12","ma20":41.5975,"prev_close":38.55,"prev_ma20":41.195,"cross_above_ma20":true,"ma20_distance_pct":2.0494020073,"stock_name":"茂達","industry_category":"半導體業","type":"tpex"},{"stock_id":"6145","last_trade_date":"2010-02-10","open":25.15,"high":28.7,"low":24.9,"close":28.2,"volume":14450342,"date":"2010-02-12","ma20":27.3275,"prev_close":24.85,"prev_ma20":26.9275,"cross_above_ma20":true,"ma20_distance_pct":3.1927545513,"stock_name":"勁永","industry_category":"電子工業","type":"twse"},{"stock_id":"6154","last_trade_date":"2010-02-10","open":24.15,"high":26.2,"low":24.15,"close":25.4,"volume":574726,"date":"2010-02-12","ma20":25.295,"prev_close":24.25,"prev_ma20":25.21,"cross_above_ma20":true,"ma20_distance_pct":0.4151017988,"stock_name":"順發","industry_category":"電子通路業","type":"tpex"},{"stock_id":"6164","last_trade_date":"2010-02-10","open":26.0,"high":27.8,"low":25.5,"close":27.4,"volume":2413054,"date":"2010-02-12","ma20":26.7425,"prev_close":26.1,"prev_ma20":26.645,"cross_above_ma20":true,"ma20_distance_pct":2.4586332617,"stock_name":"華興","industry_category":"光電業","type":"twse"},{"stock_id":"6166","last_trade_date":"2010-02-10","open":24.6,"high":26.15,"low":24.0,"close":26.0,"volume":814234,"date":"2010-02-12","ma20":25.7475,"prev_close":24.8,"prev_ma20":25.525,"cross_above_ma20":true,"ma20_distance_pct":0.9806777357,"stock_name":"凌華","industry_category":"電子工業","type":"twse"},{"stock_id":"6168","last_trade_date":"2010-02-10","open":29.4,"high":32.4,"low":29.2,"close":30.95,"volume":3265483,"date":"2010-02-12","ma20":30.6025,"prev_close":29.4,"prev_ma20":30.5125,"cross_above_ma20":true,"ma20_distance_pct":1.1355281431,"stock_name":"宏齊","industry_category":"光電業","type":"twse"},{"stock_id":"6179","last_trade_date":"2010-02-10","open":12.0,"high":13.8,"low":12.0,"close":13.8,"volume":1086718,"date":"2010-02-12","ma20":13.243,"prev_close":12.4,"prev_ma20":12.953,"cross_above_ma20":true,"ma20_distance_pct":4.2059956203,"stock_name":"亞通","industry_category":"其他","type":"tpex"},{"stock_id":"6190","last_trade_date":"2010-02-10","open":15.05,"high":16.45,"low":15.05,"close":16.2,"volume":1235198,"date":"2010-02-12","ma20":16.17,"prev_close":15.5,"prev_ma20":16.1425,"cross_above_ma20":true,"ma20_distance_pct":0.185528757,"stock_name":"萬泰科","industry_category":"通信網路業","type":"tpex"},{"stock_id":"6191","last_trade_date":"2010-02-10","open":20.3,"high":21.75,"low":20.1,"close":21.35,"volume":2481689,"date":"2010-02-12","ma20":20.9075,"prev_close":20.5,"prev_ma20":20.74,"cross_above_ma20":true,"ma20_distance_pct":2.1164653832,"stock_name":"精成科","industry_category":"電子工業","type":"twse"},{"stock_id":"6224","last_trade_date":"2010-02-10","open":50.5,"high":56.5,"low":50.5,"close":55.0,"volume":2548876,"date":"2010-02-12","ma20":53.2275,"prev_close":50.3,"prev_ma20":52.865,"cross_above_ma20":true,"ma20_distance_pct":3.3300455592,"stock_name":"聚鼎","industry_category":"電子零組件業","type":"twse"},{"stock_id":"6244","last_trade_date":"2010-02-10","open":113.0,"high":125.0,"low":111.0,"close":125.0,"volume":21674779,"date":"2010-02-12","ma20":116.875,"prev_close":113.0,"prev_ma20":115.19,"cross_above_ma20":true,"ma20_distance_pct":6.9518716578,"stock_name":"茂迪","industry_category":"光電業","type":"tpex"},{"stock_id":"6275","last_trade_date":"2010-02-10","open":12.2,"high":14.4,"low":12.1,"close":14.4,"volume":1296320,"date":"2010-02-12","ma20":13.3775,"prev_close":12.05,"prev_ma20":13.24,"cross_above_ma20":true,"ma20_distance_pct":7.6434311344,"stock_name":"元山","industry_category":"其他電子類","type":"tpex"},{"stock_id":"6282","last_trade_date":"2010-02-10","open":24.1,"high":26.15,"low":23.9,"close":25.5,"volume":12741685,"date":"2010-02-12","ma20":24.8775,"prev_close":23.9,"prev_ma20":24.6775,"cross_above_ma20":true,"ma20_distance_pct":2.5022610793,"stock_name":"康舒","industry_category":"電子工業","type":"twse"},{"stock_id":"6609","last_trade_date":"2010-02-10","open":14.75,"high":15.1,"low":14.1,"close":15.1,"volume":259535,"date":"2010-02-12","ma20":14.68,"prev_close":14.5,"prev_ma20":14.6075,"cross_above_ma20":true,"ma20_distance_pct":2.8610354223,"stock_name":"瀧澤科","industry_category":"電機機械","type":"tpex"},{"stock_id":"8039","last_trade_date":"2010-02-10","open":48.6,"high":52.8,"low":48.1,"close":51.3,"volume":10219969,"date":"2010-02-12","ma20":50.5425,"prev_close":47.9,"prev_ma20":50.0775,"cross_above_ma20":true,"ma20_distance_pct":1.4987386853,"stock_name":"台虹","industry_category":"電子工業","type":"twse"},{"stock_id":"8049","last_trade_date":"2010-02-10","open":13.0,"high":15.0,"low":13.0,"close":15.0,"volume":1452102,"date":"2010-02-12","ma20":14.5125,"prev_close":13.55,"prev_ma20":14.3425,"cross_above_ma20":true,"ma20_distance_pct":3.3591731266,"stock_name":"晶采","industry_category":"光電業","type":"tpex"},{"stock_id":"8070","last_trade_date":"2010-02-10","open":138.0,"high":148.0,"low":137.0,"close":147.0,"volume":1266369,"date":"2010-02-12","ma20":141.425,"prev_close":138.0,"prev_ma20":139.875,"cross_above_ma20":true,"ma20_distance_pct":3.9420187378,"stock_name":"長華*","industry_category":"電子通路業","type":"twse"},{"stock_id":"8092","last_trade_date":"2010-02-10","open":11.5,"high":12.3,"low":11.05,"close":12.2,"volume":416793,"date":"2010-02-12","ma20":11.383,"prev_close":11.05,"prev_ma20":11.214,"cross_above_ma20":true,"ma20_distance_pct":7.1773697619,"stock_name":"建暐","industry_category":"其他電子類","type":"tpex"},{"stock_id":"8101","last_trade_date":"2010-02-10","open":11.9,"high":13.35,"low":11.7,"close":13.25,"volume":7072158,"date":"2010-02-12","ma20":13.145,"prev_close":12.0,"prev_ma20":13.07,"cross_above_ma20":true,"ma20_distance_pct":0.7987828072,"stock_name":"華冠","industry_category":"電子工業","type":"twse"},{"stock_id":"8103","last_trade_date":"2010-02-10","open":38.5,"high":41.4,"low":38.0,"close":40.2,"volume":5496369,"date":"2010-02-12","ma20":37.9425,"prev_close":37.7,"prev_ma20":37.8225,"cross_above_ma20":true,"ma20_distance_pct":5.9497924491,"stock_name":"瀚荃","industry_category":"電子工業","type":"twse"},{"stock_id":"8111","last_trade_date":"2010-02-10","open":18.35,"high":19.3,"low":17.4,"close":18.95,"volume":2665622,"date":"2010-02-12","ma20":18.56,"prev_close":17.8,"prev_ma20":18.48,"cross_above_ma20":true,"ma20_distance_pct":2.1012931034,"stock_name":"立碁","industry_category":"光電業","type":"tpex"},{"stock_id":"8114","last_trade_date":"2010-02-10","open":54.5,"high":56.5,"low":54.0,"close":55.0,"volume":544342,"date":"2010-02-12","ma20":54.89,"prev_close":54.5,"prev_ma20":54.9,"cross_above_ma20":true,"ma20_distance_pct":0.2004008016,"stock_name":"振樺電","industry_category":"電腦及週邊設備業","type":"twse"},{"stock_id":"8121","last_trade_date":"2010-02-10","open":34.5,"high":37.6,"low":32.5,"close":37.6,"volume":4866799,"date":"2010-02-12","ma20":36.7375,"prev_close":33.9,"prev_ma20":36.3325,"cross_above_ma20":true,"ma20_distance_pct":2.3477373256,"stock_name":"越峰","industry_category":"電子零組件業","type":"tpex"},{"stock_id":"8183","last_trade_date":"2010-02-10","open":10.3,"high":11.2,"low":9.9,"close":10.8,"volume":5386074,"date":"2010-02-12","ma20":10.697,"prev_close":10.3,"prev_ma20":10.5555,"cross_above_ma20":true,"ma20_distance_pct":0.9628867907,"stock_name":"精星","industry_category":"其他電子類","type":"tpex"},{"stock_id":"8199","last_trade_date":"2010-02-09","open":33.15,"high":35.5,"low":33.0,"close":34.0,"volume":1143628,"date":"2010-02-12","ma20":33.165,"prev_close":32.2,"prev_ma20":32.89,"cross_above_ma20":true,"ma20_distance_pct":2.517714458,"stock_name":"廣鎵","industry_category":"光電業","type":"twse"},{"stock_id":"8210","last_trade_date":"2010-02-10","open":22.0,"high":23.95,"low":21.5,"close":23.65,"volume":1307150,"date":"2010-02-12","ma20":23.5775,"prev_close":22.0,"prev_ma20":23.23,"cross_above_ma20":true,"ma20_distance_pct":0.3074965539,"stock_name":"勤誠","industry_category":"電腦及週邊設備業","type":"twse"},{"stock_id":"8240","last_trade_date":"2010-02-10","open":62.4,"high":67.9,"low":62.0,"close":65.5,"volume":2667697,"date":"2010-02-12","ma20":65.04,"prev_close":61.9,"prev_ma20":65.055,"cross_above_ma20":true,"ma20_distance_pct":0.7072570726,"stock_name":"華宏","industry_category":"光電業","type":"tpex"},{"stock_id":"8905","last_trade_date":"2010-02-10","open":14.7,"high":15.05,"low":14.2,"close":15.05,"volume":110000,"date":"2010-02-12","ma20":14.9,"prev_close":14.7,"prev_ma20":14.9025,"cross_above_ma20":true,"ma20_distance_pct":1.0067114094,"stock_name":"裕國","industry_category":"其他","type":"tpex"},{"stock_id":"8923","last_trade_date":"2010-02-10","open":14.5,"high":14.5,"low":14.0,"close":14.45,"volume":18009,"date":"2010-02-12","ma20":14.16,"prev_close":14.0,"prev_ma20":14.1025,"cross_above_ma20":true,"ma20_distance_pct":2.0480225989,"stock_name":"時報","industry_category":"文化創意業","type":"tpex"},{"stock_id":"9925","last_trade_date":"2010-02-10","open":21.3,"high":22.65,"low":21.15,"close":22.5,"volume":2379857,"date":"2010-02-12","ma20":21.75,"prev_close":21.25,"prev_ma20":21.665,"cross_above_ma20":true,"ma20_distance_pct":3.4482758621,"stock_name":"新保","industry_category":"其他","type":"twse"},{"stock_id":"9931","last_trade_date":"2010-02-10","open":17.45,"high":18.35,"low":17.35,"close":17.85,"volume":37001,"date":"2010-02-12","ma20":17.5825,"prev_close":17.5,"prev_ma20":17.57,"cross_above_ma20":true,"ma20_distance_pct":1.5213991184,"stock_name":"欣高","industry_category":"油電燃氣業","type":"twse"},{"stock_id":"9935","last_trade_date":"2010-02-10","open":9.0,"high":10.1,"low":8.8,"close":9.87,"volume":2650511,"date":"2010-02-12","ma20":9.2355,"prev_close":9.0,"prev_ma20":9.079,"cross_above_ma20":true,"ma20_distance_pct":6.8702290076,"stock_name":"慶豐富","industry_category":"其他","type":"twse"},{"stock_id":"9942","last_trade_date":"2010-02-10","open":30.65,"high":31.4,"low":30.2,"close":31.2,"volume":179594,"date":"2010-02-12","ma20":30.995,"prev_close":30.65,"prev_ma20":30.8425,"cross_above_ma20":true,"ma20_distance_pct":0.6613969995,"stock_name":"茂順","industry_category":"其他","type":"twse"},{"stock_id":"9944","last_trade_date":"2010-02-10","open":24.0,"high":25.0,"low":23.5,"close":24.75,"volume":170100,"date":"2010-02-12","ma20":24.435,"prev_close":23.5,"prev_ma20":24.3475,"cross_above_ma20":true,"ma20_distance_pct":1.2891344383,"stock_name":"新麗","industry_category":"其他","type":"twse"},{"stock_id":"9945","last_trade_date":"2010-02-10","open":36.0,"high":40.25,"low":35.8,"close":39.65,"volume":15101936,"date":"2010-02-12","ma20":39.4,"prev_close":35.8,"prev_ma20":39.0325,"cross_above_ma20":true,"ma20_distance_pct":0.6345177665,"stock_name":"潤泰新","industry_category":"其他","type":"twse"}]