[{"stock_id":"3141","date":"2012-12-06","open":6.99,"high":7.0,"low":6.95,"close":7.0,"volume":94000,"ma20":6.8665,"prev_close":6.8,"prev_ma20":6.8765,"cross_above_ma20":true,"ma20_distance_pct":1.9442219471,"stock_name":"晶宏","industry_category":"半導體業","type":"tpex"},{"stock_id":"5240","date":"2012-12-06","open":30.1,"high":30.36,"low":30.0,"close":30.36,"volume":13000,"ma20":29.978,"prev_close":29.6,"prev_ma20":30.0,"cross_above_ma20":true,"ma20_distance_pct":1.2742677964,"stock_name":"建騰","industry_category":"光電業","type":"emerging"}]