[{"stock_id":"1103","date":"2013-02-22","open":14.05,"high":14.05,"low":13.85,"close":13.95,"volume":1607360,"ma20":13.8275,"prev_close":13.85,"prev_ma20":13.865,"cross_above_ma20":true,"ma20_distance_pct":0.8859157476,"stock_name":"嘉泥","industry_category":"水泥工業","type":"twse"},{"stock_id":"1216","date":"2013-02-22","open":52.2,"high":55.4,"low":51.3,"close":54.9,"volume":72766239,"ma20":52.34,"prev_close":51.5,"prev_ma20":52.195,"cross_above_ma20":true,"ma20_distance_pct":4.8910966756,"stock_name":"統一","industry_category":"食品工業","type":"twse"},{"stock_id":"1220","date":"2013-02-22","open":10.55,"high":10.7,"low":10.5,"close":10.65,"volume":222879,"ma20":10.5125,"prev_close":10.5,"prev_ma20":10.53,"cross_above_ma20":true,"ma20_distance_pct":1.3079667063,"stock_name":"台榮","industry_category":"食品工業","type":"twse"},{"stock_id":"1225","date":"2013-02-22","open":13.0,"high":13.35,"low":12.9,"close":13.2,"volume":5529264,"ma20":12.8975,"prev_close":12.9,"prev_ma20":12.9025,"cross_above_ma20":true,"ma20_distance_pct":2.3454157783,"stock_name":"福懋油","industry_category":"食品工業","type":"twse"},{"stock_id":"1234","date":"2013-02-22","open":38.3,"high":39.3,"low":37.75,"close":38.85,"volume":5724654,"ma20":38.035,"prev_close":37.85,"prev_ma20":38.4925,"cross_above_ma20":true,"ma20_distance_pct":2.1427632444,"stock_name":"黑松","industry_category":"食品工業","type":"twse"},{"stock_id":"1316","date":"2013-02-22","open":10.35,"high":11.0,"low":10.2,"close":11.0,"volume":3970371,"ma20":10.267,"prev_close":10.1,"prev_ma20":10.417,"cross_above_ma20":true,"ma20_distance_pct":7.1393785916,"stock_name":"上曜","industry_category":"建材營造","type":"twse"},{"stock_id":"1409","date":"2013-02-22","open":9.6,"high":9.73,"low":9.51,"close":9.63,"volume":20546545,"ma20":9.511,"prev_close":9.51,"prev_ma20":9.542,"cross_above_ma20":true,"ma20_distance_pct":1.2511828409,"stock_name":"新纖","industry_category":"紡織纖維","type":"twse"},{"stock_id":"1416","date":"2013-02-22","open":17.4,"high":18.1,"low":17.25,"close":17.5,"volume":5192175,"ma20":17.39,"prev_close":17.25,"prev_ma20":17.4275,"cross_above_ma20":true,"ma20_distance_pct":0.6325474411,"stock_name":"廣豐","industry_category":"其他","type":"twse"},{"stock_id":"1443","date":"2013-02-22","open":5.29,"high":5.58,"low":5.26,"close":5.43,"volume":909890,"ma20":5.267,"prev_close":5.23,"prev_ma20":5.2605,"cross_above_ma20":true,"ma20_distance_pct":3.0947408392,"stock_name":"立益","industry_category":"紡織纖維","type":"twse"},{"stock_id":"1474","date":"2013-02-22","open":7.09,"high":7.09,"low":6.96,"close":6.96,"volume":146503,"ma20":6.9515,"prev_close":6.95,"prev_ma20":6.972,"cross_above_ma20":true,"ma20_distance_pct":0.1222757678,"stock_name":"弘裕","industry_category":"紡織纖維","type":"twse"},{"stock_id":"1512","date":"2013-02-22","open":7.66,"high":8.12,"low":7.65,"close":8.01,"volume":2157772,"ma20":7.785,"prev_close":7.76,"prev_ma20":7.838,"cross_above_ma20":true,"ma20_distance_pct":2.8901734104,"stock_name":"瑞利","industry_category":"汽車工業","type":"twse"},{"stock_id":"1519","date":"2013-02-22","open":11.9,"high":12.1,"low":11.75,"close":12.05,"volume":1489011,"ma20":11.9925,"prev_close":11.8,"prev_ma20":12.055,"cross_above_ma20":true,"ma20_distance_pct":0.4794663331,"stock_name":"華城","industry_category":"電機機械","type":"twse"},{"stock_id":"1522","date":"2013-02-22","open":10.7,"high":11.25,"low":10.55,"close":10.9,"volume":2595463,"ma20":10.75,"prev_close":10.7,"prev_ma20":10.81,"cross_above_ma20":true,"ma20_distance_pct":1.3953488372,"stock_name":"堤維西","industry_category":"汽車工業","type":"twse"},{"stock_id":"1525","date":"2013-02-22","open":48.5,"high":48.5,"low":46.35,"close":47.2,"volume":866544,"ma20":46.725,"prev_close":46.65,"prev_ma20":46.905,"cross_above_ma20":true,"ma20_distance_pct":1.0165864098,"stock_name":"江申","industry_category":"汽車工業","type":"twse"},{"stock_id":"1526","date":"2013-02-22","open":7.0,"high":7.15,"low":6.95,"close":7.03,"volume":150551,"ma20":6.9485,"prev_close":6.88,"prev_ma20":6.974,"cross_above_ma20":true,"ma20_distance_pct":1.1729150176,"stock_name":"日馳","industry_category":"電機機械","type":"twse"},{"stock_id":"1569","date":"2013-02-22","open":36.5,"high":39.9,"low":35.5,"close":38.85,"volume":7254522,"ma20":37.4075,"prev_close":34.75,"prev_ma20":38.015,"cross_above_ma20":true,"ma20_distance_pct":3.8561785738,"stock_name":"濱川","industry_category":"電腦及週邊設備業","type":"tpex"},{"stock_id":"1593","date":"2013-02-22","open":25.1,"high":28.0,"low":25.1,"close":27.6,"volume":615093,"ma20":25.7025,"prev_close":25.0,"prev_ma20":25.7625,"cross_above_ma20":true,"ma20_distance_pct":7.3825503356,"stock_name":"祺驊","industry_category":"生技醫療業","type":"tpex"},{"stock_id":"1609","date":"2013-02-22","open":7.05,"high":7.29,"low":7.05,"close":7.26,"volume":4248046,"ma20":7.048,"prev_close":7.05,"prev_ma20":7.053,"cross_above_ma20":true,"ma20_distance_pct":3.0079455165,"stock_name":"大亞","industry_category":"電器電纜","type":"twse"},{"stock_id":"1611","date":"2013-02-22","open":17.55,"high":17.9,"low":17.5,"close":17.85,"volume":1620521,"ma20":17.6075,"prev_close":17.55,"prev_ma20":17.77,"cross_above_ma20":true,"ma20_distance_pct":1.3772540111,"stock_name":"中電","industry_category":"電器電纜","type":"twse"},{"stock_id":"1618","date":"2013-02-22","open":11.1,"high":11.4,"low":11.0,"close":11.2,"volume":2571977,"ma20":10.98,"prev_close":11.0,"prev_ma20":11.0075,"cross_above_ma20":true,"ma20_distance_pct":2.0036429872,"stock_name":"合機","industry_category":"電器電纜","type":"twse"},{"stock_id":"1701","date":"2013-02-22","open":20.4,"high":20.8,"low":20.1,"close":20.5,"volume":7822742,"ma20":19.9125,"prev_close":19.75,"prev_ma20":19.935,"cross_above_ma20":true,"ma20_distance_pct":2.9504080352,"stock_name":"中化","industry_category":"生技醫療業","type":"twse"},{"stock_id":"1702","date":"2013-02-22","open":28.4,"high":29.15,"low":28.0,"close":28.75,"volume":4715484,"ma20":28.485,"prev_close":28.0,"prev_ma20":28.5875,"cross_above_ma20":true,"ma20_distance_pct":0.9303142005,"stock_name":"南僑","industry_category":"食品工業","type":"twse"},{"stock_id":"1708","date":"2013-02-22","open":32.8,"high":33.7,"low":32.7,"close":33.4,"volume":1719261,"ma20":32.59,"prev_close":32.45,"prev_ma20":32.57,"cross_above_ma20":true,"ma20_distance_pct":2.485424977,"stock_name":"東鹼","industry_category":"化學生技醫療","type":"twse"},{"stock_id":"1731","date":"2013-02-22","open":15.65,"high":16.25,"low":15.35,"close":16.1,"volume":5082357,"ma20":15.4975,"prev_close":15.35,"prev_ma20":15.4475,"cross_above_ma20":true,"ma20_distance_pct":3.8877238264,"stock_name":"美吾華","industry_category":"化學生技醫療","type":"twse"},{"stock_id":"1737","date":"2013-02-22","open":20.3,"high":20.9,"low":20.25,"close":20.9,"volume":2755185,"ma20":20.69,"prev_close":20.3,"prev_ma20":20.785,"cross_above_ma20":true,"ma20_distance_pct":1.0149830836,"stock_name":"臺鹽","industry_category":"食品工業","type":"twse"},{"stock_id":"1742","date":"2013-02-22","open":14.1,"high":14.15,"low":13.7,"close":14.1,"volume":210641,"ma20":13.955,"prev_close":13.85,"prev_ma20":14.04,"cross_above_ma20":true,"ma20_distance_pct":1.0390541025,"stock_name":"台蠟","industry_category":"化學工業","type":"tpex"},{"stock_id":"1752","date":"2013-02-22","open":39.7,"high":42.7,"low":39.3,"close":42.4,"volume":4362522,"ma20":40.43,"prev_close":39.25,"prev_ma20":40.14,"cross_above_ma20":true,"ma20_distance_pct":4.8726193421,"stock_name":"南光","industry_category":"化學生技醫療","type":"twse"},{"stock_id":"1762","date":"2013-02-22","open":51.7,"high":53.8,"low":51.5,"close":53.0,"volume":3896733,"ma20":51.28,"prev_close":50.8,"prev_ma20":51.45,"cross_above_ma20":true,"ma20_distance_pct":3.3541341654,"stock_name":"中化生","industry_category":"化學生技醫療","type":"twse"},{"stock_id":"1776","date":"2013-02-22","open":17.7,"high":18.21,"low":17.7,"close":18.21,"volume":0,"ma20":17.8435,"prev_close":17.4,"prev_ma20":17.923,"cross_above_ma20":true,"ma20_distance_pct":2.0539692325,"stock_name":"展宇","industry_category":"化學生技醫療","type":"twse"},{"stock_id":"1784","date":"2013-02-22","open":38.85,"high":44.2,"low":38.5,"close":43.5,"volume":4741416,"ma20":39.2225,"prev_close":38.75,"prev_ma20":39.3975,"cross_above_ma20":true,"ma20_distance_pct":10.9057301294,"stock_name":"訊聯","industry_category":"生技醫療業","type":"tpex"},{"stock_id":"2109","date":"2013-02-22","open":6.16,"high":6.55,"low":6.13,"close":6.4,"volume":3358417,"ma20":6.1505,"prev_close":6.15,"prev_ma20":6.164,"cross_above_ma20":true,"ma20_distance_pct":4.0565807658,"stock_name":"華豐","industry_category":"橡膠工業","type":"twse"},{"stock_id":"2201","date":"2013-02-22","open":54.4,"high":55.1,"low":53.2,"close":54.6,"volume":15682677,"ma20":53.875,"prev_close":53.8,"prev_ma20":54.095,"cross_above_ma20":true,"ma20_distance_pct":1.3457076566,"stock_name":"裕隆","industry_category":"汽車工業","type":"twse"},{"stock_id":"2305","date":"2013-02-22","open":2.93,"high":2.93,"low":2.87,"close":2.91,"volume":489805,"ma20":2.878,"prev_close":2.86,"prev_ma20":2.8855,"cross_above_ma20":true,"ma20_distance_pct":1.1118832523,"stock_name":"全友","industry_category":"電子工業","type":"twse"},{"stock_id":"2325","date":"2013-02-22","open":30.65,"high":31.15,"low":30.1,"close":31.0,"volume":41439397,"ma20":30.6425,"prev_close":30.2,"prev_ma20":30.725,"cross_above_ma20":true,"ma20_distance_pct":1.1666802643,"stock_name":"矽品","industry_category":"電子工業","type":"twse"},{"stock_id":"2337","date":"2013-02-22","open":8.4,"high":8.78,"low":8.3,"close":8.64,"volume":52515304,"ma20":8.417,"prev_close":8.25,"prev_ma20":8.4745,"cross_above_ma20":true,"ma20_distance_pct":2.6494000238,"stock_name":"旺宏","industry_category":"半導體業","type":"twse"},{"stock_id":"2340","date":"2013-02-22","open":11.8,"high":12.2,"low":11.7,"close":11.95,"volume":8274603,"ma20":11.7525,"prev_close":11.6,"prev_ma20":11.815,"cross_above_ma20":true,"ma20_distance_pct":1.680493512,"stock_name":"台亞","industry_category":"光電業","type":"twse"},{"stock_id":"2353","date":"2013-02-22","open":25.4,"high":26.25,"low":24.95,"close":25.8,"volume":96696290,"ma20":25.105,"prev_close":25.1,"prev_ma20":25.255,"cross_above_ma20":true,"ma20_distance_pct":2.7683728341,"stock_name":"宏碁","industry_category":"電腦及週邊設備業","type":"twse"},{"stock_id":"2367","date":"2013-02-22","open":9.55,"high":10.45,"low":9.36,"close":9.87,"volume":12179508,"ma20":9.5505,"prev_close":9.35,"prev_ma20":9.582,"cross_above_ma20":true,"ma20_distance_pct":3.3453745877,"stock_name":"燿華","industry_category":"電子工業","type":"twse"},{"stock_id":"2384","date":"2013-02-22","open":13.7,"high":14.7,"low":13.5,"close":14.25,"volume":147151297,"ma20":13.8475,"prev_close":13.45,"prev_ma20":13.9025,"cross_above_ma20":true,"ma20_distance_pct":2.9066618523,"stock_name":"勝華","industry_category":"光電業","type":"twse"},{"stock_id":"2387","date":"2013-02-22","open":12.25,"high":13.7,"low":12.05,"close":13.2,"volume":25301677,"ma20":12.5275,"prev_close":12.2,"prev_ma20":12.53,"cross_above_ma20":true,"ma20_distance_pct":5.368189982,"stock_name":"精元","industry_category":"電子工業","type":"twse"},{"stock_id":"2401","date":"2013-02-22","open":8.61,"high":9.09,"low":8.51,"close":8.96,"volume":10117464,"ma20":8.8305,"prev_close":8.57,"prev_ma20":8.881,"cross_above_ma20":true,"ma20_distance_pct":1.4665081252,"stock_name":"凌陽","industry_category":"半導體業","type":"twse"},{"stock_id":"2404","date":"2013-02-22","open":24.5,"high":24.95,"low":24.25,"close":24.85,"volume":1638505,"ma20":24.7625,"prev_close":24.4,"prev_ma20":24.7625,"cross_above_ma20":true,"ma20_distance_pct":0.3533568905,"stock_name":"漢唐","industry_category":"其他電子業","type":"twse"},{"stock_id":"2409","date":"2013-02-22","open":11.55,"high":13.45,"low":11.5,"close":13.0,"volume":790516040,"ma20":12.07,"prev_close":11.3,"prev_ma20":11.95,"cross_above_ma20":true,"ma20_distance_pct":7.7050538525,"stock_name":"友達","industry_category":"光電業","type":"twse"},{"stock_id":"2423","date":"2013-02-22","open":17.6,"high":18.3,"low":17.5,"close":18.0,"volume":221577,"ma20":17.63,"prev_close":17.45,"prev_ma20":17.68,"cross_above_ma20":true,"ma20_distance_pct":2.0986954056,"stock_name":"固緯","industry_category":"其他電子業","type":"twse"},{"stock_id":"2425","date":"2013-02-22","open":40.6,"high":46.0,"low":40.6,"close":43.8,"volume":652264,"ma20":43.585,"prev_close":40.6,"prev_ma20":43.17,"cross_above_ma20":true,"ma20_distance_pct":0.4932889756,"stock_name":"承啟","industry_category":"電子工業","type":"twse"},{"stock_id":"2426","date":"2013-02-22","open":7.4,"high":7.68,"low":7.35,"close":7.43,"volume":4187475,"ma20":7.3045,"prev_close":7.32,"prev_ma20":7.3835,"cross_above_ma20":true,"ma20_distance_pct":1.7181189678,"stock_name":"鼎元","industry_category":"光電業","type":"twse"},{"stock_id":"2430","date":"2013-02-22","open":58.7,"high":60.3,"low":58.1,"close":59.3,"volume":1165102,"ma20":59.035,"prev_close":58.7,"prev_ma20":59.205,"cross_above_ma20":true,"ma20_distance_pct":0.4488862539,"stock_name":"燦坤","industry_category":"電子工業","type":"twse"},{"stock_id":"2460","date":"2013-02-22","open":12.1,"high":12.4,"low":11.95,"close":12.25,"volume":669671,"ma20":12.0075,"prev_close":12.0,"prev_ma20":12.0325,"cross_above_ma20":true,"ma20_distance_pct":2.0195711014,"stock_name":"建通","industry_category":"電子工業","type":"twse"},{"stock_id":"2465","date":"2013-02-22","open":4.5,"high":4.66,"low":4.36,"close":4.51,"volume":870573,"ma20":4.508,"prev_close":4.48,"prev_ma20":4.5325,"cross_above_ma20":true,"ma20_distance_pct":0.0443655723,"stock_name":"麗臺","industry_category":"電子工業","type":"twse"},{"stock_id":"2474","date":"2013-02-22","open":136.0,"high":141.0,"low":133.0,"close":138.0,"volume":75364499,"ma20":136.825,"prev_close":134.5,"prev_ma20":136.825,"cross_above_ma20":true,"ma20_distance_pct":0.8587611913,"stock_name":"可成","industry_category":"其他電子業","type":"twse"},{"stock_id":"2485","date":"2013-02-22","open":24.75,"high":26.6,"low":24.2,"close":26.0,"volume":15879371,"ma20":24.9225,"prev_close":24.6,"prev_ma20":25.09,"cross_above_ma20":true,"ma20_distance_pct":4.3234025479,"stock_name":"兆赫","industry_category":"通信網路業","type":"twse"},{"stock_id":"2492","date":"2013-02-22","open":6.99,"high":7.13,"low":6.92,"close":7.0,"volume":5470460,"ma20":6.901,"prev_close":6.92,"prev_ma20":6.931,"cross_above_ma20":true,"ma20_distance_pct":1.4345746993,"stock_name":"華新科","industry_category":"電子工業","type":"twse"},{"stock_id":"2497","date":"2013-02-22","open":26.45,"high":29.1,"low":26.0,"close":28.05,"volume":7804012,"ma20":27.255,"prev_close":25.9,"prev_ma20":27.625,"cross_above_ma20":true,"ma20_distance_pct":2.9168959824,"stock_name":"怡利電","industry_category":"汽車工業","type":"twse"},{"stock_id":"2499","date":"2013-02-22","open":27.5,"high":28.8,"low":27.2,"close":27.95,"volume":16255007,"ma20":26.885,"prev_close":27.05,"prev_ma20":27.0625,"cross_above_ma20":true,"ma20_distance_pct":3.9613167194,"stock_name":"東貝","industry_category":"電子工業","type":"twse"},{"stock_id":"2516","date":"2013-02-22","open":8.5,"high":8.82,"low":8.41,"close":8.64,"volume":6394132,"ma20":8.452,"prev_close":8.41,"prev_ma20":8.4575,"cross_above_ma20":true,"ma20_distance_pct":2.2243256034,"stock_name":"新建","industry_category":"建材營造","type":"twse"},{"stock_id":"2706","date":"2013-02-22","open":19.8,"high":19.8,"low":19.45,"close":19.6,"volume":608693,"ma20":19.49,"prev_close":19.55,"prev_ma20":19.5625,"cross_above_ma20":true,"ma20_distance_pct":0.5643919959,"stock_name":"第一店","industry_category":"觀光事業","type":"twse"},{"stock_id":"2723","date":"2013-02-22","open":203.0,"high":203.0,"low":198.5,"close":200.0,"volume":1485509,"ma20":199.575,"prev_close":200.0,"prev_ma20":200.65,"cross_above_ma20":true,"ma20_distance_pct":0.2129525241,"stock_name":"美食-KY","industry_category":"觀光事業","type":"twse"},{"stock_id":"2724","date":"2013-02-22","open":58.6,"high":65.5,"low":58.6,"close":63.3,"volume":1145084,"ma20":58.3775,"prev_close":59.2,"prev_ma20":59.2275,"cross_above_ma20":true,"ma20_distance_pct":8.4321870584,"stock_name":"富驛-KY","industry_category":"觀光事業","type":"tpex"},{"stock_id":"3006","date":"2013-02-22","open":22.2,"high":24.0,"low":22.05,"close":23.15,"volume":5983706,"ma20":22.1375,"prev_close":22.05,"prev_ma20":22.24,"cross_above_ma20":true,"ma20_distance_pct":4.5736871824,"stock_name":"晶豪科","industry_category":"半導體業","type":"twse"},{"stock_id":"3014","date":"2013-02-22","open":23.5,"high":25.65,"low":23.25,"close":25.4,"volume":17908728,"ma20":23.4925,"prev_close":23.15,"prev_ma20":23.525,"cross_above_ma20":true,"ma20_distance_pct":8.1196126423,"stock_name":"聯陽","industry_category":"半導體業","type":"twse"},{"stock_id":"3016","date":"2013-02-22","open":12.8,"high":13.05,"low":12.65,"close":12.65,"volume":1674770,"ma20":12.5525,"prev_close":12.55,"prev_ma20":12.655,"cross_above_ma20":true,"ma20_distance_pct":0.7767377017,"stock_name":"嘉晶","industry_category":"半導體業","type":"twse"},{"stock_id":"3029","date":"2013-02-22","open":14.0,"high":14.5,"low":13.9,"close":14.2,"volume":1834038,"ma20":13.8075,"prev_close":13.9,"prev_ma20":13.915,"cross_above_ma20":true,"ma20_distance_pct":2.8426579757,"stock_name":"零壹","industry_category":"資訊服務業","type":"twse"},{"stock_id":"3040","date":"2013-02-22","open":14.7,"high":16.5,"low":14.35,"close":15.85,"volume":4220117,"ma20":14.74,"prev_close":14.65,"prev_ma20":14.6825,"cross_above_ma20":true,"ma20_distance_pct":7.5305291723,"stock_name":"遠見","industry_category":"其他","type":"twse"},{"stock_id":"3078","date":"2013-02-22","open":9.1,"high":9.35,"low":9.1,"close":9.3,"volume":1237547,"ma20":9.2785,"prev_close":9.1,"prev_ma20":9.3385,"cross_above_ma20":true,"ma20_distance_pct":0.231718489,"stock_name":"僑威","industry_category":"電子零組件業","type":"tpex"},{"stock_id":"3093","date":"2013-02-22","open":42.5,"high":43.9,"low":42.5,"close":43.45,"volume":53181,"ma20":43.0575,"prev_close":42.3,"prev_ma20":43.1525,"cross_above_ma20":true,"ma20_distance_pct":0.9115717355,"stock_name":"港建*","industry_category":"其他電子類","type":"tpex"},{"stock_id":"3152","date":"2013-02-22","open":80.1,"high":80.8,"low":79.5,"close":80.2,"volume":329689,"ma20":80.05,"prev_close":79.8,"prev_ma20":80.29,"cross_above_ma20":true,"ma20_distance_pct":0.1873828857,"stock_name":"璟德","industry_category":"通信網路業","type":"tpex"},{"stock_id":"3164","date":"2013-02-22","open":45.0,"high":46.65,"low":44.0,"close":46.1,"volume":881082,"ma20":45.105,"prev_close":44.0,"prev_ma20":44.9825,"cross_above_ma20":true,"ma20_distance_pct":2.2059638621,"stock_name":"景岳","industry_category":"生技醫療業","type":"twse"},{"stock_id":"3167","date":"2013-02-22","open":32.58,"high":33.42,"low":32.45,"close":33.3,"volume":185000,"ma20":33.1015,"prev_close":29.0,"prev_ma20":33.6265,"cross_above_ma20":true,"ma20_distance_pct":0.5996707098,"stock_name":"大量","industry_category":"電機機械","type":"twse"},{"stock_id":"3217","date":"2013-02-22","open":11.55,"high":11.75,"low":11.4,"close":11.5,"volume":977625,"ma20":11.3475,"prev_close":11.2,"prev_ma20":11.3425,"cross_above_ma20":true,"ma20_distance_pct":1.3439083499,"stock_name":"優群","industry_category":"電子零組件業","type":"tpex"},{"stock_id":"3218","date":"2013-02-22","open":21.3,"high":23.5,"low":20.8,"close":23.5,"volume":6105458,"ma20":21.0475,"prev_close":21.0,"prev_ma20":21.0725,"cross_above_ma20":true,"ma20_distance_pct":11.6522152275,"stock_name":"大學光","industry_category":"生技醫療業","type":"tpex"},{"stock_id":"3287","date":"2013-02-22","open":8.09,"high":8.22,"low":8.01,"close":8.15,"volume":68840,"ma20":8.012,"prev_close":8.08,"prev_ma20":8.137,"cross_above_ma20":true,"ma20_distance_pct":1.7224163754,"stock_name":"廣寰科","industry_category":"電腦及週邊設備業","type":"tpex"},{"stock_id":"3308","date":"2013-02-22","open":6.66,"high":6.99,"low":6.55,"close":6.9,"volume":83484,"ma20":6.8205,"prev_close":6.66,"prev_ma20":6.855,"cross_above_ma20":true,"ma20_distance_pct":1.1656036947,"stock_name":"聯德","industry_category":"電子零組件業","type":"twse"},{"stock_id":"3322","date":"2013-02-22","open":8.16,"high":8.28,"low":8.0,"close":8.16,"volume":1933977,"ma20":7.8505,"prev_close":7.63,"prev_ma20":7.896,"cross_above_ma20":true,"ma20_distance_pct":3.9424240494,"stock_name":"建舜電","industry_category":"電子零組件業","type":"tpex"},{"stock_id":"3324","date":"2013-02-22","open":31.0,"high":33.0,"low":31.0,"close":32.05,"volume":4628038,"ma20":30.805,"prev_close":30.8,"prev_ma20":31.0475,"cross_above_ma20":true,"ma20_distance_pct":4.0415516962,"stock_name":"雙鴻","industry_category":"其他電子類","type":"tpex"},{"stock_id":"3357","date":"2013-02-22","open":16.19,"high":16.77,"low":16.0,"close":16.77,"volume":23021,"ma20":13.2495,"prev_close":13.0,"prev_ma20":13.116,"cross_above_ma20":true,"ma20_distance_pct":26.570813993,"stock_name":"臺慶科","industry_category":"電子零組件業","type":"tpex"},{"stock_id":"3362","date":"2013-02-22","open":36.8,"high":40.65,"low":36.5,"close":38.5,"volume":892125,"ma20":37.825,"prev_close":36.8,"prev_ma20":37.625,"cross_above_ma20":true,"ma20_distance_pct":1.7845340383,"stock_name":"先進光","industry_category":"光電業","type":"tpex"},{"stock_id":"3373","date":"2013-02-22","open":54.7,"high":66.9,"low":54.7,"close":63.8,"volume":2230752,"ma20":59.175,"prev_close":54.7,"prev_ma20":58.615,"cross_above_ma20":true,"ma20_distance_pct":7.8158005915,"stock_name":"熱映","industry_category":"其他電子類","type":"tpex"},{"stock_id":"3376","date":"2013-02-22","open":88.7,"high":97.1,"low":87.4,"close":94.8,"volume":5278694,"ma20":94.01,"prev_close":88.3,"prev_ma20":94.57,"cross_above_ma20":true,"ma20_distance_pct":0.8403361345,"stock_name":"新日興","industry_category":"電子工業","type":"twse"},{"stock_id":"3406","date":"2013-02-22","open":198.0,"high":217.0,"low":197.0,"close":215.0,"volume":14131132,"ma20":213.875,"prev_close":198.0,"prev_ma20":215.275,"cross_above_ma20":true,"ma20_distance_pct":0.5260081823,"stock_name":"玉晶光","industry_category":"光電業","type":"twse"},{"stock_id":"3432","date":"2013-02-22","open":10.5,"high":11.0,"low":10.4,"close":10.55,"volume":1005190,"ma20":10.0775,"prev_close":9.9,"prev_ma20":10.105,"cross_above_ma20":true,"ma20_distance_pct":4.6886628628,"stock_name":"台端","industry_category":"電子工業","type":"twse"},{"stock_id":"3434","date":"2013-02-22","open":8.72,"high":9.01,"low":8.51,"close":8.67,"volume":80000,"ma20":8.589,"prev_close":8.39,"prev_ma20":8.63,"cross_above_ma20":true,"ma20_distance_pct":0.9430667132,"stock_name":"哲固","industry_category":"光電業","type":"tpex"},{"stock_id":"3518","date":"2013-02-22","open":36.2,"high":40.2,"low":36.0,"close":39.5,"volume":1214722,"ma20":36.5125,"prev_close":35.8,"prev_ma20":36.6125,"cross_above_ma20":true,"ma20_distance_pct":8.1821294077,"stock_name":"柏騰","industry_category":"其他電子業","type":"twse"},{"stock_id":"3533","date":"2013-02-22","open":87.4,"high":89.1,"low":86.7,"close":87.2,"volume":2386796,"ma20":87.095,"prev_close":86.5,"prev_ma20":87.335,"cross_above_ma20":true,"ma20_distance_pct":0.1205580114,"stock_name":"嘉澤","industry_category":"電子工業","type":"twse"},{"stock_id":"3548","date":"2013-02-22","open":28.65,"high":30.1,"low":28.6,"close":29.35,"volume":2624522,"ma20":28.8475,"prev_close":28.65,"prev_ma20":29.055,"cross_above_ma20":true,"ma20_distance_pct":1.7419187105,"stock_name":"兆利","industry_category":"電子零組件業","type":"tpex"},{"stock_id":"3550","date":"2013-02-22","open":12.25,"high":13.15,"low":12.15,"close":13.15,"volume":350120,"ma20":12.355,"prev_close":12.1,"prev_ma20":12.415,"cross_above_ma20":true,"ma20_distance_pct":6.4346418454,"stock_name":"聯穎","industry_category":"電子工業","type":"twse"},{"stock_id":"3552","date":"2013-02-22","open":65.6,"high":70.0,"low":65.0,"close":67.9,"volume":2609983,"ma20":66.55,"prev_close":65.5,"prev_ma20":66.695,"cross_above_ma20":true,"ma20_distance_pct":2.0285499624,"stock_name":"同致","industry_category":"其他電子類","type":"tpex"},{"stock_id":"3557","date":"2013-02-22","open":8.58,"high":9.1,"low":8.45,"close":8.9,"volume":2711853,"ma20":8.527,"prev_close":8.33,"prev_ma20":8.526,"cross_above_ma20":true,"ma20_distance_pct":4.3743403307,"stock_name":"嘉威","industry_category":"其他","type":"twse"},{"stock_id":"3580","date":"2013-02-22","open":8.75,"high":9.5,"low":8.65,"close":9.03,"volume":531271,"ma20":8.9655,"prev_close":8.65,"prev_ma20":9.039,"cross_above_ma20":true,"ma20_distance_pct":0.7194244604,"stock_name":"友威科","industry_category":"其他電子類","type":"tpex"},{"stock_id":"3584","date":"2013-02-22","open":23.9,"high":26.8,"low":23.7,"close":25.55,"volume":16451600,"ma20":23.5275,"prev_close":23.5,"prev_ma20":23.715,"cross_above_ma20":true,"ma20_distance_pct":8.5963234513,"stock_name":"介面","industry_category":"光電業","type":"twse"},{"stock_id":"3588","date":"2013-02-22","open":45.0,"high":49.15,"low":45.0,"close":47.7,"volume":754297,"ma20":47.5675,"prev_close":45.0,"prev_ma20":48.1025,"cross_above_ma20":true,"ma20_distance_pct":0.278551532,"stock_name":"通嘉","industry_category":"電子工業","type":"twse"},{"stock_id":"3591","date":"2013-02-22","open":36.6,"high":38.0,"low":36.5,"close":37.05,"volume":1593184,"ma20":36.825,"prev_close":36.25,"prev_ma20":37.2975,"cross_above_ma20":true,"ma20_distance_pct":0.6109979633,"stock_name":"艾笛森","industry_category":"電子工業","type":"twse"},{"stock_id":"3615","date":"2013-02-22","open":54.4,"high":60.8,"low":54.2,"close":58.5,"volume":10261439,"ma20":56.7325,"prev_close":54.0,"prev_ma20":56.7325,"cross_above_ma20":true,"ma20_distance_pct":3.1154981712,"stock_name":"安可","industry_category":"光電業","type":"tpex"},{"stock_id":"4102","date":"2013-02-22","open":31.8,"high":34.15,"low":31.0,"close":33.9,"volume":1861002,"ma20":32.0375,"prev_close":31.75,"prev_ma20":32.25,"cross_above_ma20":true,"ma20_distance_pct":5.8134998049,"stock_name":"永日","industry_category":"生技醫療業","type":"tpex"},{"stock_id":"4104","date":"2013-02-22","open":55.1,"high":58.0,"low":55.0,"close":57.7,"volume":2520922,"ma20":56.335,"prev_close":54.8,"prev_ma20":56.495,"cross_above_ma20":true,"ma20_distance_pct":2.4230052365,"stock_name":"佳醫","industry_category":"化學生技醫療","type":"twse"},{"stock_id":"4109","date":"2013-02-22","open":17.6,"high":24.15,"low":17.45,"close":24.15,"volume":23597395,"ma20":17.905,"prev_close":17.45,"prev_ma20":17.575,"cross_above_ma20":true,"ma20_distance_pct":34.8785255515,"stock_name":"加捷生醫","industry_category":"生技醫療業","type":"tpex"},{"stock_id":"4126","date":"2013-02-22","open":85.6,"high":87.8,"low":84.5,"close":87.6,"volume":1506293,"ma20":84.545,"prev_close":84.5,"prev_ma20":84.53,"cross_above_ma20":true,"ma20_distance_pct":3.6134602874,"stock_name":"太醫","industry_category":"生技醫療業","type":"tpex"},{"stock_id":"4129","date":"2013-02-22","open":38.3,"high":40.95,"low":37.6,"close":40.4,"volume":1735165,"ma20":38.2925,"prev_close":38.3,"prev_ma20":38.42,"cross_above_ma20":true,"ma20_distance_pct":5.5036887119,"stock_name":"聯合","industry_category":"生技醫療業","type":"tpex"},{"stock_id":"4133","date":"2013-02-22","open":48.1,"high":53.1,"low":47.55,"close":52.8,"volume":4056457,"ma20":48.38,"prev_close":48.1,"prev_ma20":48.38,"cross_above_ma20":true,"ma20_distance_pct":9.1360066143,"stock_name":"亞諾法","industry_category":"化學生技醫療","type":"twse"},{"stock_id":"4160","date":"2013-02-22","open":44.35,"high":51.0,"low":43.0,"close":51.0,"volume":5907436,"ma20":46.435,"prev_close":44.35,"prev_ma20":46.3125,"cross_above_ma20":true,"ma20_distance_pct":9.8309464843,"stock_name":"訊聯基因","industry_category":"生技醫療業","type":"tpex"},{"stock_id":"4162","date":"2013-02-22","open":175.5,"high":215.0,"low":175.5,"close":210.0,"volume":15063799,"ma20":181.6,"prev_close":173.5,"prev_ma20":180.05,"cross_above_ma20":true,"ma20_distance_pct":15.6387665198,"stock_name":"智擎","industry_category":"生技醫療業","type":"tpex"},{"stock_id":"4163","date":"2013-02-22","open":94.0,"high":105.5,"low":92.1,"close":104.5,"volume":4341628,"ma20":102.085,"prev_close":93.5,"prev_ma20":100.235,"cross_above_ma20":true,"ma20_distance_pct":2.3656756624,"stock_name":"鐿鈦","industry_category":"生技醫療業","type":"tpex"},{"stock_id":"4168","date":"2013-02-22","open":138.5,"high":155.0,"low":132.0,"close":153.0,"volume":5560602,"ma20":147.975,"prev_close":135.5,"prev_ma20":145.925,"cross_above_ma20":true,"ma20_distance_pct":3.3958438925,"stock_name":"醣聯","industry_category":"生技醫療業","type":"tpex"},{"stock_id":"4402","date":"2013-02-22","open":7.49,"high":8.09,"low":7.16,"close":8.0,"volume":415072,"ma20":7.488,"prev_close":7.35,"prev_ma20":7.466,"cross_above_ma20":true,"ma20_distance_pct":6.8376068376,"stock_name":"郡都開發","industry_category":"紡織纖維","type":"tpex"},{"stock_id":"4419","date":"2013-02-22","open":9.6,"high":10.15,"low":9.55,"close":10.0,"volume":73012,"ma20":9.6415,"prev_close":9.61,"prev_ma20":9.6255,"cross_above_ma20":true,"ma20_distance_pct":3.7183010942,"stock_name":"元勝","industry_category":"紡織纖維","type":"tpex"},{"stock_id":"4420","date":"2013-02-22","open":18.35,"high":18.5,"low":18.2,"close":18.4,"volume":75030,"ma20":18.395,"prev_close":18.35,"prev_ma20":18.425,"cross_above_ma20":true,"ma20_distance_pct":0.0271812993,"stock_name":"光明","industry_category":"紡織纖維","type":"tpex"},{"stock_id":"4503","date":"2013-02-22","open":5.1,"high":5.29,"low":5.09,"close":5.2,"volume":68318,"ma20":5.1245,"prev_close":5.1,"prev_ma20":5.1945,"cross_above_ma20":true,"ma20_distance_pct":1.4733144697,"stock_name":"金雨","industry_category":"電機機械","type":"tpex"},{"stock_id":"4702","date":"2013-02-22","open":34.2,"high":36.5,"low":34.2,"close":35.6,"volume":936901,"ma20":35.29,"prev_close":34.0,"prev_ma20":34.745,"cross_above_ma20":true,"ma20_distance_pct":0.8784358175,"stock_name":"中美實","industry_category":"化學工業","type":"tpex"},{"stock_id":"4714","date":"2013-02-22","open":11.0,"high":11.65,"low":10.95,"close":11.5,"volume":478076,"ma20":10.7905,"prev_close":10.8,"prev_ma20":10.8555,"cross_above_ma20":true,"ma20_distance_pct":6.57522821,"stock_name":"永捷","industry_category":"化學工業","type":"tpex"},{"stock_id":"4721","date":"2013-02-22","open":21.9,"high":22.4,"low":21.55,"close":22.1,"volume":353772,"ma20":21.8,"prev_close":21.8,"prev_ma20":21.875,"cross_above_ma20":true,"ma20_distance_pct":1.376146789,"stock_name":"美琪瑪","industry_category":"化學工業","type":"tpex"},{"stock_id":"4722","date":"2013-02-22","open":22.5,"high":24.4,"low":22.45,"close":23.3,"volume":4823552,"ma20":22.4575,"prev_close":22.35,"prev_ma20":22.5175,"cross_above_ma20":true,"ma20_distance_pct":3.751530669,"stock_name":"國精化","industry_category":"化學工業","type":"twse"},{"stock_id":"4736","date":"2013-02-22","open":45.5,"high":48.5,"low":45.0,"close":47.9,"volume":905944,"ma20":45.1,"prev_close":45.0,"prev_ma20":45.205,"cross_above_ma20":true,"ma20_distance_pct":6.2084257206,"stock_name":"泰博","industry_category":"生技醫療業","type":"tpex"},{"stock_id":"4737","date":"2013-02-22","open":57.6,"high":63.1,"low":57.1,"close":61.0,"volume":744627,"ma20":59.5425,"prev_close":57.4,"prev_ma20":60.0425,"cross_above_ma20":true,"ma20_distance_pct":2.4478313809,"stock_name":"華廣","industry_category":"化學生技醫療","type":"twse"},{"stock_id":"4935","date":"2013-02-22","open":37.2,"high":38.9,"low":36.9,"close":37.35,"volume":3852190,"ma20":37.335,"prev_close":36.8,"prev_ma20":37.935,"cross_above_ma20":true,"ma20_distance_pct":0.0401767778,"stock_name":"茂林-KY","industry_category":"光電業","type":"twse"},{"stock_id":"4952","date":"2013-02-22","open":19.4,"high":20.0,"low":19.35,"close":19.6,"volume":874400,"ma20":19.5825,"prev_close":19.15,"prev_ma20":19.7025,"cross_above_ma20":true,"ma20_distance_pct":0.0893655049,"stock_name":"凌通","industry_category":"半導體業","type":"twse"},{"stock_id":"5011","date":"2013-02-22","open":21.3,"high":23.55,"low":21.0,"close":22.9,"volume":138092,"ma20":22.08,"prev_close":20.85,"prev_ma20":22.28,"cross_above_ma20":true,"ma20_distance_pct":3.7137681159,"stock_name":"久陽","industry_category":"鋼鐵工業","type":"tpex"},{"stock_id":"5211","date":"2013-02-22","open":29.0,"high":30.1,"low":28.8,"close":30.0,"volume":515102,"ma20":29.835,"prev_close":28.8,"prev_ma20":30.09,"cross_above_ma20":true,"ma20_distance_pct":0.5530417295,"stock_name":"蒙恬","industry_category":"資訊服務業","type":"tpex"},{"stock_id":"5215","date":"2013-02-22","open":43.0,"high":44.6,"low":42.6,"close":44.0,"volume":623000,"ma20":43.6125,"prev_close":42.8,"prev_ma20":44.1225,"cross_above_ma20":true,"ma20_distance_pct":0.8885067355,"stock_name":"科嘉-KY","industry_category":"電腦及週邊設備業","type":"twse"},{"stock_id":"5240","date":"2013-02-22","open":29.35,"high":29.8,"low":28.3,"close":29.8,"volume":30000,"ma20":29.596,"prev_close":29.26,"prev_ma20":29.581,"cross_above_ma20":true,"ma20_distance_pct":0.6892823355,"stock_name":"建騰","industry_category":"光電業","type":"emerging"},{"stock_id":"5272","date":"2013-02-22","open":29.6,"high":30.22,"low":29.5,"close":30.1,"volume":296671,"ma20":29.6525,"prev_close":29.4,"prev_ma20":29.5875,"cross_above_ma20":true,"ma20_distance_pct":1.5091476267,"stock_name":"笙科","industry_category":"半導體業","type":"tpex"},{"stock_id":"5344","date":"2013-02-22","open":11.2,"high":12.0,"low":11.15,"close":11.75,"volume":347376,"ma20":11.735,"prev_close":11.2,"prev_ma20":11.805,"cross_above_ma20":true,"ma20_distance_pct":0.1278227524,"stock_name":"立衛","industry_category":"半導體業","type":"tpex"},{"stock_id":"5371","date":"2013-02-22","open":22.6,"high":24.4,"low":22.5,"close":23.7,"volume":37780904,"ma20":22.76,"prev_close":22.45,"prev_ma20":22.975,"cross_above_ma20":true,"ma20_distance_pct":4.1300527241,"stock_name":"中光電","industry_category":"光電業","type":"tpex"},{"stock_id":"5425","date":"2013-02-22","open":13.1,"high":14.0,"low":13.0,"close":13.75,"volume":4605331,"ma20":12.8475,"prev_close":12.75,"prev_ma20":12.88,"cross_above_ma20":true,"ma20_distance_pct":7.0247129792,"stock_name":"台半","industry_category":"半導體業","type":"tpex"},{"stock_id":"5450","date":"2013-02-22","open":11.85,"high":12.5,"low":11.75,"close":12.45,"volume":357225,"ma20":12.2625,"prev_close":11.75,"prev_ma20":12.3025,"cross_above_ma20":true,"ma20_distance_pct":1.5290519878,"stock_name":"寶聯通","industry_category":"電腦及週邊設備業","type":"tpex"},{"stock_id":"5452","date":"2013-02-22","open":14.0,"high":14.25,"low":13.7,"close":14.0,"volume":2138368,"ma20":13.9425,"prev_close":13.85,"prev_ma20":14.015,"cross_above_ma20":true,"ma20_distance_pct":0.4124081047,"stock_name":"佶優","industry_category":"其他電子類","type":"tpex"},{"stock_id":"5455","date":"2013-02-22","open":2.13,"high":2.16,"low":2.01,"close":2.16,"volume":69682,"ma20":2.0195,"prev_close":2.0,"prev_ma20":2.0225,"cross_above_ma20":true,"ma20_distance_pct":6.9571676157,"stock_name":"昇益","industry_category":"建材營造","type":"tpex"},{"stock_id":"5464","date":"2013-02-22","open":18.6,"high":20.0,"low":18.6,"close":19.8,"volume":322148,"ma20":18.5825,"prev_close":18.45,"prev_ma20":18.6275,"cross_above_ma20":true,"ma20_distance_pct":6.5518633123,"stock_name":"霖宏","industry_category":"電子零組件業","type":"tpex"},{"stock_id":"5609","date":"2013-02-22","open":18.65,"high":19.15,"low":18.5,"close":18.9,"volume":942613,"ma20":18.855,"prev_close":18.5,"prev_ma20":18.98,"cross_above_ma20":true,"ma20_distance_pct":0.2386634845,"stock_name":"中菲行","industry_category":"航運業","type":"tpex"},{"stock_id":"6118","date":"2013-02-22","open":10.1,"high":10.2,"low":9.97,"close":10.15,"volume":304276,"ma20":10.0765,"prev_close":10.05,"prev_ma20":10.119,"cross_above_ma20":true,"ma20_distance_pct":0.7294199375,"stock_name":"建達","industry_category":"電子通路業","type":"tpex"},{"stock_id":"6127","date":"2013-02-22","open":8.65,"high":9.29,"low":8.65,"close":9.24,"volume":1017391,"ma20":8.592,"prev_close":8.6,"prev_ma20":8.635,"cross_above_ma20":true,"ma20_distance_pct":7.5418994413,"stock_name":"九豪","industry_category":"電子零組件業","type":"tpex"},{"stock_id":"6130","date":"2013-02-22","open":110.0,"high":145.5,"low":110.0,"close":145.5,"volume":897876,"ma20":115.235,"prev_close":107.0,"prev_ma20":112.775,"cross_above_ma20":true,"ma20_distance_pct":26.2637219595,"stock_name":"上亞科技","industry_category":"生技醫療業","type":"tpex"},{"stock_id":"6143","date":"2013-02-22","open":45.3,"high":49.35,"low":44.8,"close":47.45,"volume":9292146,"ma20":44.8725,"prev_close":44.2,"prev_ma20":44.7175,"cross_above_ma20":true,"ma20_distance_pct":5.7440525935,"stock_name":"振曜","industry_category":"通信網路業","type":"tpex"},{"stock_id":"6148","date":"2013-02-22","open":5.15,"high":5.53,"low":5.1,"close":5.4,"volume":737908,"ma20":5.345,"prev_close":5.18,"prev_ma20":5.3975,"cross_above_ma20":true,"ma20_distance_pct":1.0289990645,"stock_name":"驊宏資","industry_category":"資訊服務業","type":"tpex"},{"stock_id":"6168","date":"2013-02-22","open":12.3,"high":12.85,"low":12.3,"close":12.5,"volume":2570179,"ma20":12.4025,"prev_close":12.1,"prev_ma20":12.545,"cross_above_ma20":true,"ma20_distance_pct":0.7861318283,"stock_name":"宏齊","industry_category":"光電業","type":"twse"},{"stock_id":"6175","date":"2013-02-22","open":10.7,"high":11.4,"low":10.7,"close":11.15,"volume":1240462,"ma20":10.855,"prev_close":10.65,"prev_ma20":10.925,"cross_above_ma20":true,"ma20_distance_pct":2.7176416398,"stock_name":"立敦","industry_category":"電子零組件業","type":"tpex"},{"stock_id":"6179","date":"2013-02-22","open":6.28,"high":6.89,"low":6.25,"close":6.89,"volume":183253,"ma20":6.5405,"prev_close":6.28,"prev_ma20":6.57,"cross_above_ma20":true,"ma20_distance_pct":5.343628163,"stock_name":"亞通","industry_category":"其他","type":"tpex"},{"stock_id":"6188","date":"2013-02-22","open":18.05,"high":18.6,"low":18.05,"close":18.05,"volume":2041792,"ma20":17.92,"prev_close":18.05,"prev_ma20":18.0725,"cross_above_ma20":true,"ma20_distance_pct":0.7254464286,"stock_name":"廣明","industry_category":"電腦及週邊設備業","type":"tpex"},{"stock_id":"6197","date":"2013-02-22","open":24.55,"high":25.6,"low":24.4,"close":25.1,"volume":2654647,"ma20":24.8175,"prev_close":24.4,"prev_ma20":24.9125,"cross_above_ma20":true,"ma20_distance_pct":1.1383096605,"stock_name":"佳必琪","industry_category":"電子零組件業","type":"twse"},{"stock_id":"6207","date":"2013-02-22","open":20.7,"high":22.6,"low":20.6,"close":22.6,"volume":973020,"ma20":20.8675,"prev_close":20.55,"prev_ma20":20.945,"cross_above_ma20":true,"ma20_distance_pct":8.3023840901,"stock_name":"雷科","industry_category":"電子零組件業","type":"tpex"},{"stock_id":"6210","date":"2013-02-22","open":41.5,"high":43.0,"low":41.4,"close":42.4,"volume":202003,"ma20":41.2525,"prev_close":41.1,"prev_ma20":41.7825,"cross_above_ma20":true,"ma20_distance_pct":2.781649597,"stock_name":"慶生","industry_category":"電子零組件業","type":"tpex"},{"stock_id":"6226","date":"2013-02-22","open":4.78,"high":5.1,"low":4.65,"close":4.9,"volume":879050,"ma20":4.782,"prev_close":4.7,"prev_ma20":4.837,"cross_above_ma20":true,"ma20_distance_pct":2.4675867838,"stock_name":"光鼎","industry_category":"光電業","type":"twse"},{"stock_id":"6241","date":"2013-02-22","open":39.1,"high":47.8,"low":39.1,"close":46.2,"volume":489946,"ma20":39.1125,"prev_close":36.55,"prev_ma20":39.045,"cross_above_ma20":true,"ma20_distance_pct":18.1208053691,"stock_name":"鑫永洋","industry_category":"通信網路業","type":"tpex"},{"stock_id":"6247","date":"2013-02-22","open":11.7,"high":11.8,"low":11.3,"close":11.7,"volume":467000,"ma20":11.67,"prev_close":11.65,"prev_ma20":11.685,"cross_above_ma20":true,"ma20_distance_pct":0.2570694087,"stock_name":"淇譽電","industry_category":"其他電子類","type":"tpex"},{"stock_id":"6248","date":"2013-02-22","open":4.76,"high":5.58,"low":4.76,"close":5.2,"volume":107202,"ma20":4.877,"prev_close":4.69,"prev_ma20":4.8745,"cross_above_ma20":true,"ma20_distance_pct":6.6229239286,"stock_name":"沛波","industry_category":"鋼鐵工業","type":"tpex"},{"stock_id":"6251","date":"2013-02-22","open":9.9,"high":9.91,"low":9.62,"close":9.9,"volume":4240372,"ma20":9.4425,"prev_close":9.41,"prev_ma20":9.4575,"cross_above_ma20":true,"ma20_distance_pct":4.8451151708,"stock_name":"定穎","industry_category":"電子工業","type":"twse"},{"stock_id":"6276","date":"2013-02-22","open":32.6,"high":35.55,"low":32.6,"close":34.2,"volume":498149,"ma20":33.2275,"prev_close":32.5,"prev_ma20":33.5175,"cross_above_ma20":true,"ma20_distance_pct":2.9267925664,"stock_name":"安鈦克","industry_category":"電腦及週邊設備業","type":"tpex"},{"stock_id":"6284","date":"2013-02-22","open":16.45,"high":18.55,"low":16.45,"close":17.65,"volume":2646854,"ma20":17.145,"prev_close":16.35,"prev_ma20":17.3,"cross_above_ma20":true,"ma20_distance_pct":2.9454651502,"stock_name":"佳邦","industry_category":"電子零組件業","type":"tpex"},{"stock_id":"8054","date":"2013-02-22","open":33.6,"high":35.5,"low":33.2,"close":34.95,"volume":2395491,"ma20":33.995,"prev_close":33.3,"prev_ma20":34.355,"cross_above_ma20":true,"ma20_distance_pct":2.8092366524,"stock_name":"安國","industry_category":"半導體業","type":"tpex"},{"stock_id":"8078","date":"2013-02-22","open":30.8,"high":31.4,"low":30.3,"close":30.9,"volume":17393627,"ma20":30.7325,"prev_close":30.6,"prev_ma20":30.7875,"cross_above_ma20":true,"ma20_distance_pct":0.5450256243,"stock_name":"華寶","industry_category":"通信網路業","type":"twse"},{"stock_id":"8087","date":"2013-02-22","open":7.1,"high":7.35,"low":7.0,"close":7.05,"volume":48146,"ma20":6.9985,"prev_close":6.99,"prev_ma20":7.0215,"cross_above_ma20":true,"ma20_distance_pct":0.7358719726,"stock_name":"華鎂鑫","industry_category":"光電業","type":"tpex"},{"stock_id":"8103","date":"2013-02-22","open":40.8,"high":42.95,"low":40.8,"close":42.0,"volume":2766040,"ma20":41.2825,"prev_close":40.6,"prev_ma20":41.3725,"cross_above_ma20":true,"ma20_distance_pct":1.7380245867,"stock_name":"瀚荃","industry_category":"電子工業","type":"twse"},{"stock_id":"8121","date":"2013-02-22","open":37.0,"high":38.7,"low":37.0,"close":37.15,"volume":5177067,"ma20":36.605,"prev_close":36.6,"prev_ma20":37.0825,"cross_above_ma20":true,"ma20_distance_pct":1.488867641,"stock_name":"越峰","industry_category":"電子零組件業","type":"tpex"},{"stock_id":"8163","date":"2013-02-22","open":18.7,"high":18.95,"low":18.25,"close":18.55,"volume":4518690,"ma20":18.265,"prev_close":18.0,"prev_ma20":18.43,"cross_above_ma20":true,"ma20_distance_pct":1.5603613468,"stock_name":"達方","industry_category":"電腦及週邊設備業","type":"twse"},{"stock_id":"8234","date":"2013-02-22","open":24.65,"high":25.7,"low":24.55,"close":25.3,"volume":597917,"ma20":24.9975,"prev_close":24.6,"prev_ma20":25.095,"cross_above_ma20":true,"ma20_distance_pct":1.2101210121,"stock_name":"新漢","industry_category":"電腦及週邊設備業","type":"tpex"},{"stock_id":"8299","date":"2013-02-22","open":201.0,"high":221.5,"low":198.0,"close":218.0,"volume":20571784,"ma20":206.35,"prev_close":199.0,"prev_ma20":207.275,"cross_above_ma20":true,"ma20_distance_pct":5.6457475164,"stock_name":"群聯","industry_category":"半導體業","type":"tpex"},{"stock_id":"8422","date":"2013-02-22","open":200.0,"high":205.5,"low":196.5,"close":201.0,"volume":1869173,"ma20":199.5,"prev_close":198.5,"prev_ma20":200.2,"cross_above_ma20":true,"ma20_distance_pct":0.7518796992,"stock_name":"可寧衛","industry_category":"其他","type":"twse"},{"stock_id":"8424","date":"2013-02-22","open":33.55,"high":40.0,"low":33.5,"close":38.0,"volume":3400276,"ma20":33.7915,"prev_close":33.35,"prev_ma20":33.534,"cross_above_ma20":true,"ma20_distance_pct":12.4543154344,"stock_name":"惠普","industry_category":"建材營造","type":"tpex"},{"stock_id":"8427","date":"2013-02-22","open":63.4,"high":66.5,"low":62.8,"close":64.2,"volume":328412,"ma20":63.645,"prev_close":62.2,"prev_ma20":63.955,"cross_above_ma20":true,"ma20_distance_pct":0.872024511,"stock_name":"基勝-KY","industry_category":"其他","type":"twse"},{"stock_id":"8432","date":"2013-02-22","open":96.5,"high":101.0,"low":93.7,"close":101.0,"volume":1609428,"ma20":98.495,"prev_close":94.5,"prev_ma20":98.995,"cross_above_ma20":true,"ma20_distance_pct":2.5432763084,"stock_name":"東生華","industry_category":"生技醫療業","type":"tpex"},{"stock_id":"8923","date":"2013-02-22","open":15.8,"high":16.8,"low":15.8,"close":16.8,"volume":4120,"ma20":16.03,"prev_close":15.8,"prev_ma20":16.0,"cross_above_ma20":true,"ma20_distance_pct":4.8034934498,"stock_name":"時報","industry_category":"文化創意業","type":"tpex"},{"stock_id":"9136","date":"2013-02-22","open":14.3,"high":15.3,"low":14.2,"close":14.5,"volume":10135596,"ma20":14.21,"prev_close":13.9,"prev_ma20":14.18,"cross_above_ma20":true,"ma20_distance_pct":2.0408163265,"stock_name":"巨騰-DR","industry_category":"存託憑證","type":"twse"},{"stock_id":"9933","date":"2013-02-22","open":59.0,"high":61.8,"low":58.0,"close":59.1,"volume":13003501,"ma20":58.105,"prev_close":58.0,"prev_ma20":58.5,"cross_above_ma20":true,"ma20_distance_pct":1.7124171758,"stock_name":"中鼎","industry_category":"其他","type":"twse"},{"stock_id":"9938","date":"2013-02-22","open":15.95,"high":18.25,"low":15.95,"close":18.1,"volume":3199377,"ma20":17.355,"prev_close":17.15,"prev_ma20":17.4175,"cross_above_ma20":true,"ma20_distance_pct":4.2927110343,"stock_name":"百和","industry_category":"其他","type":"twse"},{"stock_id":"9950","date":"2013-02-22","open":19.1,"high":20.2,"low":19.1,"close":19.7,"volume":244065,"ma20":19.285,"prev_close":19.1,"prev_ma20":19.2875,"cross_above_ma20":true,"ma20_distance_pct":2.151931553,"stock_name":"萬國通","industry_category":"塑膠工業","type":"tpex"},{"stock_id":"9957","date":"2013-02-22","open":8.81,"high":8.95,"low":8.79,"close":8.95,"volume":642348,"ma20":8.945,"prev_close":8.83,"prev_ma20":8.945,"cross_above_ma20":true,"ma20_distance_pct":0.0558971492,"stock_name":"燁聯","industry_category":"鋼鐵工業","type":"emerging"}]