[{"date":"2020-11-16","open":24.27,"high":24.3,"low":23.5,"close":23.65,"volume":66646,"ma20":null,"cross_above_ma20":false,"ma20_rising":false,"ma20_distance_pct":null,"capital_billion":1.7661,"capital_report_date":"2020-06-30"},{"date":"2020-11-23","open":23.64,"high":24.3,"low":23.5,"close":23.7,"volume":118894,"ma20":null,"cross_above_ma20":false,"ma20_rising":false,"ma20_distance_pct":null,"capital_billion":1.7661,"capital_report_date":"2020-06-30"},{"date":"2020-11-30","open":21.78,"high":22.1,"low":20.0,"close":20.5,"volume":136955,"ma20":null,"cross_above_ma20":false,"ma20_rising":false,"ma20_distance_pct":null,"capital_billion":1.7661,"capital_report_date":"2020-06-30"},{"date":"2020-12-07","open":23.41,"high":24.0,"low":20.9,"close":21.15,"volume":213435,"ma20":null,"cross_above_ma20":false,"ma20_rising":false,"ma20_distance_pct":null,"capital_billion":1.7661,"capital_report_date":"2020-06-30"},{"date":"2020-12-14","open":21.2,"high":21.95,"low":21.2,"close":21.55,"volume":54638,"ma20":null,"cross_above_ma20":false,"ma20_rising":false,"ma20_distance_pct":null,"capital_billion":1.7661,"capital_report_date":"2020-06-30"},{"date":"2020-12-21","open":21.38,"high":21.75,"low":20.9,"close":21.0,"volume":98700,"ma20":null,"cross_above_ma20":false,"ma20_rising":false,"ma20_distance_pct":null,"capital_billion":1.7661,"capital_report_date":"2020-06-30"},{"date":"2020-12-28","open":21.07,"high":21.65,"low":20.8,"close":21.0,"volume":29504,"ma20":null,"cross_above_ma20":false,"ma20_rising":false,"ma20_distance_pct":null,"capital_billion":1.7661,"capital_report_date":"2020-06-30"},{"date":"2021-01-04","open":20.9,"high":21.1,"low":20.75,"close":21.0,"volume":51600,"ma20":null,"cross_above_ma20":false,"ma20_rising":false,"ma20_distance_pct":null,"capital_billion":1.7661,"capital_report_date":"2020-06-30"},{"date":"2021-01-11","open":20.64,"high":32.1,"low":20.6,"close":31.1,"volume":1354789,"ma20":null,"cross_above_ma20":false,"ma20_rising":false,"ma20_distance_pct":null,"capital_billion":1.7661,"capital_report_date":"2020-06-30"},{"date":"2021-01-18","open":30.07,"high":33.6,"low":27.75,"close":30.6,"volume":1669923,"ma20":null,"cross_above_ma20":false,"ma20_rising":false,"ma20_distance_pct":null,"capital_billion":1.7661,"capital_report_date":"2020-06-30"},{"date":"2021-01-25","open":30.35,"high":37.05,"low":29.9,"close":36.8,"volume":1677639,"ma20":null,"cross_above_ma20":false,"ma20_rising":false,"ma20_distance_pct":null,"capital_billion":1.7661,"capital_report_date":"2020-06-30"},{"date":"2021-02-01","open":32.88,"high":34.1,"low":31.4,"close":32.05,"volume":332272,"ma20":null,"cross_above_ma20":false,"ma20_rising":false,"ma20_distance_pct":null,"capital_billion":1.7661,"capital_report_date":"2020-06-30"},{"date":"2021-02-15","open":32.93,"high":37.5,"low":32.8,"close":36.3,"volume":428169,"ma20":null,"cross_above_ma20":false,"ma20_rising":false,"ma20_distance_pct":null,"capital_billion":1.7661,"capital_report_date":"2020-06-30"},{"date":"2021-02-22","open":45.86,"high":62.1,"low":45.6,"close":61.2,"volume":1371007,"ma20":null,"cross_above_ma20":false,"ma20_rising":false,"ma20_distance_pct":null,"capital_billion":1.7661,"capital_report_date":"2020-06-30"},{"date":"2021-03-01","open":59.76,"high":62.9,"low":48.0,"close":51.8,"volume":814665,"ma20":null,"cross_above_ma20":false,"ma20_rising":false,"ma20_distance_pct":null,"capital_billion":1.7661,"capital_report_date":"2020-06-30"},{"date":"2021-03-08","open":52.08,"high":54.2,"low":48.3,"close":49.7,"volume":588677,"ma20":null,"cross_above_ma20":false,"ma20_rising":false,"ma20_distance_pct":null,"capital_billion":1.7661,"capital_report_date":"2020-06-30"},{"date":"2021-03-15","open":49.9,"high":50.4,"low":43.85,"close":45.95,"volume":947707,"ma20":null,"cross_above_ma20":false,"ma20_rising":false,"ma20_distance_pct":null,"capital_billion":1.7661,"capital_report_date":"2020-06-30"},{"date":"2021-03-22","open":51.68,"high":56.2,"low":47.95,"close":48.3,"volume":563186,"ma20":null,"cross_above_ma20":false,"ma20_rising":false,"ma20_distance_pct":null,"capital_billion":1.7661,"capital_report_date":"2020-06-30"},{"date":"2021-03-29","open":49.02,"high":50.6,"low":48.15,"close":50.2,"volume":99808,"ma20":null,"cross_above_ma20":false,"ma20_rising":false,"ma20_distance_pct":null,"capital_billion":1.7661,"capital_report_date":"2020-06-30"},{"date":"2021-04-05","open":49.65,"high":52.4,"low":48.85,"close":50.0,"volume":406234,"ma20":34.8775,"cross_above_ma20":false,"ma20_rising":false,"ma20_distance_pct":43.3588990037,"capital_billion":1.8446,"capital_report_date":"2020-12-31"},{"date":"2021-04-12","open":50.04,"high":52.2,"low":47.55,"close":49.05,"volume":443252,"ma20":36.1475,"cross_above_ma20":false,"ma20_rising":true,"ma20_distance_pct":35.6940313991,"capital_billion":1.8446,"capital_report_date":"2020-12-31"},{"date":"2021-04-19","open":49.09,"high":49.75,"low":37.25,"close":39.15,"volume":591728,"ma20":36.92,"cross_above_ma20":false,"ma20_rising":true,"ma20_distance_pct":6.0400866739,"capital_billion":1.8446,"capital_report_date":"2020-12-31"},{"date":"2021-04-26","open":36.19,"high":50.2,"low":34.25,"close":46.2,"volume":567636,"ma20":38.205,"cross_above_ma20":false,"ma20_rising":true,"ma20_distance_pct":20.9265802905,"capital_billion":1.8446,"capital_report_date":"2020-12-31"},{"date":"2021-05-03","open":43.6,"high":43.9,"low":39.8,"close":42.45,"volume":83076,"ma20":39.27,"cross_above_ma20":false,"ma20_rising":true,"ma20_distance_pct":8.0977845684,"capital_billion":1.8446,"capital_report_date":"2020-12-31"},{"date":"2021-05-10","open":40.85,"high":41.65,"low":33.45,"close":35.4,"volume":215696,"ma20":39.9625,"cross_above_ma20":false,"ma20_rising":true,"ma20_distance_pct":-11.4169533938,"capital_billion":1.8446,"capital_report_date":"2020-12-31"},{"date":"2021-05-17","open":35.18,"high":36.9,"low":35.0,"close":36.45,"volume":78467,"ma20":40.735,"cross_above_ma20":false,"ma20_rising":true,"ma20_distance_pct":-10.519209525,"capital_billion":1.8446,"capital_report_date":"2020-12-31"},{"date":"2021-05-24","open":35.72,"high":38.7,"low":35.6,"close":38.15,"volume":113293,"ma20":41.5925,"cross_above_ma20":false,"ma20_rising":true,"ma20_distance_pct":-8.276732584,"capital_billion":1.8446,"capital_report_date":"2020-12-31"},{"date":"2021-05-31","open":38.01,"high":38.7,"low":36.8,"close":37.0,"volume":64037,"ma20":42.3925,"cross_above_ma20":false,"ma20_rising":true,"ma20_distance_pct":-12.72041045,"capital_billion":1.8446,"capital_report_date":"2020-12-31"},{"date":"2021-06-07","open":37.0,"high":37.0,"low":34.35,"close":35.0,"volume":60704,"ma20":42.5875,"cross_above_ma20":false,"ma20_rising":true,"ma20_distance_pct":-17.8162606399,"capital_billion":1.8446,"capital_report_date":"2020-12-31"},{"date":"2021-06-14","open":34.9,"high":36.0,"low":34.25,"close":35.0,"volume":79416,"ma20":42.8075,"cross_above_ma20":false,"ma20_rising":true,"ma20_distance_pct":-18.2386264089,"capital_billion":1.8446,"capital_report_date":"2020-12-31"},{"date":"2021-06-21","open":33.08,"high":34.35,"low":32.65,"close":32.85,"volume":71232,"ma20":42.61,"cross_above_ma20":false,"ma20_rising":false,"ma20_distance_pct":-22.9054212626,"capital_billion":1.8446,"capital_report_date":"2020-12-31"},{"date":"2021-06-28","open":32.58,"high":35.0,"low":32.2,"close":32.65,"volume":173055,"ma20":42.64,"cross_above_ma20":false,"ma20_rising":true,"ma20_distance_pct":-23.4287054409,"capital_billion":1.8446,"capital_report_date":"2020-12-31"},{"date":"2021-07-05","open":32.48,"high":33.6,"low":32.0,"close":32.25,"volume":178994,"ma20":42.4375,"cross_above_ma20":false,"ma20_rising":false,"ma20_distance_pct":-24.0058910162,"capital_billion":1.8446,"capital_report_date":"2020-12-31"},{"date":"2021-07-12","open":32.23,"high":32.25,"low":30.05,"close":31.05,"volume":153955,"ma20":40.93,"cross_above_ma20":false,"ma20_rising":false,"ma20_distance_pct":-24.1387735158,"capital_billion":1.8446,"capital_report_date":"2020-12-31"},{"date":"2021-07-19","open":30.36,"high":31.15,"low":29.5,"close":29.7,"volume":119386,"ma20":39.825,"cross_above_ma20":false,"ma20_rising":false,"ma20_distance_pct":-25.4237288136,"capital_billion":1.8446,"capital_report_date":"2020-12-31"},{"date":"2021-07-26","open":28.21,"high":28.65,"low":25.1,"close":26.2,"volume":119248,"ma20":38.65,"cross_above_ma20":false,"ma20_rising":false,"ma20_distance_pct":-32.212160414,"capital_billion":1.8446,"capital_report_date":"2020-12-31"},{"date":"2021-08-09","open":31.17,"high":31.25,"low":28.05,"close":29.0,"volume":50274,"ma20":37.8025,"cross_above_ma20":false,"ma20_rising":false,"ma20_distance_pct":-23.2854969909,"capital_billion":1.8446,"capital_report_date":"2020-12-31"},{"date":"2021-08-16","open":28.84,"high":29.05,"low":26.7,"close":27.25,"volume":68933,"ma20":36.75,"cross_above_ma20":false,"ma20_rising":false,"ma20_distance_pct":-25.8503401361,"capital_billion":1.8446,"capital_report_date":"2021-06-30"},{"date":"2021-08-23","open":28.13,"high":28.95,"low":27.75,"close":28.55,"volume":1320,"ma20":35.6675,"cross_above_ma20":false,"ma20_rising":false,"ma20_distance_pct":-19.955141235,"capital_billion":1.8446,"capital_report_date":"2021-06-30"},{"date":"2021-08-30","open":27.0,"high":27.3,"low":26.6,"close":26.95,"volume":81821,"ma20":34.515,"cross_above_ma20":false,"ma20_rising":false,"ma20_distance_pct":-21.9180066638,"capital_billion":1.8446,"capital_report_date":"2021-06-30"},{"date":"2021-09-06","open":26.85,"high":27.1,"low":26.0,"close":26.65,"volume":88140,"ma20":33.395,"cross_above_ma20":false,"ma20_rising":false,"ma20_distance_pct":-20.1976343764,"capital_billion":1.8446,"capital_report_date":"2021-06-30"},{"date":"2021-09-13","open":26.59,"high":26.65,"low":25.5,"close":26.6,"volume":37422,"ma20":32.7675,"cross_above_ma20":false,"ma20_rising":false,"ma20_distance_pct":-18.8220035096,"capital_billion":1.8446,"capital_report_date":"2021-06-30"},{"date":"2021-09-27","open":26.5,"high":26.5,"low":24.9,"close":26.05,"volume":14773,"ma20":31.76,"cross_above_ma20":false,"ma20_rising":false,"ma20_distance_pct":-17.9785894207,"capital_billion":1.8446,"capital_report_date":"2021-06-30"},{"date":"2021-10-04","open":25.64,"high":26.05,"low":24.65,"close":25.5,"volume":90759,"ma20":30.9125,"cross_above_ma20":false,"ma20_rising":false,"ma20_distance_pct":-17.5090982612,"capital_billion":1.8446,"capital_report_date":"2021-06-30"},{"date":"2021-10-11","open":25.4,"high":25.55,"low":24.55,"close":24.7,"volume":259088,"ma20":30.3775,"cross_above_ma20":false,"ma20_rising":false,"ma20_distance_pct":-18.6898197679,"capital_billion":1.8446,"capital_report_date":"2021-06-30"},{"date":"2021-10-18","open":25.1,"high":25.6,"low":24.45,"close":25.2,"volume":46098,"ma20":29.815,"cross_above_ma20":false,"ma20_rising":false,"ma20_distance_pct":-15.4787858461,"capital_billion":1.8446,"capital_report_date":"2021-06-30"},{"date":"2021-10-25","open":28.64,"high":32.65,"low":28.4,"close":30.6,"volume":188004,"ma20":29.4375,"cross_above_ma20":true,"ma20_rising":false,"ma20_distance_pct":3.949044586,"capital_billion":1.8446,"capital_report_date":"2021-06-30"},{"date":"2021-11-01","open":29.08,"high":29.45,"low":27.3,"close":28.55,"volume":160940,"ma20":29.015,"cross_above_ma20":false,"ma20_rising":false,"ma20_distance_pct":-1.6026193348,"capital_billion":1.8446,"capital_report_date":"2021-06-30"},{"date":"2021-11-08","open":27.58,"high":30.0,"low":27.45,"close":29.35,"volume":86374,"ma20":28.7325,"cross_above_ma20":true,"ma20_rising":false,"ma20_distance_pct":2.1491342556,"capital_billion":1.8446,"capital_report_date":"2021-06-30"},{"date":"2021-11-15","open":29.39,"high":30.25,"low":28.8,"close":28.9,"volume":82259,"ma20":28.4275,"cross_above_ma20":false,"ma20_rising":false,"ma20_distance_pct":1.6621229443,"capital_billion":1.8446,"capital_report_date":"2021-06-30"},{"date":"2021-11-22","open":28.16,"high":28.35,"low":26.95,"close":27.4,"volume":81085,"ma20":28.155,"cross_above_ma20":false,"ma20_rising":false,"ma20_distance_pct":-2.6815840881,"capital_billion":1.8446,"capital_report_date":"2021-06-30"},{"date":"2021-11-29","open":27.35,"high":27.35,"low":26.2,"close":27.35,"volume":12798,"ma20":27.89,"cross_above_ma20":false,"ma20_rising":false,"ma20_distance_pct":-1.9361778415,"capital_billion":1.8446,"capital_report_date":"2021-06-30"},{"date":"2021-12-06","open":27.46,"high":28.05,"low":27.2,"close":28.05,"volume":21793,"ma20":27.68,"cross_above_ma20":true,"ma20_rising":false,"ma20_distance_pct":1.3367052023,"capital_billion":1.8446,"capital_report_date":"2021-06-30"},{"date":"2021-12-13","open":27.53,"high":27.65,"low":26.85,"close":27.0,"volume":142176,"ma20":27.4775,"cross_above_ma20":false,"ma20_rising":false,"ma20_distance_pct":-1.7377854608,"capital_billion":1.8446,"capital_report_date":"2021-06-30"},{"date":"2021-12-20","open":26.95,"high":27.05,"low":26.35,"close":26.6,"volume":21629,"ma20":27.3225,"cross_above_ma20":false,"ma20_rising":false,"ma20_distance_pct":-2.6443407448,"capital_billion":1.8446,"capital_report_date":"2021-06-30"},{"date":"2021-12-27","open":27.06,"high":27.25,"low":26.7,"close":26.7,"volume":9819,"ma20":27.3475,"cross_above_ma20":false,"ma20_rising":true,"ma20_distance_pct":-2.3676752902,"capital_billion":1.8446,"capital_report_date":"2021-06-30"},{"date":"2022-01-03","open":27.47,"high":28.25,"low":26.75,"close":26.75,"volume":38510,"ma20":27.235,"cross_above_ma20":false,"ma20_rising":false,"ma20_distance_pct":-1.7807967689,"capital_billion":1.8446,"capital_report_date":"2021-06-30"},{"date":"2022-01-10","open":27.08,"high":29.7,"low":27.05,"close":29.05,"volume":73333,"ma20":27.325,"cross_above_ma20":true,"ma20_rising":true,"ma20_distance_pct":6.3129002745,"capital_billion":1.8446,"capital_report_date":"2021-06-30"},{"date":"2022-01-17","open":30.23,"high":31.05,"low":29.6,"close":30.05,"volume":48200,"ma20":27.4,"cross_above_ma20":false,"ma20_rising":true,"ma20_distance_pct":9.6715328467,"capital_billion":1.8446,"capital_report_date":"2021-06-30"},{"date":"2022-01-24","open":29.44,"high":29.5,"low":29.3,"close":29.5,"volume":18117,"ma20":27.5275,"cross_above_ma20":false,"ma20_rising":true,"ma20_distance_pct":7.165561711,"capital_billion":1.8446,"capital_report_date":"2021-06-30"},{"date":"2022-02-07","open":30.5,"high":30.5,"low":28.9,"close":29.25,"volume":51218,"ma20":27.6575,"cross_above_ma20":false,"ma20_rising":true,"ma20_distance_pct":5.7579318449,"capital_billion":1.8446,"capital_report_date":"2021-06-30"},{"date":"2022-02-14","open":29.08,"high":29.35,"low":28.45,"close":29.15,"volume":37550,"ma20":27.785,"cross_above_ma20":false,"ma20_rising":true,"ma20_distance_pct":4.9127226921,"capital_billion":1.8446,"capital_report_date":"2021-06-30"},{"date":"2022-02-21","open":28.96,"high":29.2,"low":28.35,"close":29.05,"volume":34909,"ma20":27.935,"cross_above_ma20":false,"ma20_rising":true,"ma20_distance_pct":3.9914086272,"capital_billion":1.8446,"capital_report_date":"2021-06-30"},{"date":"2022-02-28","open":28.97,"high":29.45,"low":28.75,"close":29.05,"volume":49414,"ma20":28.1125,"cross_above_ma20":false,"ma20_rising":true,"ma20_distance_pct":3.3348154735,"capital_billion":1.8446,"capital_report_date":"2021-06-30"},{"date":"2022-03-07","open":28.82,"high":29.1,"low":28.45,"close":28.7,"volume":77035,"ma20":28.3125,"cross_above_ma20":false,"ma20_rising":true,"ma20_distance_pct":1.3686534216,"capital_billion":1.8446,"capital_report_date":"2021-06-30"},{"date":"2022-03-14","open":28.71,"high":29.45,"low":28.35,"close":28.7,"volume":46494,"ma20":28.4875,"cross_above_ma20":false,"ma20_rising":true,"ma20_distance_pct":0.7459412023,"capital_billion":1.8446,"capital_report_date":"2021-06-30"},{"date":"2022-03-21","open":28.66,"high":29.7,"low":28.3,"close":28.5,"volume":31834,"ma20":28.3825,"cross_above_ma20":false,"ma20_rising":false,"ma20_distance_pct":0.4139874923,"capital_billion":1.8446,"capital_report_date":"2021-06-30"},{"date":"2022-03-28","open":28.57,"high":28.75,"low":28.35,"close":28.65,"volume":44184,"ma20":28.3875,"cross_above_ma20":false,"ma20_rising":true,"ma20_distance_pct":0.9247027741,"capital_billion":1.8446,"capital_report_date":"2021-06-30"},{"date":"2022-04-04","open":28.53,"high":28.7,"low":27.9,"close":28.0,"volume":145586,"ma20":28.32,"cross_above_ma20":false,"ma20_rising":false,"ma20_distance_pct":-1.1299435028,"capital_billion":1.8446,"capital_report_date":"2021-12-31"},{"date":"2022-04-11","open":28.02,"high":28.1,"low":27.05,"close":27.05,"volume":80704,"ma20":28.2275,"cross_above_ma20":false,"ma20_rising":false,"ma20_distance_pct":-4.1714639979,"capital_billion":1.8446,"capital_report_date":"2021-12-31"},{"date":"2022-04-18","open":26.95,"high":28.1,"low":26.7,"close":27.05,"volume":73049,"ma20":28.21,"cross_above_ma20":false,"ma20_rising":false,"ma20_distance_pct":-4.1120170152,"capital_billion":1.8446,"capital_report_date":"2021-12-31"},{"date":"2022-04-25","open":26.39,"high":26.55,"low":26.2,"close":26.5,"volume":3260,"ma20":28.1675,"cross_above_ma20":false,"ma20_rising":false,"ma20_distance_pct":-5.9199431969,"capital_billion":1.8446,"capital_report_date":"2021-12-31"},{"date":"2022-05-02","open":26.36,"high":26.55,"low":26.05,"close":26.55,"volume":19628,"ma20":28.0925,"cross_above_ma20":false,"ma20_rising":false,"ma20_distance_pct":-5.4907893566,"capital_billion":1.8446,"capital_report_date":"2021-12-31"},{"date":"2022-05-09","open":26.31,"high":26.35,"low":25.0,"close":25.25,"volume":27833,"ma20":28.005,"cross_above_ma20":false,"ma20_rising":false,"ma20_distance_pct":-9.8375290127,"capital_billion":1.8446,"capital_report_date":"2021-12-31"},{"date":"2022-05-16","open":25.06,"high":26.35,"low":24.9,"close":26.35,"volume":25830,"ma20":27.9925,"cross_above_ma20":false,"ma20_rising":false,"ma20_distance_pct":-5.8676431187,"capital_billion":1.8446,"capital_report_date":"2021-12-31"},{"date":"2022-05-23","open":25.69,"high":26.95,"low":25.1,"close":26.35,"volume":37021,"ma20":27.975,"cross_above_ma20":false,"ma20_rising":false,"ma20_distance_pct":-5.8087578195,"capital_billion":1.8446,"capital_report_date":"2021-12-31"},{"date":"2022-05-30","open":28.7,"high":29.75,"low":28.7,"close":29.75,"volume":10340,"ma20":28.125,"cross_above_ma20":true,"ma20_rising":true,"ma20_distance_pct":5.7777777778,"capital_billion":1.8446,"capital_report_date":"2021-12-31"},{"date":"2022-06-06","open":29.25,"high":30.05,"low":28.45,"close":29.25,"volume":23480,"ma20":28.135,"cross_above_ma20":false,"ma20_rising":true,"ma20_distance_pct":3.9630353652,"capital_billion":1.8446,"capital_report_date":"2021-12-31"},{"date":"2022-06-13","open":28.05,"high":28.05,"low":26.75,"close":28.05,"volume":5466,"ma20":28.035,"cross_above_ma20":false,"ma20_rising":false,"ma20_distance_pct":0.0535045479,"capital_billion":1.8446,"capital_report_date":"2021-12-31"},{"date":"2022-06-20","open":27.94,"high":27.95,"low":26.2,"close":26.55,"volume":96195,"ma20":27.8875,"cross_above_ma20":false,"ma20_rising":false,"ma20_distance_pct":-4.7960555805,"capital_billion":1.8446,"capital_report_date":"2021-12-31"},{"date":"2022-06-27","open":26.23,"high":26.75,"low":26.05,"close":26.75,"volume":10021,"ma20":27.7625,"cross_above_ma20":false,"ma20_rising":false,"ma20_distance_pct":-3.6470058532,"capital_billion":1.8446,"capital_report_date":"2021-12-31"},{"date":"2022-07-04","open":26.75,"high":27.0,"low":26.75,"close":27.0,"volume":6010,"ma20":27.655,"cross_above_ma20":false,"ma20_rising":false,"ma20_distance_pct":-2.3684686314,"capital_billion":1.8446,"capital_report_date":"2021-12-31"},{"date":"2022-07-11","open":26.75,"high":27.05,"low":25.75,"close":26.55,"volume":20152,"ma20":27.53,"cross_above_ma20":false,"ma20_rising":false,"ma20_distance_pct":-3.5597529967,"capital_billion":1.8446,"capital_report_date":"2021-12-31"},{"date":"2022-07-18","open":25.89,"high":25.95,"low":25.85,"close":25.95,"volume":9000,"ma20":27.375,"cross_above_ma20":false,"ma20_rising":false,"ma20_distance_pct":-5.2054794521,"capital_billion":1.8446,"capital_report_date":"2021-12-31"},{"date":"2022-07-25","open":28.88,"high":30.1,"low":28.6,"close":29.45,"volume":51350,"ma20":27.4125,"cross_above_ma20":true,"ma20_rising":true,"ma20_distance_pct":7.4327405381,"capital_billion":1.8446,"capital_report_date":"2021-12-31"},{"date":"2022-08-01","open":27.4,"high":27.5,"low":26.2,"close":27.4,"volume":51129,"ma20":27.3475,"cross_above_ma20":false,"ma20_rising":false,"ma20_distance_pct":0.1919736722,"capital_billion":1.8446,"capital_report_date":"2021-12-31"},{"date":"2022-08-08","open":26.55,"high":27.4,"low":26.5,"close":27.4,"volume":2110,"ma20":27.2925,"cross_above_ma20":false,"ma20_rising":false,"ma20_distance_pct":0.3938811029,"capital_billion":1.8446,"capital_report_date":"2021-12-31"},{"date":"2022-08-15","open":28.55,"high":28.85,"low":28.55,"close":28.85,"volume":5210,"ma20":27.3025,"cross_above_ma20":false,"ma20_rising":true,"ma20_distance_pct":5.6679791228,"capital_billion":1.8446,"capital_report_date":"2022-06-30"},{"date":"2022-08-22","open":29.67,"high":30.15,"low":28.2,"close":29.65,"volume":82390,"ma20":27.385,"cross_above_ma20":false,"ma20_rising":true,"ma20_distance_pct":8.2709512507,"capital_billion":1.8446,"capital_report_date":"2022-06-30"},{"date":"2022-08-29","open":28.71,"high":30.2,"low":28.55,"close":29.1,"volume":159990,"ma20":27.4875,"cross_above_ma20":false,"ma20_rising":true,"ma20_distance_pct":5.8663028649,"capital_billion":1.8446,"capital_report_date":"2022-06-30"},{"date":"2022-09-05","open":29.03,"high":29.1,"low":28.15,"close":28.9,"volume":29021,"ma20":27.58,"cross_above_ma20":false,"ma20_rising":true,"ma20_distance_pct":4.7860768673,"capital_billion":1.8446,"capital_report_date":"2022-06-30"},{"date":"2022-09-19","open":36.52,"high":38.25,"low":35.9,"close":37.6,"volume":193403,"ma20":28.135,"cross_above_ma20":false,"ma20_rising":true,"ma20_distance_pct":33.6413719566,"capital_billion":1.8446,"capital_report_date":"2022-06-30"},{"date":"2022-09-26","open":36.72,"high":37.6,"low":34.65,"close":36.1,"volume":205591,"ma20":28.6125,"cross_above_ma20":false,"ma20_rising":true,"ma20_distance_pct":26.1686325907,"capital_billion":1.8446,"capital_report_date":"2022-06-30"},{"date":"2022-10-03","open":35.83,"high":37.0,"low":31.95,"close":32.45,"volume":170488,"ma20":28.9725,"cross_above_ma20":false,"ma20_rising":true,"ma20_distance_pct":12.0027612391,"capital_billion":1.8446,"capital_report_date":"2022-06-30"},{"date":"2022-10-10","open":31.54,"high":33.45,"low":29.7,"close":30.1,"volume":154221,"ma20":29.16,"cross_above_ma20":false,"ma20_rising":true,"ma20_distance_pct":3.2235939643,"capital_billion":1.8446,"capital_report_date":"2022-06-30"},{"date":"2022-10-17","open":27.46,"high":27.8,"low":26.55,"close":27.1,"volume":54837,"ma20":29.1975,"cross_above_ma20":false,"ma20_rising":true,"ma20_distance_pct":-7.1838342324,"capital_billion":1.8446,"capital_report_date":"2022-06-30"},{"date":"2022-10-24","open":27.21,"high":27.45,"low":25.7,"close":26.3,"volume":64055,"ma20":29.025,"cross_above_ma20":false,"ma20_rising":false,"ma20_distance_pct":-9.3884582257,"capital_billion":1.8446,"capital_report_date":"2022-06-30"},{"date":"2022-10-31","open":26.5,"high":27.0,"low":26.15,"close":26.65,"volume":60389,"ma20":28.895,"cross_above_ma20":false,"ma20_rising":false,"ma20_distance_pct":-7.7695102959,"capital_billion":1.8446,"capital_report_date":"2022-06-30"},{"date":"2022-11-07","open":26.63,"high":29.1,"low":26.45,"close":27.95,"volume":118828,"ma20":28.89,"cross_above_ma20":false,"ma20_rising":false,"ma20_distance_pct":-3.2537210107,"capital_billion":1.8446,"capital_report_date":"2022-06-30"},{"date":"2022-11-14","open":27.79,"high":28.1,"low":26.7,"close":26.85,"volume":87804,"ma20":28.905,"cross_above_ma20":false,"ma20_rising":true,"ma20_distance_pct":-7.1094966269,"capital_billion":1.8446,"capital_report_date":"2022-06-30"},{"date":"2022-11-21","open":27.04,"high":28.05,"low":26.85,"close":28.0,"volume":18632,"ma20":28.9675,"cross_above_ma20":false,"ma20_rising":true,"ma20_distance_pct":-3.3399499439,"capital_billion":1.8446,"capital_report_date":"2022-06-30"},{"date":"2022-11-28","open":27.52,"high":28.05,"low":26.9,"close":27.15,"volume":94955,"ma20":28.975,"cross_above_ma20":false,"ma20_rising":true,"ma20_distance_pct":-6.2985332183,"capital_billion":1.8446,"capital_report_date":"2022-06-30"},{"date":"2022-12-05","open":27.54,"high":28.05,"low":27.05,"close":27.5,"volume":53342,"ma20":29.0225,"cross_above_ma20":false,"ma20_rising":true,"ma20_distance_pct":-5.245929882,"capital_billion":1.8446,"capital_report_date":"2022-06-30"},{"date":"2022-12-12","open":26.9,"high":27.7,"low":26.45,"close":27.1,"volume":40609,"ma20":29.08,"cross_above_ma20":false,"ma20_rising":true,"ma20_distance_pct":-6.8088033012,"capital_billion":1.8446,"capital_report_date":"2022-06-30"},{"date":"2022-12-19","open":26.91,"high":27.45,"low":25.65,"close":26.75,"volume":99394,"ma20":28.945,"cross_above_ma20":false,"ma20_rising":false,"ma20_distance_pct":-7.5833477285,"capital_billion":1.8446,"capital_report_date":"2022-06-30"},{"date":"2022-12-26","open":26.24,"high":26.7,"low":25.65,"close":26.55,"volume":45890,"ma20":28.9025,"cross_above_ma20":false,"ma20_rising":false,"ma20_distance_pct":-8.139434305,"capital_billion":1.8446,"capital_report_date":"2022-06-30"},{"date":"2023-01-02","open":26.0,"high":28.0,"low":25.0,"close":25.95,"volume":154152,"ma20":28.83,"cross_above_ma20":false,"ma20_rising":false,"ma20_distance_pct":-9.9895941727,"capital_billion":1.8446,"capital_report_date":"2022-06-30"},{"date":"2023-01-09","open":26.3,"high":27.05,"low":26.0,"close":26.55,"volume":45573,"ma20":28.715,"cross_above_ma20":false,"ma20_rising":false,"ma20_distance_pct":-7.5396134425,"capital_billion":1.8446,"capital_report_date":"2022-06-30"},{"date":"2023-01-16","open":25.62,"high":26.1,"low":25.5,"close":25.6,"volume":30900,"ma20":28.5125,"cross_above_ma20":false,"ma20_rising":false,"ma20_distance_pct":-10.2148180623,"capital_billion":1.8446,"capital_report_date":"2022-06-30"},{"date":"2023-01-30","open":25.85,"high":27.3,"low":25.45,"close":27.25,"volume":61095,"ma20":28.42,"cross_above_ma20":false,"ma20_rising":false,"ma20_distance_pct":-4.1168191414,"capital_billion":1.8446,"capital_report_date":"2022-06-30"},{"date":"2023-02-06","open":29.63,"high":30.85,"low":29.05,"close":29.75,"volume":162927,"ma20":28.4625,"cross_above_ma20":true,"ma20_rising":true,"ma20_distance_pct":4.5234958278,"capital_billion":1.8446,"capital_report_date":"2022-06-30"},{"date":"2023-02-13","open":29.56,"high":29.6,"low":28.7,"close":29.0,"volume":48002,"ma20":28.0325,"cross_above_ma20":false,"ma20_rising":false,"ma20_distance_pct":3.4513511103,"capital_billion":1.8446,"capital_report_date":"2022-06-30"},{"date":"2023-02-20","open":28.74,"high":30.6,"low":27.85,"close":30.0,"volume":43458,"ma20":27.7275,"cross_above_ma20":false,"ma20_rising":false,"ma20_distance_pct":8.1958344604,"capital_billion":1.8446,"capital_report_date":"2022-06-30"},{"date":"2023-02-27","open":29.72,"high":30.0,"low":28.5,"close":29.45,"volume":12030,"ma20":27.5775,"cross_above_ma20":false,"ma20_rising":false,"ma20_distance_pct":6.7899555797,"capital_billion":1.8446,"capital_report_date":"2022-06-30"},{"date":"2023-03-06","open":31.15,"high":37.5,"low":30.6,"close":33.4,"volume":367974,"ma20":27.7425,"cross_above_ma20":false,"ma20_rising":true,"ma20_distance_pct":20.3928989817,"capital_billion":1.8446,"capital_report_date":"2022-06-30"},{"date":"2023-03-13","open":31.79,"high":32.65,"low":31.15,"close":32.35,"volume":44369,"ma20":28.005,"cross_above_ma20":false,"ma20_rising":true,"ma20_distance_pct":15.5150865917,"capital_billion":1.8446,"capital_report_date":"2022-06-30"},{"date":"2023-03-20","open":31.78,"high":33.0,"low":28.05,"close":31.15,"volume":210412,"ma20":28.2475,"cross_above_ma20":false,"ma20_rising":true,"ma20_distance_pct":10.275245597,"capital_billion":1.8446,"capital_report_date":"2022-06-30"},{"date":"2023-03-27","open":31.17,"high":31.6,"low":28.9,"close":31.0,"volume":87639,"ma20":28.465,"cross_above_ma20":false,"ma20_rising":true,"ma20_distance_pct":8.9056736343,"capital_billion":1.8446,"capital_report_date":"2022-06-30"},{"date":"2023-04-03","open":30.98,"high":31.2,"low":30.0,"close":31.0,"volume":30263,"ma20":28.6175,"cross_above_ma20":false,"ma20_rising":true,"ma20_distance_pct":8.3253254128,"capital_billion":1.8446,"capital_report_date":"2022-06-30"},{"date":"2023-04-10","open":30.76,"high":32.45,"low":30.0,"close":31.55,"volume":109875,"ma20":28.8525,"cross_above_ma20":false,"ma20_rising":true,"ma20_distance_pct":9.3492764925,"capital_billion":1.8446,"capital_report_date":"2022-06-30"},{"date":"2023-04-17","open":35.06,"high":36.1,"low":33.05,"close":34.45,"volume":240216,"ma20":29.175,"cross_above_ma20":false,"ma20_rising":true,"ma20_distance_pct":18.0805484147,"capital_billion":1.8446,"capital_report_date":"2022-06-30"},{"date":"2023-04-24","open":34.73,"high":35.9,"low":33.3,"close":34.3,"volume":97991,"ma20":29.5325,"cross_above_ma20":false,"ma20_rising":true,"ma20_distance_pct":16.1432320325,"capital_billion":1.8446,"capital_report_date":"2022-06-30"},{"date":"2023-05-01","open":33.99,"high":34.95,"low":33.15,"close":34.5,"volume":95925,"ma20":29.8825,"cross_above_ma20":false,"ma20_rising":true,"ma20_distance_pct":15.4521877353,"capital_billion":1.8446,"capital_report_date":"2022-06-30"},{"date":"2023-05-08","open":34.89,"high":35.85,"low":32.8,"close":34.1,"volume":166784,"ma20":30.2325,"cross_above_ma20":false,"ma20_rising":true,"ma20_distance_pct":12.792524601,"capital_billion":1.8446,"capital_report_date":"2022-06-30"},{"date":"2023-05-15","open":34.15,"high":36.2,"low":33.6,"close":35.05,"volume":660370,"ma20":30.6475,"cross_above_ma20":false,"ma20_rising":true,"ma20_distance_pct":14.3649563586,"capital_billion":1.8446,"capital_report_date":"2022-06-30"},{"date":"2023-05-22","open":35.2,"high":35.85,"low":32.75,"close":33.0,"volume":134080,"ma20":30.97,"cross_above_ma20":false,"ma20_rising":true,"ma20_distance_pct":6.5547303842,"capital_billion":1.8446,"capital_report_date":"2022-06-30"},{"date":"2023-05-29","open":30.58,"high":31.8,"low":29.5,"close":31.8,"volume":133332,"ma20":31.2625,"cross_above_ma20":false,"ma20_rising":true,"ma20_distance_pct":1.7193122751,"capital_billion":1.8446,"capital_report_date":"2022-06-30"},{"date":"2023-06-05","open":31.93,"high":33.3,"low":30.9,"close":32.0,"volume":71322,"ma20":31.535,"cross_above_ma20":false,"ma20_rising":true,"ma20_distance_pct":1.474552085,"capital_billion":1.8446,"capital_report_date":"2022-06-30"},{"date":"2023-06-12","open":31.32,"high":32.35,"low":29.95,"close":31.15,"volume":131762,"ma20":31.8125,"cross_above_ma20":false,"ma20_rising":true,"ma20_distance_pct":-2.0825147348,"capital_billion":1.8446,"capital_report_date":"2022-06-30"},{"date":"2023-06-19","open":30.83,"high":31.15,"low":29.6,"close":30.95,"volume":67843,"ma20":31.9975,"cross_above_ma20":false,"ma20_rising":true,"ma20_distance_pct":-3.2736932573,"capital_billion":1.8446,"capital_report_date":"2022-06-30"},{"date":"2023-06-26","open":30.45,"high":31.05,"low":28.25,"close":29.35,"volume":165759,"ma20":31.9775,"cross_above_ma20":false,"ma20_rising":false,"ma20_distance_pct":-8.2167148776,"capital_billion":1.8446,"capital_report_date":"2022-06-30"},{"date":"2023-07-03","open":29.19,"high":29.65,"low":27.95,"close":28.85,"volume":153951,"ma20":31.97,"cross_above_ma20":false,"ma20_rising":false,"ma20_distance_pct":-9.7591492024,"capital_billion":1.8446,"capital_report_date":"2022-06-30"},{"date":"2023-07-10","open":28.6,"high":29.3,"low":27.9,"close":28.05,"volume":52101,"ma20":31.8725,"cross_above_ma20":false,"ma20_rising":false,"ma20_distance_pct":-11.9930974978,"capital_billion":1.8446,"capital_report_date":"2022-06-30"},{"date":"2023-07-17","open":28.04,"high":28.05,"low":26.7,"close":27.7,"volume":106753,"ma20":31.785,"cross_above_ma20":false,"ma20_rising":false,"ma20_distance_pct":-12.8519742017,"capital_billion":1.8446,"capital_report_date":"2022-06-30"},{"date":"2023-07-24","open":27.5,"high":27.7,"low":26.6,"close":27.4,"volume":59928,"ma20":31.485,"cross_above_ma20":false,"ma20_rising":false,"ma20_distance_pct":-12.9744322693,"capital_billion":1.8446,"capital_report_date":"2022-06-30"},{"date":"2023-07-31","open":27.28,"high":27.4,"low":26.95,"close":27.35,"volume":19500,"ma20":31.235,"cross_above_ma20":false,"ma20_rising":false,"ma20_distance_pct":-12.4379702257,"capital_billion":1.8446,"capital_report_date":"2022-06-30"},{"date":"2023-08-07","open":27.29,"high":27.6,"low":26.4,"close":27.1,"volume":32690,"ma20":31.0325,"cross_above_ma20":false,"ma20_rising":false,"ma20_distance_pct":-12.6721985016,"capital_billion":1.8446,"capital_report_date":"2022-06-30"},{"date":"2023-08-21","open":26.81,"high":27.0,"low":25.8,"close":26.8,"volume":46209,"ma20":30.8225,"cross_above_ma20":false,"ma20_rising":false,"ma20_distance_pct":-13.0505312677,"capital_billion":1.8446,"capital_report_date":"2023-06-30"},{"date":"2023-08-28","open":27.0,"high":27.0,"low":25.75,"close":27.0,"volume":7377,"ma20":30.6225,"cross_above_ma20":false,"ma20_rising":false,"ma20_distance_pct":-11.8295371051,"capital_billion":1.8446,"capital_report_date":"2023-06-30"},{"date":"2023-09-04","open":27.0,"high":27.05,"low":27.0,"close":27.05,"volume":2003,"ma20":30.3975,"cross_above_ma20":false,"ma20_rising":false,"ma20_distance_pct":-11.0124187844,"capital_billion":1.8446,"capital_report_date":"2023-06-30"},{"date":"2023-09-11","open":26.83,"high":28.25,"low":25.8,"close":28.25,"volume":38699,"ma20":30.0875,"cross_above_ma20":false,"ma20_rising":false,"ma20_distance_pct":-6.1071873702,"capital_billion":1.8446,"capital_report_date":"2023-06-30"},{"date":"2023-09-18","open":27.4,"high":28.15,"low":27.0,"close":27.55,"volume":4112,"ma20":29.75,"cross_above_ma20":false,"ma20_rising":false,"ma20_distance_pct":-7.3949579832,"capital_billion":1.8446,"capital_report_date":"2023-06-30"},{"date":"2023-09-25","open":27.55,"high":28.3,"low":26.9,"close":27.1,"volume":24035,"ma20":29.38,"cross_above_ma20":false,"ma20_rising":false,"ma20_distance_pct":-7.7603812117,"capital_billion":1.8446,"capital_report_date":"2023-06-30"},{"date":"2023-10-02","open":26.52,"high":27.15,"low":25.9,"close":26.55,"volume":26517,"ma20":29.0025,"cross_above_ma20":false,"ma20_rising":false,"ma20_distance_pct":-8.4561675718,"capital_billion":1.8446,"capital_report_date":"2023-06-30"},{"date":"2023-10-09","open":27.03,"high":27.15,"low":26.0,"close":26.0,"volume":13525,"ma20":28.55,"cross_above_ma20":false,"ma20_rising":false,"ma20_distance_pct":-8.9316987741,"capital_billion":1.8446,"capital_report_date":"2023-06-30"},{"date":"2023-10-16","open":27.1,"high":27.1,"low":25.9,"close":26.1,"volume":19900,"ma20":28.205,"cross_above_ma20":false,"ma20_rising":false,"ma20_distance_pct":-7.4632157419,"capital_billion":1.8446,"capital_report_date":"2023-06-30"},{"date":"2023-10-23","open":26.21,"high":26.45,"low":25.35,"close":26.4,"volume":19854,"ma20":27.935,"cross_above_ma20":false,"ma20_rising":false,"ma20_distance_pct":-5.4948988724,"capital_billion":1.8446,"capital_report_date":"2023-06-30"},{"date":"2023-10-30","open":26.23,"high":26.55,"low":25.15,"close":26.4,"volume":68166,"ma20":27.655,"cross_above_ma20":false,"ma20_rising":false,"ma20_distance_pct":-4.5380582173,"capital_billion":1.8446,"capital_report_date":"2023-06-30"},{"date":"2023-11-06","open":25.41,"high":26.05,"low":24.95,"close":26.0,"volume":78993,"ma20":27.3975,"cross_above_ma20":false,"ma20_rising":false,"ma20_distance_pct":-5.1008303677,"capital_billion":1.8446,"capital_report_date":"2023-06-30"},{"date":"2023-11-13","open":25.15,"high":26.15,"low":25.0,"close":26.15,"volume":11355,"ma20":27.1575,"cross_above_ma20":false,"ma20_rising":false,"ma20_distance_pct":-3.7098407438,"capital_billion":1.8446,"capital_report_date":"2023-06-30"},{"date":"2023-11-20","open":25.35,"high":26.25,"low":24.9,"close":26.1,"volume":31256,"ma20":26.995,"cross_above_ma20":false,"ma20_rising":false,"ma20_distance_pct":-3.3154287831,"capital_billion":1.8446,"capital_report_date":"2023-06-30"},{"date":"2023-11-27","open":25.09,"high":26.1,"low":24.95,"close":26.0,"volume":58215,"ma20":26.8525,"cross_above_ma20":false,"ma20_rising":false,"ma20_distance_pct":-3.1747509543,"capital_billion":1.8446,"capital_report_date":"2023-06-30"},{"date":"2023-12-04","open":25.38,"high":25.95,"low":24.8,"close":25.4,"volume":57635,"ma20":26.72,"cross_above_ma20":false,"ma20_rising":false,"ma20_distance_pct":-4.9401197605,"capital_billion":1.8446,"capital_report_date":"2023-06-30"},{"date":"2023-12-11","open":24.94,"high":25.7,"low":24.75,"close":25.45,"volume":41312,"ma20":26.6075,"cross_above_ma20":false,"ma20_rising":false,"ma20_distance_pct":-4.3502771775,"capital_billion":1.8446,"capital_report_date":"2023-06-30"},{"date":"2023-12-18","open":25.65,"high":25.65,"low":24.5,"close":25.0,"volume":24405,"ma20":26.4875,"cross_above_ma20":false,"ma20_rising":false,"ma20_distance_pct":-5.6158565361,"capital_billion":1.8446,"capital_report_date":"2023-06-30"},{"date":"2023-12-25","open":25.2,"high":25.7,"low":24.75,"close":25.1,"volume":15132,"ma20":26.375,"cross_above_ma20":false,"ma20_rising":false,"ma20_distance_pct":-4.8341232227,"capital_billion":1.8446,"capital_report_date":"2023-06-30"},{"date":"2024-01-01","open":25.15,"high":25.55,"low":24.65,"close":25.1,"volume":12275,"ma20":26.275,"cross_above_ma20":false,"ma20_rising":false,"ma20_distance_pct":-4.4719314938,"capital_billion":1.8446,"capital_report_date":"2023-06-30"},{"date":"2024-01-08","open":24.88,"high":25.8,"low":24.6,"close":25.1,"volume":34838,"ma20":26.19,"cross_above_ma20":false,"ma20_rising":false,"ma20_distance_pct":-4.1618938526,"capital_billion":1.8446,"capital_report_date":"2023-06-30"},{"date":"2024-01-15","open":25.2,"high":25.65,"low":23.45,"close":24.35,"volume":66254,"ma20":26.0575,"cross_above_ma20":false,"ma20_rising":false,"ma20_distance_pct":-6.5528158879,"capital_billion":1.8446,"capital_report_date":"2023-06-30"},{"date":"2024-01-22","open":23.87,"high":24.35,"low":20.95,"close":22.05,"volume":96747,"ma20":25.8075,"cross_above_ma20":false,"ma20_rising":false,"ma20_distance_pct":-14.5597210113,"capital_billion":1.8446,"capital_report_date":"2023-06-30"},{"date":"2024-01-29","open":21.81,"high":22.25,"low":20.0,"close":20.4,"volume":96547,"ma20":25.415,"cross_above_ma20":false,"ma20_rising":false,"ma20_distance_pct":-19.7324414716,"capital_billion":1.8446,"capital_report_date":"2023-06-30"},{"date":"2024-02-05","open":20.39,"high":21.3,"low":20.3,"close":21.3,"volume":12781,"ma20":25.1025,"cross_above_ma20":false,"ma20_rising":false,"ma20_distance_pct":-15.1478936361,"capital_billion":1.8446,"capital_report_date":"2023-06-30"},{"date":"2024-02-26","open":24.08,"high":25.6,"low":23.55,"close":24.65,"volume":26467,"ma20":24.98,"cross_above_ma20":false,"ma20_rising":false,"ma20_distance_pct":-1.3210568455,"capital_billion":1.8446,"capital_report_date":"2023-06-30"},{"date":"2024-03-04","open":24.65,"high":24.7,"low":23.5,"close":24.65,"volume":8559,"ma20":24.885,"cross_above_ma20":false,"ma20_rising":false,"ma20_distance_pct":-0.9443439823,"capital_billion":1.8446,"capital_report_date":"2023-06-30"},{"date":"2024-03-11","open":24.65,"high":25.75,"low":23.6,"close":24.6,"volume":33580,"ma20":24.815,"cross_above_ma20":false,"ma20_rising":false,"ma20_distance_pct":-0.8664114447,"capital_billion":1.8446,"capital_report_date":"2023-06-30"},{"date":"2024-03-18","open":24.6,"high":24.6,"low":23.25,"close":23.9,"volume":77723,"ma20":24.705,"cross_above_ma20":false,"ma20_rising":false,"ma20_distance_pct":-3.2584497065,"capital_billion":1.8446,"capital_report_date":"2023-06-30"},{"date":"2024-03-25","open":23.85,"high":23.9,"low":23.25,"close":23.25,"volume":2025,"ma20":24.5475,"cross_above_ma20":false,"ma20_rising":false,"ma20_distance_pct":-5.2856706386,"capital_billion":1.8446,"capital_report_date":"2023-06-30"},{"date":"2024-04-01","open":24.33,"high":24.65,"low":22.7,"close":23.0,"volume":10766,"ma20":24.3775,"cross_above_ma20":false,"ma20_rising":false,"ma20_distance_pct":-5.6507024921,"capital_billion":1.8446,"capital_report_date":"2023-06-30"},{"date":"2024-04-08","open":23.75,"high":23.8,"low":22.65,"close":22.8,"volume":11792,"ma20":24.2175,"cross_above_ma20":false,"ma20_rising":false,"ma20_distance_pct":-5.8532053267,"capital_billion":1.8446,"capital_report_date":"2023-06-30"},{"date":"2024-04-15","open":22.7,"high":23.6,"low":21.2,"close":21.8,"volume":39050,"ma20":24.0,"cross_above_ma20":false,"ma20_rising":false,"ma20_distance_pct":-9.1666666667,"capital_billion":1.8446,"capital_report_date":"2023-06-30"},{"date":"2024-04-22","open":21.58,"high":21.8,"low":19.85,"close":20.8,"volume":57234,"ma20":23.735,"cross_above_ma20":false,"ma20_rising":false,"ma20_distance_pct":-12.3657046556,"capital_billion":1.8446,"capital_report_date":"2023-06-30"},{"date":"2024-04-29","open":21.16,"high":21.65,"low":20.55,"close":21.5,"volume":28919,"ma20":23.51,"cross_above_ma20":false,"ma20_rising":false,"ma20_distance_pct":-8.5495533815,"capital_billion":1.8446,"capital_report_date":"2023-06-30"},{"date":"2024-05-06","open":21.52,"high":22.1,"low":21.05,"close":22.1,"volume":19461,"ma20":23.345,"cross_above_ma20":false,"ma20_rising":false,"ma20_distance_pct":-5.3330477618,"capital_billion":1.8446,"capital_report_date":"2023-06-30"},{"date":"2024-05-13","open":22.05,"high":22.1,"low":20.75,"close":21.7,"volume":46180,"ma20":23.1575,"cross_above_ma20":false,"ma20_rising":false,"ma20_distance_pct":-6.2938572817,"capital_billion":1.8446,"capital_report_date":"2023-06-30"},{"date":"2024-05-20","open":20.89,"high":21.7,"low":20.05,"close":21.1,"volume":67325,"ma20":22.9625,"cross_above_ma20":false,"ma20_rising":false,"ma20_distance_pct":-8.111050626,"capital_billion":1.8446,"capital_report_date":"2023-06-30"},{"date":"2024-05-27","open":20.77,"high":21.05,"low":19.05,"close":20.1,"volume":122516,"ma20":22.7125,"cross_above_ma20":false,"ma20_rising":false,"ma20_distance_pct":-11.5024766098,"capital_billion":1.8446,"capital_report_date":"2023-06-30"},{"date":"2024-06-03","open":19.75,"high":20.2,"low":19.7,"close":20.1,"volume":37190,"ma20":22.4625,"cross_above_ma20":false,"ma20_rising":false,"ma20_distance_pct":-10.5175292154,"capital_billion":1.8446,"capital_report_date":"2023-06-30"},{"date":"2024-06-10","open":20.1,"high":21.0,"low":18.55,"close":19.35,"volume":105699,"ma20":22.175,"cross_above_ma20":false,"ma20_rising":false,"ma20_distance_pct":-12.7395715896,"capital_billion":1.8446,"capital_report_date":"2023-06-30"},{"date":"2024-06-17","open":19.17,"high":19.8,"low":18.95,"close":19.6,"volume":15804,"ma20":21.9375,"cross_above_ma20":false,"ma20_rising":false,"ma20_distance_pct":-10.6552706553,"capital_billion":1.8446,"capital_report_date":"2023-06-30"},{"date":"2024-06-24","open":19.44,"high":19.6,"low":18.3,"close":19.25,"volume":77881,"ma20":21.7975,"cross_above_ma20":false,"ma20_rising":false,"ma20_distance_pct":-11.6871200826,"capital_billion":1.8446,"capital_report_date":"2023-06-30"},{"date":"2024-07-01","open":18.94,"high":19.8,"low":18.1,"close":18.95,"volume":63673,"ma20":21.725,"cross_above_ma20":false,"ma20_rising":false,"ma20_distance_pct":-12.7733026467,"capital_billion":1.8446,"capital_report_date":"2023-06-30"},{"date":"2024-07-08","open":18.61,"high":18.95,"low":17.15,"close":17.9,"volume":208019,"ma20":21.555,"cross_above_ma20":false,"ma20_rising":false,"ma20_distance_pct":-16.9566225934,"capital_billion":1.8446,"capital_report_date":"2023-06-30"},{"date":"2024-07-15","open":17.8,"high":19.45,"low":17.05,"close":19.45,"volume":46898,"ma20":21.295,"cross_above_ma20":false,"ma20_rising":false,"ma20_distance_pct":-8.6640056351,"capital_billion":1.8446,"capital_report_date":"2023-06-30"},{"date":"2024-07-22","open":19.09,"high":19.45,"low":18.0,"close":18.65,"volume":20271,"ma20":20.995,"cross_above_ma20":false,"ma20_rising":false,"ma20_distance_pct":-11.16932603,"capital_billion":1.8446,"capital_report_date":"2023-06-30"},{"date":"2024-07-29","open":18.05,"high":18.8,"low":17.9,"close":18.1,"volume":19081,"ma20":20.67,"cross_above_ma20":false,"ma20_rising":false,"ma20_distance_pct":-12.4334784712,"capital_billion":1.8446,"capital_report_date":"2023-06-30"},{"date":"2024-08-05","open":17.96,"high":18.1,"low":17.1,"close":18.1,"volume":14377,"ma20":20.38,"cross_above_ma20":false,"ma20_rising":false,"ma20_distance_pct":-11.1874386654,"capital_billion":1.8446,"capital_report_date":"2023-06-30"},{"date":"2024-08-12","open":17.95,"high":18.75,"low":17.25,"close":18.7,"volume":49259,"ma20":20.1525,"cross_above_ma20":false,"ma20_rising":false,"ma20_distance_pct":-7.2075424885,"capital_billion":1.8446,"capital_report_date":"2023-06-30"},{"date":"2024-08-19","open":19.53,"high":19.65,"low":17.95,"close":18.55,"volume":28474,"ma20":19.93,"cross_above_ma20":false,"ma20_rising":false,"ma20_distance_pct":-6.9242348219,"capital_billion":1.8446,"capital_report_date":"2023-06-30"},{"date":"2024-08-26","open":18.49,"high":18.75,"low":17.75,"close":18.75,"volume":11444,"ma20":19.7275,"cross_above_ma20":false,"ma20_rising":false,"ma20_distance_pct":-4.955012039,"capital_billion":1.8446,"capital_report_date":"2023-06-30"},{"date":"2024-09-02","open":18.32,"high":18.75,"low":16.8,"close":17.15,"volume":35175,"ma20":19.495,"cross_above_ma20":false,"ma20_rising":false,"ma20_distance_pct":-12.0287253142,"capital_billion":1.8446,"capital_report_date":"2023-06-30"},{"date":"2024-09-09","open":17.03,"high":17.85,"low":16.7,"close":17.8,"volume":23282,"ma20":19.345,"cross_above_ma20":false,"ma20_rising":false,"ma20_distance_pct":-7.9865598346,"capital_billion":1.8446,"capital_report_date":"2023-06-30"},{"date":"2024-09-16","open":17.8,"high":17.8,"low":16.25,"close":17.1,"volume":50721,"ma20":19.125,"cross_above_ma20":false,"ma20_rising":false,"ma20_distance_pct":-10.5882352941,"capital_billion":1.8446,"capital_report_date":"2023-06-30"},{"date":"2024-09-23","open":17.15,"high":17.8,"low":16.95,"close":17.4,"volume":7333,"ma20":18.89,"cross_above_ma20":false,"ma20_rising":false,"ma20_distance_pct":-7.8877713076,"capital_billion":1.8446,"capital_report_date":"2023-06-30"},{"date":"2024-09-30","open":17.4,"high":17.5,"low":16.85,"close":17.35,"volume":10273,"ma20":18.6725,"cross_above_ma20":false,"ma20_rising":false,"ma20_distance_pct":-7.0826081135,"capital_billion":1.8446,"capital_report_date":"2023-06-30"},{"date":"2024-10-07","open":16.9,"high":17.35,"low":16.5,"close":16.9,"volume":9558,"ma20":18.4625,"cross_above_ma20":false,"ma20_rising":false,"ma20_distance_pct":-8.4631008802,"capital_billion":1.8446,"capital_report_date":"2023-06-30"},{"date":"2024-10-14","open":16.64,"high":16.9,"low":14.55,"close":14.9,"volume":74178,"ma20":18.2025,"cross_above_ma20":false,"ma20_rising":false,"ma20_distance_pct":-18.1431122099,"capital_billion":1.8446,"capital_report_date":"2023-06-30"},{"date":"2024-10-21","open":14.8,"high":15.65,"low":14.7,"close":15.4,"volume":135586,"ma20":17.9675,"cross_above_ma20":false,"ma20_rising":false,"ma20_distance_pct":-14.2896897175,"capital_billion":1.8446,"capital_report_date":"2023-06-30"},{"date":"2024-10-28","open":15.02,"high":16.75,"low":14.75,"close":16.75,"volume":69342,"ma20":17.8375,"cross_above_ma20":false,"ma20_rising":false,"ma20_distance_pct":-6.096706377,"capital_billion":1.8446,"capital_report_date":"2023-06-30"},{"date":"2024-11-04","open":18.8,"high":19.1,"low":17.8,"close":17.9,"volume":90466,"ma20":17.7525,"cross_above_ma20":true,"ma20_rising":false,"ma20_distance_pct":0.8308688917,"capital_billion":1.8446,"capital_report_date":"2023-06-30"},{"date":"2024-11-11","open":17.88,"high":18.7,"low":16.55,"close":17.3,"volume":54700,"ma20":17.655,"cross_above_ma20":false,"ma20_rising":false,"ma20_distance_pct":-2.0107618238,"capital_billion":1.8446,"capital_report_date":"2023-06-30"},{"date":"2024-11-18","open":17.01,"high":17.3,"low":15.85,"close":16.5,"volume":39814,"ma20":17.5325,"cross_above_ma20":false,"ma20_rising":false,"ma20_distance_pct":-5.8890631684,"capital_billion":1.8446,"capital_report_date":"2023-06-30"},{"date":"2024-11-25","open":16.47,"high":16.5,"low":15.55,"close":16.25,"volume":64171,"ma20":17.45,"cross_above_ma20":false,"ma20_rising":false,"ma20_distance_pct":-6.8767908309,"capital_billion":1.8446,"capital_report_date":"2023-06-30"},{"date":"2024-12-02","open":17.04,"high":17.5,"low":16.45,"close":16.8,"volume":20159,"ma20":17.3175,"cross_above_ma20":false,"ma20_rising":false,"ma20_distance_pct":-2.9883066262,"capital_billion":1.8446,"capital_report_date":"2023-06-30"},{"date":"2024-12-09","open":16.46,"high":16.8,"low":15.7,"close":16.35,"volume":62275,"ma20":17.2025,"cross_above_ma20":false,"ma20_rising":false,"ma20_distance_pct":-4.9556750472,"capital_billion":1.8446,"capital_report_date":"2023-06-30"},{"date":"2024-12-16","open":15.95,"high":25.25,"low":15.05,"close":21.5,"volume":298456,"ma20":17.3725,"cross_above_ma20":true,"ma20_rising":true,"ma20_distance_pct":23.7588142179,"capital_billion":1.8446,"capital_report_date":"2023-06-30"},{"date":"2024-12-23","open":22.39,"high":23.0,"low":20.3,"close":22.45,"volume":126107,"ma20":17.59,"cross_above_ma20":false,"ma20_rising":true,"ma20_distance_pct":27.6293348493,"capital_billion":1.8446,"capital_report_date":"2023-06-30"},{"date":"2024-12-30","open":22.44,"high":22.8,"low":19.9,"close":22.35,"volume":256123,"ma20":17.7725,"cross_above_ma20":false,"ma20_rising":true,"ma20_distance_pct":25.7560838374,"capital_billion":1.8446,"capital_report_date":"2023-06-30"},{"date":"2025-01-06","open":24.03,"high":26.15,"low":20.9,"close":21.8,"volume":153919,"ma20":17.935,"cross_above_ma20":false,"ma20_rising":true,"ma20_distance_pct":21.5500418177,"capital_billion":1.8446,"capital_report_date":"2023-06-30"},{"date":"2025-01-13","open":21.26,"high":21.95,"low":20.15,"close":21.45,"volume":136871,"ma20":18.07,"cross_above_ma20":false,"ma20_rising":true,"ma20_distance_pct":18.7050359712,"capital_billion":1.8446,"capital_report_date":"2023-06-30"},{"date":"2025-01-20","open":20.79,"high":21.45,"low":19.95,"close":21.1,"volume":84691,"ma20":18.2675,"cross_above_ma20":false,"ma20_rising":true,"ma20_distance_pct":15.5056794854,"capital_billion":1.8446,"capital_report_date":"2023-06-30"},{"date":"2025-02-03","open":20.78,"high":22.25,"low":20.45,"close":20.95,"volume":95294,"ma20":18.425,"cross_above_ma20":false,"ma20_rising":true,"ma20_distance_pct":13.7042062415,"capital_billion":1.8446,"capital_report_date":"2023-06-30"},{"date":"2025-02-10","open":20.78,"high":20.95,"low":19.6,"close":20.45,"volume":100408,"ma20":18.5925,"cross_above_ma20":false,"ma20_rising":true,"ma20_distance_pct":9.9905876025,"capital_billion":1.8446,"capital_report_date":"2023-06-30"},{"date":"2025-02-17","open":19.88,"high":20.45,"low":18.6,"close":19.35,"volume":93731,"ma20":18.69,"cross_above_ma20":false,"ma20_rising":true,"ma20_distance_pct":3.5313001605,"capital_billion":1.8446,"capital_report_date":"2023-06-30"},{"date":"2025-02-24","open":18.87,"high":19.8,"low":18.8,"close":19.0,"volume":55898,"ma20":18.7725,"cross_above_ma20":false,"ma20_rising":true,"ma20_distance_pct":1.2118790784,"capital_billion":1.8446,"capital_report_date":"2023-06-30"},{"date":"2025-03-03","open":18.89,"high":19.3,"low":18.4,"close":19.3,"volume":36848,"ma20":18.8925,"cross_above_ma20":false,"ma20_rising":true,"ma20_distance_pct":2.1569405849,"capital_billion":1.8446,"capital_report_date":"2023-06-30"},{"date":"2025-03-10","open":19.03,"high":19.55,"low":18.4,"close":19.15,"volume":46407,"ma20":19.105,"cross_above_ma20":false,"ma20_rising":true,"ma20_distance_pct":0.2355404344,"capital_billion":1.8446,"capital_report_date":"2023-06-30"},{"date":"2025-03-17","open":18.8,"high":19.2,"low":18.35,"close":19.2,"volume":53459,"ma20":19.295,"cross_above_ma20":false,"ma20_rising":true,"ma20_distance_pct":-0.4923555325,"capital_billion":1.8446,"capital_report_date":"2023-06-30"},{"date":"2025-03-24","open":18.4,"high":19.2,"low":17.65,"close":18.85,"volume":87431,"ma20":19.4,"cross_above_ma20":false,"ma20_rising":true,"ma20_distance_pct":-2.8350515464,"capital_billion":1.8446,"capital_report_date":"2023-06-30"},{"date":"2025-03-31","open":18.85,"high":19.05,"low":18.05,"close":18.95,"volume":29011,"ma20":19.4525,"cross_above_ma20":false,"ma20_rising":true,"ma20_distance_pct":-2.583215525,"capital_billion":1.8446,"capital_report_date":"2023-06-30"},{"date":"2025-04-07","open":17.54,"high":18.4,"low":16.95,"close":18.4,"volume":98706,"ma20":19.5075,"cross_above_ma20":false,"ma20_rising":true,"ma20_distance_pct":-5.6773036012,"capital_billion":1.8446,"capital_report_date":"2024-12-31"},{"date":"2025-04-14","open":18.4,"high":20.25,"low":17.7,"close":20.25,"volume":70734,"ma20":19.695,"cross_above_ma20":true,"ma20_rising":true,"ma20_distance_pct":2.8179741051,"capital_billion":1.8446,"capital_report_date":"2024-12-31"},{"date":"2025-04-21","open":19.8,"high":19.8,"low":18.15,"close":19.05,"volume":24103,"ma20":19.835,"cross_above_ma20":false,"ma20_rising":true,"ma20_distance_pct":-3.9576506176,"capital_billion":1.8446,"capital_report_date":"2024-12-31"},{"date":"2025-04-28","open":19.05,"high":19.05,"low":17.6,"close":18.15,"volume":30527,"ma20":19.9025,"cross_above_ma20":false,"ma20_rising":true,"ma20_distance_pct":-8.805426454,"capital_billion":1.8446,"capital_report_date":"2024-12-31"},{"date":"2025-05-05","open":18.11,"high":18.2,"low":17.45,"close":18.15,"volume":64,"ma20":19.9925,"cross_above_ma20":false,"ma20_rising":true,"ma20_distance_pct":-9.2159559835,"capital_billion":1.8446,"capital_report_date":"2024-12-31"},{"date":"2025-05-12","open":18.15,"high":18.2,"low":17.15,"close":18.15,"volume":72345,"ma20":19.825,"cross_above_ma20":false,"ma20_rising":false,"ma20_distance_pct":-8.4489281211,"capital_billion":1.8446,"capital_report_date":"2024-12-31"},{"date":"2025-05-19","open":18.15,"high":18.2,"low":17.15,"close":17.95,"volume":84380,"ma20":19.6,"cross_above_ma20":false,"ma20_rising":false,"ma20_distance_pct":-8.4183673469,"capital_billion":1.8446,"capital_report_date":"2024-12-31"},{"date":"2025-05-26","open":17.95,"high":18.05,"low":17.15,"close":18.05,"volume":47417,"ma20":19.385,"cross_above_ma20":false,"ma20_rising":false,"ma20_distance_pct":-6.8867681197,"capital_billion":1.8446,"capital_report_date":"2024-12-31"},{"date":"2025-06-02","open":17.49,"high":18.1,"low":17.4,"close":18.05,"volume":30529,"ma20":19.1975,"cross_above_ma20":false,"ma20_rising":false,"ma20_distance_pct":-5.9773407996,"capital_billion":1.8446,"capital_report_date":"2024-12-31"},{"date":"2025-06-09","open":17.67,"high":18.95,"low":17.5,"close":18.2,"volume":66626,"ma20":19.035,"cross_above_ma20":false,"ma20_rising":false,"ma20_distance_pct":-4.3866561597,"capital_billion":1.8446,"capital_report_date":"2024-12-31"},{"date":"2025-06-16","open":18.07,"high":18.1,"low":17.25,"close":17.95,"volume":69830,"ma20":18.8775,"cross_above_ma20":false,"ma20_rising":false,"ma20_distance_pct":-4.9132565223,"capital_billion":1.8446,"capital_report_date":"2024-12-31"},{"date":"2025-06-23","open":18.25,"high":18.25,"low":17.4,"close":17.6,"volume":9507,"ma20":18.71,"cross_above_ma20":false,"ma20_rising":false,"ma20_distance_pct":-5.9326563335,"capital_billion":1.8446,"capital_report_date":"2024-12-31"},{"date":"2025-06-30","open":17.53,"high":18.05,"low":16.7,"close":17.1,"volume":76664,"ma20":18.5425,"cross_above_ma20":false,"ma20_rising":false,"ma20_distance_pct":-7.7794256438,"capital_billion":1.8446,"capital_report_date":"2024-12-31"},{"date":"2025-07-07","open":17.01,"high":17.25,"low":16.4,"close":17.05,"volume":48015,"ma20":18.4275,"cross_above_ma20":false,"ma20_rising":false,"ma20_distance_pct":-7.4752408086,"capital_billion":1.8446,"capital_report_date":"2024-12-31"},{"date":"2025-07-14","open":17.05,"high":17.05,"low":16.2,"close":16.8,"volume":34064,"ma20":18.3175,"cross_above_ma20":false,"ma20_rising":false,"ma20_distance_pct":-8.2844274601,"capital_billion":1.8446,"capital_report_date":"2024-12-31"},{"date":"2025-07-21","open":17.05,"high":17.05,"low":16.15,"close":16.95,"volume":15937,"ma20":18.2,"cross_above_ma20":false,"ma20_rising":false,"ma20_distance_pct":-6.8681318681,"capital_billion":1.8446,"capital_report_date":"2024-12-31"},{"date":"2025-07-28","open":16.85,"high":16.85,"low":16.3,"close":16.85,"volume":1387,"ma20":18.085,"cross_above_ma20":false,"ma20_rising":false,"ma20_distance_pct":-6.8288636992,"capital_billion":1.8446,"capital_report_date":"2024-12-31"},{"date":"2025-08-04","open":16.85,"high":16.85,"low":15.25,"close":15.95,"volume":99487,"ma20":17.9225,"cross_above_ma20":false,"ma20_rising":false,"ma20_distance_pct":-11.0057190682,"capital_billion":1.8446,"capital_report_date":"2024-12-31"},{"date":"2025-08-11","open":16.51,"high":16.7,"low":15.3,"close":16.0,"volume":16155,"ma20":17.78,"cross_above_ma20":false,"ma20_rising":false,"ma20_distance_pct":-10.0112485939,"capital_billion":1.8446,"capital_report_date":"2024-12-31"},{"date":"2025-08-18","open":15.96,"high":16.1,"low":15.45,"close":15.6,"volume":40530,"ma20":17.6125,"cross_above_ma20":false,"ma20_rising":false,"ma20_distance_pct":-11.426543648,"capital_billion":1.8446,"capital_report_date":"2025-06-30"},{"date":"2025-08-25","open":15.6,"high":19.2,"low":15.4,"close":17.1,"volume":114119,"ma20":17.5475,"cross_above_ma20":false,"ma20_rising":false,"ma20_distance_pct":-2.5502208292,"capital_billion":1.8446,"capital_report_date":"2025-06-30"},{"date":"2025-09-01","open":17.1,"high":17.1,"low":15.9,"close":17.1,"volume":97542,"ma20":17.39,"cross_above_ma20":false,"ma20_rising":false,"ma20_distance_pct":-1.6676250719,"capital_billion":1.8446,"capital_report_date":"2025-06-30"},{"date":"2025-09-08","open":17.0,"high":17.85,"low":15.85,"close":16.6,"volume":83151,"ma20":17.2675,"cross_above_ma20":false,"ma20_rising":false,"ma20_distance_pct":-3.86564355,"capital_billion":1.8446,"capital_report_date":"2025-06-30"},{"date":"2025-09-15","open":16.12,"high":16.65,"low":15.75,"close":16.45,"volume":110303,"ma20":17.1825,"cross_above_ma20":false,"ma20_rising":false,"ma20_distance_pct":-4.2630583442,"capital_billion":1.8446,"capital_report_date":"2025-06-30"},{"date":"2025-09-22","open":16.45,"high":16.55,"low":15.7,"close":16.45,"volume":34200,"ma20":17.0975,"cross_above_ma20":false,"ma20_rising":false,"ma20_distance_pct":-3.7871033777,"capital_billion":1.8446,"capital_report_date":"2025-06-30"},{"date":"2025-09-29","open":16.4,"high":16.5,"low":15.6,"close":16.5,"volume":109257,"ma20":17.015,"cross_above_ma20":false,"ma20_rising":false,"ma20_distance_pct":-3.0267411108,"capital_billion":1.8446,"capital_report_date":"2025-06-30"},{"date":"2025-10-06","open":15.91,"high":16.55,"low":15.65,"close":16.1,"volume":48148,"ma20":16.9225,"cross_above_ma20":false,"ma20_rising":false,"ma20_distance_pct":-4.8603929679,"capital_billion":1.8446,"capital_report_date":"2025-06-30"},{"date":"2025-10-13","open":17.59,"high":17.75,"low":15.65,"close":16.5,"volume":77510,"ma20":16.845,"cross_above_ma20":false,"ma20_rising":false,"ma20_distance_pct":-2.0480854853,"capital_billion":1.8446,"capital_report_date":"2025-06-30"},{"date":"2025-10-20","open":16.16,"high":16.6,"low":15.9,"close":16.55,"volume":47140,"ma20":16.77,"cross_above_ma20":false,"ma20_rising":false,"ma20_distance_pct":-1.3118664281,"capital_billion":1.8446,"capital_report_date":"2025-06-30"},{"date":"2025-10-27","open":16.02,"high":16.65,"low":15.9,"close":16.5,"volume":113046,"ma20":16.685,"cross_above_ma20":false,"ma20_rising":false,"ma20_distance_pct":-1.1087803416,"capital_billion":1.8446,"capital_report_date":"2025-06-30"},{"date":"2025-11-03","open":16.06,"high":17.05,"low":16.0,"close":17.0,"volume":34013,"ma20":16.6375,"cross_above_ma20":true,"ma20_rising":false,"ma20_distance_pct":2.1788129226,"capital_billion":1.8446,"capital_report_date":"2025-06-30"},{"date":"2025-11-10","open":17.05,"high":17.8,"low":16.9,"close":16.9,"volume":30038,"ma20":16.6025,"cross_above_ma20":false,"ma20_rising":false,"ma20_distance_pct":1.7918988104,"capital_billion":1.8446,"capital_report_date":"2025-06-30"},{"date":"2025-11-17","open":16.84,"high":17.1,"low":16.2,"close":17.1,"volume":122537,"ma20":16.6025,"cross_above_ma20":false,"ma20_rising":false,"ma20_distance_pct":2.9965366662,"capital_billion":1.8446,"capital_report_date":"2025-06-30"},{"date":"2025-11-24","open":16.55,"high":18.0,"low":16.5,"close":17.0,"volume":231341,"ma20":16.6,"cross_above_ma20":false,"ma20_rising":false,"ma20_distance_pct":2.4096385542,"capital_billion":1.8446,"capital_report_date":"2025-06-30"},{"date":"2025-12-01","open":17.0,"high":17.65,"low":16.2,"close":17.45,"volume":34628,"ma20":16.6325,"cross_above_ma20":false,"ma20_rising":true,"ma20_distance_pct":4.9150759056,"capital_billion":1.8446,"capital_report_date":"2025-06-30"},{"date":"2025-12-08","open":17.18,"high":17.5,"low":16.15,"close":16.6,"volume":27381,"ma20":16.615,"cross_above_ma20":false,"ma20_rising":false,"ma20_distance_pct":-0.0902798676,"capital_billion":1.8446,"capital_report_date":"2025-06-30"},{"date":"2025-12-15","open":16.6,"high":17.25,"low":16.45,"close":17.0,"volume":37145,"ma20":16.6225,"cross_above_ma20":true,"ma20_rising":true,"ma20_distance_pct":2.2710181982,"capital_billion":1.8446,"capital_report_date":"2025-06-30"},{"date":"2025-12-22","open":17.0,"high":17.25,"low":16.4,"close":17.15,"volume":45016,"ma20":16.6825,"cross_above_ma20":false,"ma20_rising":true,"ma20_distance_pct":2.8023377791,"capital_billion":1.8446,"capital_report_date":"2025-06-30"},{"date":"2025-12-29","open":16.76,"high":17.5,"low":16.4,"close":17.35,"volume":97346,"ma20":16.75,"cross_above_ma20":false,"ma20_rising":true,"ma20_distance_pct":3.5820895522,"capital_billion":1.8446,"capital_report_date":"2025-06-30"},{"date":"2026-01-05","open":16.81,"high":17.5,"low":16.7,"close":17.15,"volume":75863,"ma20":16.8275,"cross_above_ma20":false,"ma20_rising":true,"ma20_distance_pct":1.9165057198,"capital_billion":1.8446,"capital_report_date":"2025-06-30"},{"date":"2026-01-12","open":17.45,"high":17.6,"low":16.8,"close":17.35,"volume":51787,"ma20":16.84,"cross_above_ma20":false,"ma20_rising":true,"ma20_distance_pct":3.0285035629,"capital_billion":1.8446,"capital_report_date":"2025-06-30"},{"date":"2026-01-19","open":16.92,"high":20.5,"low":16.45,"close":19.5,"volume":185729,"ma20":16.96,"cross_above_ma20":false,"ma20_rising":true,"ma20_distance_pct":14.9764150943,"capital_billion":1.8446,"capital_report_date":"2025-06-30"},{"date":"2026-01-26","open":19.86,"high":20.35,"low":18.55,"close":19.25,"volume":80516,"ma20":17.0925,"cross_above_ma20":false,"ma20_rising":true,"ma20_distance_pct":12.6224952465,"capital_billion":1.8446,"capital_report_date":"2025-06-30"},{"date":"2026-02-02","open":18.58,"high":19.25,"low":17.25,"close":18.1,"volume":35373,"ma20":17.175,"cross_above_ma20":false,"ma20_rising":true,"ma20_distance_pct":5.3857350801,"capital_billion":1.8446,"capital_report_date":"2025-06-30"},{"date":"2026-02-09","open":18.37,"high":19.0,"low":18.2,"close":19.0,"volume":5061,"ma20":17.3025,"cross_above_ma20":false,"ma20_rising":true,"ma20_distance_pct":9.8107209941,"capital_billion":1.8446,"capital_report_date":"2025-06-30"},{"date":"2026-02-23","open":18.07,"high":18.3,"low":17.3,"close":18.2,"volume":69123,"ma20":17.3875,"cross_above_ma20":false,"ma20_rising":true,"ma20_distance_pct":4.6728971963,"capital_billion":1.8446,"capital_report_date":"2025-06-30"},{"date":"2026-03-02","open":18.02,"high":21.75,"low":17.6,"close":21.3,"volume":232099,"ma20":17.6475,"cross_above_ma20":false,"ma20_rising":true,"ma20_distance_pct":20.6969825754,"capital_billion":1.8446,"capital_report_date":"2025-06-30"},{"date":"2026-03-09","open":19.77,"high":19.95,"low":17.7,"close":18.45,"volume":110384,"ma20":17.745,"cross_above_ma20":false,"ma20_rising":true,"ma20_distance_pct":3.9729501268,"capital_billion":1.8446,"capital_report_date":"2025-06-30"},{"date":"2026-03-16","open":18.21,"high":21.8,"low":17.1,"close":20.5,"volume":330893,"ma20":17.9425,"cross_above_ma20":false,"ma20_rising":true,"ma20_distance_pct":14.253866518,"capital_billion":1.8446,"capital_report_date":"2025-06-30"},{"date":"2026-03-23","open":20.38,"high":31.45,"low":20.35,"close":25.4,"volume":2488667,"ma20":18.3875,"cross_above_ma20":false,"ma20_rising":true,"ma20_distance_pct":38.13732155,"capital_billion":1.8446,"capital_report_date":"2025-06-30"},{"date":"2026-03-30","open":24.24,"high":26.2,"low":21.8,"close":22.7,"volume":698691,"ma20":18.6725,"cross_above_ma20":false,"ma20_rising":true,"ma20_distance_pct":21.569152497,"capital_billion":1.8446,"capital_report_date":"2025-06-30"},{"date":"2026-04-06","open":21.87,"high":23.2,"low":21.4,"close":22.4,"volume":59358,"ma20":18.9475,"cross_above_ma20":false,"ma20_rising":true,"ma20_distance_pct":18.2214012403,"capital_billion":1.8446,"capital_report_date":"2025-12-31"},{"date":"2026-04-13","open":27.07,"high":35.75,"low":23.0,"close":31.6,"volume":1327803,"ma20":19.6725,"cross_above_ma20":false,"ma20_rising":true,"ma20_distance_pct":60.6303215148,"capital_billion":1.8446,"capital_report_date":"2025-12-31"},{"date":"2026-04-20","open":31.2,"high":43.75,"low":27.0,"close":33.15,"volume":2688036,"ma20":20.48,"cross_above_ma20":false,"ma20_rising":true,"ma20_distance_pct":61.865234375,"capital_billion":1.8446,"capital_report_date":"2025-12-31"},{"date":"2026-04-27","open":33.38,"high":36.75,"low":29.55,"close":32.8,"volume":891538,"ma20":21.2475,"cross_above_ma20":false,"ma20_rising":true,"ma20_distance_pct":54.3711024826,"capital_billion":1.8446,"capital_report_date":"2025-12-31"},{"date":"2026-05-04","open":32.58,"high":33.2,"low":30.0,"close":31.2,"volume":551002,"ma20":21.9775,"cross_above_ma20":false,"ma20_rising":true,"ma20_distance_pct":41.9633716301,"capital_billion":1.8446,"capital_report_date":"2025-12-31"},{"date":"2026-05-11","open":26.81,"high":31.8,"low":24.9,"close":30.0,"volume":462438,"ma20":22.6275,"cross_above_ma20":false,"ma20_rising":true,"ma20_distance_pct":32.5820351342,"capital_billion":1.8446,"capital_report_date":"2025-12-31"},{"date":"2026-05-18","open":28.86,"high":29.0,"low":25.65,"close":27.0,"volume":432894,"ma20":23.12,"cross_above_ma20":false,"ma20_rising":true,"ma20_distance_pct":16.7820069204,"capital_billion":1.8446,"capital_report_date":"2025-12-31"},{"date":"2026-05-25","open":26.14,"high":28.3,"low":25.5,"close":27.5,"volume":209252,"ma20":23.6275,"cross_above_ma20":false,"ma20_rising":true,"ma20_distance_pct":16.3898000212,"capital_billion":1.8446,"capital_report_date":"2025-12-31"},{"date":"2026-06-01","open":26.91,"high":27.5,"low":24.8,"close":26.0,"volume":349907,"ma20":24.07,"cross_above_ma20":false,"ma20_rising":true,"ma20_distance_pct":8.0182800166,"capital_billion":1.8446,"capital_report_date":"2025-12-31"},{"date":"2026-06-08","open":25.37,"high":25.9,"low":23.85,"close":25.45,"volume":1212840,"ma20":24.475,"cross_above_ma20":false,"ma20_rising":true,"ma20_distance_pct":3.9836567926,"capital_billion":1.8446,"capital_report_date":"2025-12-31"},{"date":"2026-06-15","open":24.85,"high":25.2,"low":20.95,"close":21.9,"volume":971146,"ma20":24.595,"cross_above_ma20":false,"ma20_rising":true,"ma20_distance_pct":-10.9575116894,"capital_billion":1.8446,"capital_report_date":"2025-12-31"},{"date":"2026-06-22","open":23.12,"high":25.35,"low":21.0,"close":22.2,"volume":236159,"ma20":24.7425,"cross_above_ma20":false,"ma20_rising":true,"ma20_distance_pct":-10.275841164,"capital_billion":1.8446,"capital_report_date":"2025-12-31"},{"date":"2026-06-29","open":21.65,"high":22.9,"low":19.8,"close":20.5,"volume":222059,"ma20":24.8625,"cross_above_ma20":false,"ma20_rising":true,"ma20_distance_pct":-17.5465057818,"capital_billion":1.8446,"capital_report_date":"2025-12-31"},{"date":"2026-07-06","open":20.05,"high":21.15,"low":19.4,"close":20.2,"volume":108555,"ma20":24.9225,"cross_above_ma20":false,"ma20_rising":true,"ma20_distance_pct":-18.9487410974,"capital_billion":1.8446,"capital_report_date":"2025-12-31"},{"date":"2026-07-13","open":19.82,"high":21.55,"low":19.6,"close":21.4,"volume":159671,"ma20":25.0825,"cross_above_ma20":false,"ma20_rising":true,"ma20_distance_pct":-14.6815508821,"capital_billion":1.8446,"capital_report_date":"2025-12-31"}]