[{"date":"2025-01-06","open":105.83,"high":115.0,"low":78.0,"close":89.3,"volume":284867,"ma20":null,"cross_above_ma20":false,"ma20_rising":false,"ma20_distance_pct":null,"capital_billion":1.8,"capital_report_date":"2024-09-30"},{"date":"2025-01-13","open":85.08,"high":87.2,"low":77.1,"close":83.8,"volume":98194,"ma20":null,"cross_above_ma20":false,"ma20_rising":false,"ma20_distance_pct":null,"capital_billion":1.8,"capital_report_date":"2024-09-30"},{"date":"2025-01-20","open":83.86,"high":99.4,"low":80.1,"close":92.3,"volume":120361,"ma20":null,"cross_above_ma20":false,"ma20_rising":false,"ma20_distance_pct":null,"capital_billion":1.8,"capital_report_date":"2024-09-30"},{"date":"2025-02-03","open":86.06,"high":89.9,"low":82.8,"close":86.9,"volume":27816,"ma20":null,"cross_above_ma20":false,"ma20_rising":false,"ma20_distance_pct":null,"capital_billion":1.8,"capital_report_date":"2024-09-30"},{"date":"2025-02-10","open":87.78,"high":89.3,"low":82.8,"close":89.3,"volume":57927,"ma20":null,"cross_above_ma20":false,"ma20_rising":false,"ma20_distance_pct":null,"capital_billion":1.8,"capital_report_date":"2024-09-30"},{"date":"2025-02-17","open":86.0,"high":89.4,"low":84.1,"close":86.9,"volume":82434,"ma20":null,"cross_above_ma20":false,"ma20_rising":false,"ma20_distance_pct":null,"capital_billion":1.8,"capital_report_date":"2024-09-30"},{"date":"2025-02-24","open":88.66,"high":89.9,"low":83.1,"close":86.4,"volume":51808,"ma20":null,"cross_above_ma20":false,"ma20_rising":false,"ma20_distance_pct":null,"capital_billion":1.8,"capital_report_date":"2024-09-30"},{"date":"2025-03-03","open":84.95,"high":87.0,"low":83.1,"close":85.5,"volume":45343,"ma20":null,"cross_above_ma20":false,"ma20_rising":false,"ma20_distance_pct":null,"capital_billion":1.8,"capital_report_date":"2024-09-30"},{"date":"2025-03-10","open":83.1,"high":85.2,"low":81.6,"close":83.1,"volume":5360,"ma20":null,"cross_above_ma20":false,"ma20_rising":false,"ma20_distance_pct":null,"capital_billion":1.8,"capital_report_date":"2024-09-30"},{"date":"2025-03-17","open":83.34,"high":86.6,"low":82.9,"close":84.8,"volume":74815,"ma20":null,"cross_above_ma20":false,"ma20_rising":false,"ma20_distance_pct":null,"capital_billion":1.8,"capital_report_date":"2024-09-30"},{"date":"2025-03-24","open":85.08,"high":86.9,"low":82.1,"close":85.8,"volume":40594,"ma20":null,"cross_above_ma20":false,"ma20_rising":false,"ma20_distance_pct":null,"capital_billion":1.8,"capital_report_date":"2024-09-30"},{"date":"2025-03-31","open":85.96,"high":88.4,"low":83.1,"close":85.4,"volume":45840,"ma20":null,"cross_above_ma20":false,"ma20_rising":false,"ma20_distance_pct":null,"capital_billion":1.8,"capital_report_date":"2024-09-30"},{"date":"2025-04-07","open":67.72,"high":75.0,"low":66.5,"close":66.5,"volume":34204,"ma20":null,"cross_above_ma20":false,"ma20_rising":false,"ma20_distance_pct":null,"capital_billion":1.8,"capital_report_date":"2024-12-31"},{"date":"2025-04-14","open":76.4,"high":80.4,"low":72.7,"close":80.4,"volume":6191,"ma20":null,"cross_above_ma20":false,"ma20_rising":false,"ma20_distance_pct":null,"capital_billion":1.8,"capital_report_date":"2024-12-31"},{"date":"2025-04-21","open":79.84,"high":80.4,"low":76.5,"close":79.9,"volume":3206,"ma20":null,"cross_above_ma20":false,"ma20_rising":false,"ma20_distance_pct":null,"capital_billion":1.8,"capital_report_date":"2024-12-31"},{"date":"2025-04-28","open":79.45,"high":80.3,"low":76.1,"close":80.2,"volume":16165,"ma20":null,"cross_above_ma20":false,"ma20_rising":false,"ma20_distance_pct":null,"capital_billion":1.8,"capital_report_date":"2024-12-31"},{"date":"2025-05-05","open":80.2,"high":80.2,"low":73.3,"close":79.1,"volume":16220,"ma20":null,"cross_above_ma20":false,"ma20_rising":false,"ma20_distance_pct":null,"capital_billion":1.8,"capital_report_date":"2024-12-31"},{"date":"2025-05-12","open":79.5,"high":79.6,"low":79.5,"close":79.5,"volume":3301,"ma20":null,"cross_above_ma20":false,"ma20_rising":false,"ma20_distance_pct":null,"capital_billion":1.8,"capital_report_date":"2024-12-31"},{"date":"2025-05-19","open":78.57,"high":79.9,"low":75.8,"close":79.9,"volume":18142,"ma20":null,"cross_above_ma20":false,"ma20_rising":false,"ma20_distance_pct":null,"capital_billion":1.8,"capital_report_date":"2025-03-31"},{"date":"2025-05-26","open":78.03,"high":82.0,"low":76.1,"close":80.0,"volume":33145,"ma20":83.25,"cross_above_ma20":false,"ma20_rising":false,"ma20_distance_pct":-3.9039039039,"capital_billion":1.8,"capital_report_date":"2025-03-31"},{"date":"2025-06-02","open":80.0,"high":80.0,"low":77.0,"close":79.9,"volume":53242,"ma20":82.78,"cross_above_ma20":false,"ma20_rising":false,"ma20_distance_pct":-3.4791012322,"capital_billion":1.8,"capital_report_date":"2025-03-31"},{"date":"2025-06-09","open":79.72,"high":85.2,"low":79.5,"close":83.8,"volume":42956,"ma20":82.78,"cross_above_ma20":true,"ma20_rising":false,"ma20_distance_pct":1.2321816864,"capital_billion":1.8,"capital_report_date":"2025-03-31"},{"date":"2025-06-16","open":84.8,"high":87.9,"low":83.7,"close":86.5,"volume":24819,"ma20":82.49,"cross_above_ma20":false,"ma20_rising":false,"ma20_distance_pct":4.8611952964,"capital_billion":1.8,"capital_report_date":"2025-03-31"},{"date":"2025-06-23","open":98.24,"high":99.8,"low":95.0,"close":98.5,"volume":31565,"ma20":83.07,"cross_above_ma20":false,"ma20_rising":true,"ma20_distance_pct":18.5746960395,"capital_billion":1.8,"capital_report_date":"2025-03-31"},{"date":"2025-06-30","open":103.5,"high":104.0,"low":96.1,"close":99.2,"volume":33963,"ma20":83.565,"cross_above_ma20":false,"ma20_rising":true,"ma20_distance_pct":18.7099862383,"capital_billion":1.8,"capital_report_date":"2025-03-31"},{"date":"2025-07-07","open":96.07,"high":98.1,"low":92.6,"close":97.4,"volume":23255,"ma20":84.09,"cross_above_ma20":false,"ma20_rising":true,"ma20_distance_pct":15.8282792246,"capital_billion":1.8,"capital_report_date":"2025-03-31"},{"date":"2025-07-14","open":100.78,"high":112.5,"low":100.5,"close":107.0,"volume":264820,"ma20":85.12,"cross_above_ma20":false,"ma20_rising":true,"ma20_distance_pct":25.704887218,"capital_billion":1.8,"capital_report_date":"2025-03-31"},{"date":"2025-07-21","open":108.0,"high":110.5,"low":96.2,"close":103.5,"volume":190612,"ma20":86.02,"cross_above_ma20":false,"ma20_rising":true,"ma20_distance_pct":20.320855615,"capital_billion":1.8,"capital_report_date":"2025-03-31"},{"date":"2025-07-28","open":100.76,"high":106.5,"low":100.0,"close":104.0,"volume":91293,"ma20":87.065,"cross_above_ma20":false,"ma20_rising":true,"ma20_distance_pct":19.4509848963,"capital_billion":1.8,"capital_report_date":"2025-03-31"},{"date":"2025-08-04","open":103.86,"high":127.5,"low":102.0,"close":127.0,"volume":333410,"ma20":89.175,"cross_above_ma20":false,"ma20_rising":true,"ma20_distance_pct":42.4165965798,"capital_billion":1.8,"capital_report_date":"2025-03-31"},{"date":"2025-08-11","open":120.61,"high":142.0,"low":119.0,"close":126.5,"volume":416375,"ma20":91.21,"cross_above_ma20":false,"ma20_rising":true,"ma20_distance_pct":38.6909330117,"capital_billion":1.8,"capital_report_date":"2025-03-31"},{"date":"2025-08-18","open":124.67,"high":129.0,"low":122.0,"close":124.5,"volume":53018,"ma20":93.165,"cross_above_ma20":false,"ma20_rising":true,"ma20_distance_pct":33.6338753824,"capital_billion":1.8,"capital_report_date":"2025-06-30"},{"date":"2025-08-25","open":147.0,"high":147.5,"low":133.0,"close":142.0,"volume":216725,"ma20":96.94,"cross_above_ma20":false,"ma20_rising":true,"ma20_distance_pct":46.4823602228,"capital_billion":1.8,"capital_report_date":"2025-06-30"},{"date":"2025-09-01","open":141.16,"high":142.0,"low":133.5,"close":138.0,"volume":65255,"ma20":99.82,"cross_above_ma20":false,"ma20_rising":true,"ma20_distance_pct":38.2488479263,"capital_billion":1.8,"capital_report_date":"2025-06-30"},{"date":"2025-09-08","open":142.79,"high":144.0,"low":132.0,"close":134.5,"volume":301811,"ma20":102.55,"cross_above_ma20":false,"ma20_rising":true,"ma20_distance_pct":31.1555338859,"capital_billion":1.8,"capital_report_date":"2025-06-30"},{"date":"2025-09-15","open":133.11,"high":134.0,"low":124.5,"close":126.0,"volume":162519,"ma20":104.84,"cross_above_ma20":false,"ma20_rising":true,"ma20_distance_pct":20.1831362076,"capital_billion":1.8,"capital_report_date":"2025-06-30"},{"date":"2025-09-22","open":130.66,"high":135.0,"low":128.0,"close":132.0,"volume":120451,"ma20":107.485,"cross_above_ma20":false,"ma20_rising":true,"ma20_distance_pct":22.8078336512,"capital_billion":1.8,"capital_report_date":"2025-06-30"},{"date":"2025-09-29","open":137.48,"high":139.5,"low":134.0,"close":136.0,"volume":68364,"ma20":110.31,"cross_above_ma20":false,"ma20_rising":true,"ma20_distance_pct":23.2889130632,"capital_billion":1.8,"capital_report_date":"2025-06-30"},{"date":"2025-10-06","open":135.51,"high":136.0,"low":134.0,"close":135.0,"volume":42077,"ma20":113.065,"cross_above_ma20":false,"ma20_rising":true,"ma20_distance_pct":19.4003449343,"capital_billion":1.8,"capital_report_date":"2025-06-30"},{"date":"2025-10-13","open":131.64,"high":132.0,"low":130.0,"close":131.5,"volume":1825,"ma20":115.64,"cross_above_ma20":false,"ma20_rising":true,"ma20_distance_pct":13.7149775164,"capital_billion":1.8,"capital_report_date":"2025-06-30"},{"date":"2025-10-20","open":132.41,"high":135.5,"low":132.0,"close":135.5,"volume":87063,"ma20":118.42,"cross_above_ma20":false,"ma20_rising":true,"ma20_distance_pct":14.4232393177,"capital_billion":1.8,"capital_report_date":"2025-06-30"},{"date":"2025-10-27","open":136.13,"high":137.0,"low":134.5,"close":136.5,"volume":105540,"ma20":121.055,"cross_above_ma20":false,"ma20_rising":true,"ma20_distance_pct":12.7586634175,"capital_billion":1.8,"capital_report_date":"2025-06-30"},{"date":"2025-11-03","open":137.76,"high":139.0,"low":134.0,"close":135.5,"volume":90626,"ma20":123.505,"cross_above_ma20":false,"ma20_rising":true,"ma20_distance_pct":9.7121574025,"capital_billion":1.8,"capital_report_date":"2025-06-30"},{"date":"2025-11-10","open":134.2,"high":135.5,"low":131.0,"close":133.0,"volume":29682,"ma20":125.23,"cross_above_ma20":false,"ma20_rising":true,"ma20_distance_pct":6.2045835662,"capital_billion":1.8,"capital_report_date":"2025-06-30"},{"date":"2025-11-17","open":132.24,"high":134.0,"low":131.5,"close":131.5,"volume":29101,"ma20":126.845,"cross_above_ma20":false,"ma20_rising":true,"ma20_distance_pct":3.6698332611,"capital_billion":1.8,"capital_report_date":"2025-09-30"},{"date":"2025-11-24","open":132.62,"high":153.5,"low":131.5,"close":152.0,"volume":91783,"ma20":129.575,"cross_above_ma20":false,"ma20_rising":true,"ma20_distance_pct":17.3065792012,"capital_billion":1.8,"capital_report_date":"2025-09-30"},{"date":"2025-12-01","open":196.6,"high":202.5,"low":181.5,"close":183.0,"volume":178277,"ma20":133.375,"cross_above_ma20":false,"ma20_rising":true,"ma20_distance_pct":37.2071227741,"capital_billion":1.8,"capital_report_date":"2025-09-30"},{"date":"2025-12-08","open":170.81,"high":191.5,"low":162.0,"close":180.0,"volume":263541,"ma20":137.2,"cross_above_ma20":false,"ma20_rising":true,"ma20_distance_pct":31.195335277,"capital_billion":1.8,"capital_report_date":"2025-09-30"},{"date":"2025-12-15","open":172.48,"high":175.5,"low":161.0,"close":163.5,"volume":357538,"ma20":140.175,"cross_above_ma20":false,"ma20_rising":true,"ma20_distance_pct":16.6399143927,"capital_billion":1.8,"capital_report_date":"2025-09-30"},{"date":"2025-12-22","open":163.23,"high":299.0,"low":157.0,"close":288.0,"volume":5562535,"ma20":148.225,"cross_above_ma20":false,"ma20_rising":true,"ma20_distance_pct":94.2992072862,"capital_billion":1.8,"capital_report_date":"2025-09-30"},{"date":"2025-12-29","open":273.0,"high":339.5,"low":273.0,"close":338.0,"volume":4595134,"ma20":158.8,"cross_above_ma20":false,"ma20_rising":true,"ma20_distance_pct":112.8463476071,"capital_billion":1.8,"capital_report_date":"2025-09-30"},{"date":"2026-01-05","open":335.0,"high":335.0,"low":249.0,"close":259.5,"volume":5170776,"ma20":165.55,"cross_above_ma20":false,"ma20_rising":true,"ma20_distance_pct":56.7502265177,"capital_billion":1.8,"capital_report_date":"2025-09-30"},{"date":"2026-01-12","open":273.0,"high":317.5,"low":273.0,"close":280.0,"volume":4683448,"ma20":172.45,"cross_above_ma20":false,"ma20_rising":true,"ma20_distance_pct":62.3659031603,"capital_billion":1.8,"capital_report_date":"2025-09-30"},{"date":"2026-01-19","open":284.0,"high":285.0,"low":240.5,"close":243.0,"volume":1790373,"ma20":177.7,"cross_above_ma20":false,"ma20_rising":true,"ma20_distance_pct":36.7473269555,"capital_billion":1.8,"capital_report_date":"2025-09-30"},{"date":"2026-01-26","open":245.5,"high":263.5,"low":210.5,"close":213.5,"volume":1677818,"ma20":181.65,"cross_above_ma20":false,"ma20_rising":true,"ma20_distance_pct":17.5337186898,"capital_billion":1.8,"capital_report_date":"2025-09-30"},{"date":"2026-02-02","open":213.5,"high":216.0,"low":187.5,"close":195.0,"volume":803329,"ma20":185.1,"cross_above_ma20":false,"ma20_rising":true,"ma20_distance_pct":5.3484602917,"capital_billion":1.8,"capital_report_date":"2025-09-30"},{"date":"2026-02-09","open":206.0,"high":206.0,"low":187.0,"close":188.0,"volume":516551,"ma20":187.9,"cross_above_ma20":false,"ma20_rising":true,"ma20_distance_pct":0.0532197978,"capital_billion":1.8,"capital_report_date":"2025-09-30"},{"date":"2026-02-23","open":194.0,"high":233.5,"low":194.0,"close":227.0,"volume":1636080,"ma20":192.45,"cross_above_ma20":false,"ma20_rising":true,"ma20_distance_pct":17.9527149909,"capital_billion":1.8,"capital_report_date":"2025-09-30"},{"date":"2026-03-02","open":222.0,"high":223.0,"low":181.0,"close":187.5,"volume":888140,"ma20":195.075,"cross_above_ma20":false,"ma20_rising":true,"ma20_distance_pct":-3.8831218762,"capital_billion":1.8,"capital_report_date":"2025-09-30"},{"date":"2026-03-09","open":171.0,"high":204.0,"low":171.0,"close":200.0,"volume":663476,"ma20":198.5,"cross_above_ma20":true,"ma20_rising":true,"ma20_distance_pct":0.7556675063,"capital_billion":1.8,"capital_report_date":"2025-09-30"},{"date":"2026-03-16","open":214.5,"high":225.5,"low":200.5,"close":223.5,"volume":1264765,"ma20":202.9,"cross_above_ma20":false,"ma20_rising":true,"ma20_distance_pct":10.152784623,"capital_billion":1.8,"capital_report_date":"2025-09-30"},{"date":"2026-03-23","open":245.5,"high":286.0,"low":245.5,"close":274.0,"volume":5623726,"ma20":209.775,"cross_above_ma20":false,"ma20_rising":true,"ma20_distance_pct":30.6161363366,"capital_billion":1.8,"capital_report_date":"2025-09-30"},{"date":"2026-03-30","open":267.5,"high":284.0,"low":228.5,"close":232.0,"volume":2062348,"ma20":214.6,"cross_above_ma20":false,"ma20_rising":true,"ma20_distance_pct":8.1081081081,"capital_billion":1.8,"capital_report_date":"2025-09-30"},{"date":"2026-04-06","open":236.0,"high":253.5,"low":232.0,"close":246.0,"volume":941060,"ma20":220.25,"cross_above_ma20":false,"ma20_rising":true,"ma20_distance_pct":11.6912599319,"capital_billion":2.025,"capital_report_date":"2025-12-31"},{"date":"2026-04-13","open":244.0,"high":270.0,"low":239.0,"close":243.5,"volume":1225816,"ma20":225.85,"cross_above_ma20":false,"ma20_rising":true,"ma20_distance_pct":7.814921408,"capital_billion":2.025,"capital_report_date":"2025-12-31"},{"date":"2026-04-20","open":234.0,"high":255.0,"low":212.0,"close":213.5,"volume":1441022,"ma20":228.925,"cross_above_ma20":false,"ma20_rising":true,"ma20_distance_pct":-6.7380146336,"capital_billion":2.025,"capital_report_date":"2025-12-31"},{"date":"2026-04-27","open":222.0,"high":227.0,"low":216.0,"close":218.0,"volume":433620,"ma20":230.675,"cross_above_ma20":false,"ma20_rising":true,"ma20_distance_pct":-5.494743687,"capital_billion":2.025,"capital_report_date":"2025-12-31"},{"date":"2026-05-04","open":224.0,"high":229.0,"low":210.0,"close":212.0,"volume":600412,"ma20":232.275,"cross_above_ma20":false,"ma20_rising":true,"ma20_distance_pct":-8.7288774082,"capital_billion":2.025,"capital_report_date":"2025-12-31"},{"date":"2026-05-11","open":222.5,"high":250.0,"low":222.5,"close":240.5,"volume":1556498,"ma20":236.125,"cross_above_ma20":true,"ma20_rising":true,"ma20_distance_pct":1.8528321863,"capital_billion":2.025,"capital_report_date":"2025-12-31"},{"date":"2026-05-18","open":236.5,"high":259.5,"low":224.0,"close":229.0,"volume":1219117,"ma20":233.175,"cross_above_ma20":false,"ma20_rising":false,"ma20_distance_pct":-1.7905006969,"capital_billion":2.025,"capital_report_date":"2026-03-31"},{"date":"2026-05-25","open":232.5,"high":243.5,"low":225.0,"close":232.0,"volume":900337,"ma20":227.875,"cross_above_ma20":true,"ma20_rising":false,"ma20_distance_pct":1.8102029622,"capital_billion":2.025,"capital_report_date":"2026-03-31"},{"date":"2026-06-01","open":235.5,"high":247.0,"low":225.0,"close":226.5,"volume":861407,"ma20":226.225,"cross_above_ma20":false,"ma20_rising":false,"ma20_distance_pct":0.1215603934,"capital_billion":2.025,"capital_report_date":"2026-03-31"},{"date":"2026-06-08","open":204.0,"high":211.5,"low":196.5,"close":204.5,"volume":636890,"ma20":222.45,"cross_above_ma20":false,"ma20_rising":false,"ma20_distance_pct":-8.0692290402,"capital_billion":2.025,"capital_report_date":"2026-03-31"},{"date":"2026-06-15","open":211.5,"high":215.5,"low":202.5,"close":208.0,"volume":202974,"ma20":220.7,"cross_above_ma20":false,"ma20_rising":false,"ma20_distance_pct":-5.7544177617,"capital_billion":2.025,"capital_report_date":"2026-03-31"},{"date":"2026-06-22","open":210.0,"high":215.5,"low":193.5,"close":193.5,"volume":347945,"ma20":219.7,"cross_above_ma20":false,"ma20_rising":false,"ma20_distance_pct":-11.9253527538,"capital_billion":2.025,"capital_report_date":"2026-03-31"},{"date":"2026-06-29","open":193.5,"high":215.0,"low":193.5,"close":205.0,"volume":252030,"ma20":220.2,"cross_above_ma20":false,"ma20_rising":true,"ma20_distance_pct":-6.9028156222,"capital_billion":2.025,"capital_report_date":"2026-03-31"},{"date":"2026-07-06","open":206.0,"high":213.5,"low":201.0,"close":203.5,"volume":296068,"ma20":220.975,"cross_above_ma20":false,"ma20_rising":true,"ma20_distance_pct":-7.9081344043,"capital_billion":2.025,"capital_report_date":"2026-03-31"},{"date":"2026-07-13","open":208.5,"high":214.0,"low":198.5,"close":202.5,"volume":127515,"ma20":219.75,"cross_above_ma20":false,"ma20_rising":false,"ma20_distance_pct":-7.8498293515,"capital_billion":2.025,"capital_report_date":"2026-03-31"}]